Workbook

Sheet Solicitações
J1: Preenchimento do Coordenador
A2: Projeto | B2: Linha | C2: Aprovado | D2: Ação | E2: Trâmite | F2: Data Pedido | G2: Dígito | H2: Rodada em que foi solicitado o atendimento | I2: Preenchimento da TGCO | J2: Observação do Coordenador | K2: Impactos do não atendimento | L2: Projeto | M2: Atividade | N2: Tarefa | O2: Valor total | P2: Executora | Q2: ND | R2: PACOTE | S2: Para Contrato | T2: Para Motores | U2: Mês previsto
A3: A-29 | B3: 10000 | C3: {=INDEX('MTA 28-09'!B:B,MATCH(B3,'MTA 28-09'!A:A,0))} -> SIM | D3: {=INDEX('MTA 28-09'!D:D,MATCH(B3,'MTA 28-09'!A:A,0))} -> 2048 | E3: {=INDEX('MTA 28-09'!F:F,MATCH(B3,'MTA 28-09'!A:A,0))} -> ATENDIDO | F3: {=INDEX('MTA 28-09'!I:I,MATCH(B3,'MTA 28-09'!A:A,0))} -> 46052 | G3: {=INDEX('MTA 28-09'!J:J,MATCH(B3,'MTA 28-09'!A:A,0))} -> C26059 | H3: 1 | L3: {=INDEX('MTA 28-09'!S:S,MATCH(B3,'MTA 28-09'!A:A,0))} -> A-29 | M3: {=INDEX('MTA 28-09'!T:T,MATCH(B3,'MTA 28-09'!A:A,0))} -> CTT 102/CELOG-PAMALS/2023 – EMBRAER - PSLI | N3: {=INDEX('MTA 28-09'!U:U,MATCH(B3,'MTA 28-09'!A:A,0))} -> Parcela Fixa 01/12 | O3: {=INDEX('MTA 28-09'!AC:AC,MATCH(B3,'MTA 28-09'!A:A,0))} -> 664243.94 | P3: {=INDEX('MTA 28-09'!N:N,MATCH(B3,'MTA 28-09'!A:A,0))} -> CELOG | Q3: {=INDEX('MTA 28-09'!Z:Z,MATCH(B3,'MTA 28-09'!A:A,0))} -> 339039 | R3: {=INDEX('MTA 28-09'!L:L,MATCH(B3,'MTA 28-09'!A:A,0))} -> A | S3: {=INDEX('MTA 28-09'!X:X,MATCH(B3,'MTA 28-09'!A:A,0))} -> PARCELA FIXA | T3: {=INDEX('MTA 28-09'!W:W,MATCH(B3,'MTA 28-09'!A:A,0))} -> Não | U3: {=INDEX('MTA 28-09'!AE:AE,MATCH(B3,'MTA 28-09'!A:A,0))} -> 46107
A4: A-29 | B4: 10001 | C4: {=INDEX('MTA 28-09'!B:B,MATCH(B4,'MTA 28-09'!A:A,0))} -> SIM | D4: {=INDEX('MTA 28-09'!D:D,MATCH(B4,'MTA 28-09'!A:A,0))} -> 2048 | E4: {=INDEX('MTA 28-09'!F:F,MATCH(B4,'MTA 28-09'!A:A,0))} -> ATENDIDO | F4: {=INDEX('MTA 28-09'!I:I,MATCH(B4,'MTA 28-09'!A:A,0))} -> 46052 | G4: {=INDEX('MTA 28-09'!J:J,MATCH(B4,'MTA 28-09'!A:A,0))} -> C26065 | H4: 1 | L4: {=INDEX('MTA 28-09'!S:S,MATCH(B4,'MTA 28-09'!A:A,0))} -> A-29 | M4: {=INDEX('MTA 28-09'!T:T,MATCH(B4,'MTA 28-09'!A:A,0))} -> CTT 102/CELOG-PAMALS/2023 – EMBRAER - PSLI | N4: {=INDEX('MTA 28-09'!U:U,MATCH(B4,'MTA 28-09'!A:A,0))} -> Parcela Fixa 01/12 | O4: {=INDEX('MTA 28-09'!AC:AC,MATCH(B4,'MTA 28-09'!A:A,0))} -> 1645756.1 | P4: {=INDEX('MTA 28-09'!N:N,MATCH(B4,'MTA 28-09'!A:A,0))} -> CELOG | Q4: {=INDEX('MTA 28-09'!Z:Z,MATCH(B4,'MTA 28-09'!A:A,0))} -> 339039 | R4: {=INDEX('MTA 28-09'!L:L,MATCH(B4,'MTA 28-09'!A:A,0))} -> A | S4: {=INDEX('MTA 28-09'!X:X,MATCH(B4,'MTA 28-09'!A:A,0))} -> PARCELA FIXA | T4: {=INDEX('MTA 28-09'!W:W,MATCH(B4,'MTA 28-09'!A:A,0))} -> Não | U4: {=INDEX('MTA 28-09'!AE:AE,MATCH(B4,'MTA 28-09'!A:A,0))} -> 46107
A5: C-97 | B5: 10020 | C5: {=INDEX('MTA 28-09'!B:B,MATCH(B5,'MTA 28-09'!A:A,0))} -> SIM | D5: {=INDEX('MTA 28-09'!D:D,MATCH(B5,'MTA 28-09'!A:A,0))} -> 2048 | E5: {=INDEX('MTA 28-09'!F:F,MATCH(B5,'MTA 28-09'!A:A,0))} -> ATENDIDO | F5: {=INDEX('MTA 28-09'!I:I,MATCH(B5,'MTA 28-09'!A:A,0))} -> 46041 | G5: {=INDEX('MTA 28-09'!J:J,MATCH(B5,'MTA 28-09'!A:A,0))} -> C26050 | H5: 1 | L5: {=INDEX('MTA 28-09'!S:S,MATCH(B5,'MTA 28-09'!A:A,0))} -> C-97 | M5: {=INDEX('MTA 28-09'!T:T,MATCH(B5,'MTA 28-09'!A:A,0))} -> CTT 096/CAE-PAMALS/2021 - CLS C-97 | N5: {=INDEX('MTA 28-09'!U:U,MATCH(B5,'MTA 28-09'!A:A,0))} -> Parcela Fixa 01/12 | O5: {=INDEX('MTA 28-09'!AC:AC,MATCH(B5,'MTA 28-09'!A:A,0))} -> 332718.75 | P5: {=INDEX('MTA 28-09'!N:N,MATCH(B5,'MTA 28-09'!A:A,0))} -> CELOG | Q5: {=INDEX('MTA 28-09'!Z:Z,MATCH(B5,'MTA 28-09'!A:A,0))} -> 339039 | R5: {=INDEX('MTA 28-09'!L:L,MATCH(B5,'MTA 28-09'!A:A,0))} -> A | S5: {=INDEX('MTA 28-09'!X:X,MATCH(B5,'MTA 28-09'!A:A,0))} -> PARCELA FIXA | T5: {=INDEX('MTA 28-09'!W:W,MATCH(B5,'MTA 28-09'!A:A,0))} -> Não | U5: {=INDEX('MTA 28-09'!AE:AE,MATCH(B5,'MTA 28-09'!A:A,0))} -> 46107
A6: C-97 | B6: 10040 | C6: {=INDEX('MTA 28-09'!B:B,MATCH(B6,'MTA 28-09'!A:A,0))} -> SIM | D6: {=INDEX('MTA 28-09'!D:D,MATCH(B6,'MTA 28-09'!A:A,0))} -> 2048 | E6: {=INDEX('MTA 28-09'!F:F,MATCH(B6,'MTA 28-09'!A:A,0))} -> ATENDIDO | F6: {=INDEX('MTA 28-09'!I:I,MATCH(B6,'MTA 28-09'!A:A,0))} -> 46041 | G6: {=INDEX('MTA 28-09'!J:J,MATCH(B6,'MTA 28-09'!A:A,0))} -> C26052 | H6: 1 | L6: {=INDEX('MTA 28-09'!S:S,MATCH(B6,'MTA 28-09'!A:A,0))} -> C-97 | M6: {=INDEX('MTA 28-09'!T:T,MATCH(B6,'MTA 28-09'!A:A,0))} -> CTT 096/CAE-PAMALS/2021 - CLS C-97 | N6: {=INDEX('MTA 28-09'!U:U,MATCH(B6,'MTA 28-09'!A:A,0))} -> Hora de Voo 2025 (520HV voadas a mais) | O6: {=INDEX('MTA 28-09'!AC:AC,MATCH(B6,'MTA 28-09'!A:A,0))} -> 581400 | P6: {=INDEX('MTA 28-09'!N:N,MATCH(B6,'MTA 28-09'!A:A,0))} -> CELOG | Q6: {=INDEX('MTA 28-09'!Z:Z,MATCH(B6,'MTA 28-09'!A:A,0))} -> 339039 | R6: {=INDEX('MTA 28-09'!L:L,MATCH(B6,'MTA 28-09'!A:A,0))} -> A | S6: {=INDEX('MTA 28-09'!X:X,MATCH(B6,'MTA 28-09'!A:A,0))} -> HORA DE VOO | T6: {=INDEX('MTA 28-09'!W:W,MATCH(B6,'MTA 28-09'!A:A,0))} -> Não | U6: {=INDEX('MTA 28-09'!AE:AE,MATCH(B6,'MTA 28-09'!A:A,0))} -> 46107
A7: C-97 | B7: 10060 | C7: {=INDEX('MTA 28-09'!B:B,MATCH(B7,'MTA 28-09'!A:A,0))} -> SIM | D7: {=INDEX('MTA 28-09'!D:D,MATCH(B7,'MTA 28-09'!A:A,0))} -> 2048 | E7: {=INDEX('MTA 28-09'!F:F,MATCH(B7,'MTA 28-09'!A:A,0))} -> ATENDIDO | F7: {=INDEX('MTA 28-09'!I:I,MATCH(B7,'MTA 28-09'!A:A,0))} -> 46055 | G7: {=INDEX('MTA 28-09'!J:J,MATCH(B7,'MTA 28-09'!A:A,0))} -> C26070 | H7: 1 | L7: {=INDEX('MTA 28-09'!S:S,MATCH(B7,'MTA 28-09'!A:A,0))} -> C-97 | M7: {=INDEX('MTA 28-09'!T:T,MATCH(B7,'MTA 28-09'!A:A,0))} -> CTT 096/CAE-PAMALS/2021 - CLS C-97 | N7: {=INDEX('MTA 28-09'!U:U,MATCH(B7,'MTA 28-09'!A:A,0))} -> Hora de Voo 01/09 (500HV) | O7: {=INDEX('MTA 28-09'!AC:AC,MATCH(B7,'MTA 28-09'!A:A,0))} -> 2182993 | P7: {=INDEX('MTA 28-09'!N:N,MATCH(B7,'MTA 28-09'!A:A,0))} -> CELOG | Q7: {=INDEX('MTA 28-09'!Z:Z,MATCH(B7,'MTA 28-09'!A:A,0))} -> 339039 | R7: {=INDEX('MTA 28-09'!L:L,MATCH(B7,'MTA 28-09'!A:A,0))} -> A | S7: {=INDEX('MTA 28-09'!X:X,MATCH(B7,'MTA 28-09'!A:A,0))} -> HORA DE VOO | T7: {=INDEX('MTA 28-09'!W:W,MATCH(B7,'MTA 28-09'!A:A,0))} -> Não | U7: {=INDEX('MTA 28-09'!AE:AE,MATCH(B7,'MTA 28-09'!A:A,0))} -> 46107
A8: C-97 | B8: 10061 | C8: {=INDEX('MTA 28-09'!B:B,MATCH(B8,'MTA 28-09'!A:A,0))} -> SIM | D8: {=INDEX('MTA 28-09'!D:D,MATCH(B8,'MTA 28-09'!A:A,0))} -> 2048 | E8: {=INDEX('MTA 28-09'!F:F,MATCH(B8,'MTA 28-09'!A:A,0))} -> ATENDIDO | F8: {=INDEX('MTA 28-09'!I:I,MATCH(B8,'MTA 28-09'!A:A,0))} -> 46057 | G8: {=INDEX('MTA 28-09'!J:J,MATCH(B8,'MTA 28-09'!A:A,0))} -> C26079 | H8: 1 | L8: {=INDEX('MTA 28-09'!S:S,MATCH(B8,'MTA 28-09'!A:A,0))} -> C-97 | M8: {=INDEX('MTA 28-09'!T:T,MATCH(B8,'MTA 28-09'!A:A,0))} -> CTT 096/CAE-PAMALS/2021 - CLS C-97 | N8: {=INDEX('MTA 28-09'!U:U,MATCH(B8,'MTA 28-09'!A:A,0))} -> Hora de Voo 01/09 (500HV) | O8: {=INDEX('MTA 28-09'!AC:AC,MATCH(B8,'MTA 28-09'!A:A,0))} -> 221702.86 | P8: {=INDEX('MTA 28-09'!N:N,MATCH(B8,'MTA 28-09'!A:A,0))} -> CELOG | Q8: {=INDEX('MTA 28-09'!Z:Z,MATCH(B8,'MTA 28-09'!A:A,0))} -> 339039 | R8: {=INDEX('MTA 28-09'!L:L,MATCH(B8,'MTA 28-09'!A:A,0))} -> A | S8: {=INDEX('MTA 28-09'!X:X,MATCH(B8,'MTA 28-09'!A:A,0))} -> HORA DE VOO | T8: {=INDEX('MTA 28-09'!W:W,MATCH(B8,'MTA 28-09'!A:A,0))} -> Não | U8: {=INDEX('MTA 28-09'!AE:AE,MATCH(B8,'MTA 28-09'!A:A,0))} -> 46107
A9: C-97 | B9: 10062 | C9: {=INDEX('MTA 28-09'!B:B,MATCH(B9,'MTA 28-09'!A:A,0))} -> SIM | D9: {=INDEX('MTA 28-09'!D:D,MATCH(B9,'MTA 28-09'!A:A,0))} -> 2048 | E9: {=INDEX('MTA 28-09'!F:F,MATCH(B9,'MTA 28-09'!A:A,0))} -> ATENDIDO | F9: {=INDEX('MTA 28-09'!I:I,MATCH(B9,'MTA 28-09'!A:A,0))} -> 46055 | G9: {=INDEX('MTA 28-09'!J:J,MATCH(B9,'MTA 28-09'!A:A,0))} -> C26070 | H9: 1 | L9: {=INDEX('MTA 28-09'!S:S,MATCH(B9,'MTA 28-09'!A:A,0))} -> C-97 | M9: {=INDEX('MTA 28-09'!T:T,MATCH(B9,'MTA 28-09'!A:A,0))} -> CTT 096/CAE-PAMALS/2021 - CLS C-97 | N9: {=INDEX('MTA 28-09'!U:U,MATCH(B9,'MTA 28-09'!A:A,0))} -> Hora de Voo 01/09 (500HV) | O9: {=INDEX('MTA 28-09'!AC:AC,MATCH(B9,'MTA 28-09'!A:A,0))} -> 167804.17 | P9: {=INDEX('MTA 28-09'!N:N,MATCH(B9,'MTA 28-09'!A:A,0))} -> CELOG | Q9: {=INDEX('MTA 28-09'!Z:Z,MATCH(B9,'MTA 28-09'!A:A,0))} -> 339039 | R9: {=INDEX('MTA 28-09'!L:L,MATCH(B9,'MTA 28-09'!A:A,0))} -> A | S9: {=INDEX('MTA 28-09'!X:X,MATCH(B9,'MTA 28-09'!A:A,0))} -> HORA DE VOO | T9: {=INDEX('MTA 28-09'!W:W,MATCH(B9,'MTA 28-09'!A:A,0))} -> Não | U9: {=INDEX('MTA 28-09'!AE:AE,MATCH(B9,'MTA 28-09'!A:A,0))} -> 46107
A10: T-25 | B10: 10080 | C10: {=INDEX('MTA 28-09'!B:B,MATCH(B10,'MTA 28-09'!A:A,0))} -> SIM | D10: {=INDEX('MTA 28-09'!D:D,MATCH(B10,'MTA 28-09'!A:A,0))} -> 2048 | E10: {=INDEX('MTA 28-09'!F:F,MATCH(B10,'MTA 28-09'!A:A,0))} | F10: {=INDEX('MTA 28-09'!I:I,MATCH(B10,'MTA 28-09'!A:A,0))} | G10: {=INDEX('MTA 28-09'!J:J,MATCH(B10,'MTA 28-09'!A:A,0))} | H10: 46276 | I10: Atender | J10: LIVRE | L10: {=INDEX('MTA 28-09'!S:S,MATCH(B10,'MTA 28-09'!A:A,0))} -> T-25 | M10: {=INDEX('MTA 28-09'!T:T,MATCH(B10,'MTA 28-09'!A:A,0))} -> Requisição CABW | N10: {=INDEX('MTA 28-09'!U:U,MATCH(B10,'MTA 28-09'!A:A,0))} -> Requisição Consumíveis | O10: {=INDEX('MTA 28-09'!AC:AC,MATCH(B10,'MTA 28-09'!A:A,0))} -> 374409.15 | P10: {=INDEX('MTA 28-09'!N:N,MATCH(B10,'MTA 28-09'!A:A,0))} -> CABW | Q10: {=INDEX('MTA 28-09'!Z:Z,MATCH(B10,'MTA 28-09'!A:A,0))} -> 339030 | R10: {=INDEX('MTA 28-09'!L:L,MATCH(B10,'MTA 28-09'!A:A,0))} -> A | S10: {=INDEX('MTA 28-09'!X:X,MATCH(B10,'MTA 28-09'!A:A,0))} -> REQUISIÇÃO | T10: {=INDEX('MTA 28-09'!W:W,MATCH(B10,'MTA 28-09'!A:A,0))} -> Não | U10: {=INDEX('MTA 28-09'!AE:AE,MATCH(B10,'MTA 28-09'!A:A,0))} -> 46291
A11: T-25 | B11: 10081 | C11: {=INDEX('MTA 28-09'!B:B,MATCH(B11,'MTA 28-09'!A:A,0))} -> SIM | D11: {=INDEX('MTA 28-09'!D:D,MATCH(B11,'MTA 28-09'!A:A,0))} -> 2048 | E11: {=INDEX('MTA 28-09'!F:F,MATCH(B11,'MTA 28-09'!A:A,0))} -> ATENDIDO | F11: {=INDEX('MTA 28-09'!I:I,MATCH(B11,'MTA 28-09'!A:A,0))} -> 46098 | G11: {=INDEX('MTA 28-09'!J:J,MATCH(B11,'MTA 28-09'!A:A,0))} -> C26063 | H11: email do dia 11/03 | L11: {=INDEX('MTA 28-09'!S:S,MATCH(B11,'MTA 28-09'!A:A,0))} -> T-25 | M11: {=INDEX('MTA 28-09'!T:T,MATCH(B11,'MTA 28-09'!A:A,0))} -> Requisição CABW | N11: {=INDEX('MTA 28-09'!U:U,MATCH(B11,'MTA 28-09'!A:A,0))} -> Atualização de GPS | O11: {=INDEX('MTA 28-09'!AC:AC,MATCH(B11,'MTA 28-09'!A:A,0))} -> 260590.85 | P11: {=INDEX('MTA 28-09'!N:N,MATCH(B11,'MTA 28-09'!A:A,0))} -> CABW | Q11: {=INDEX('MTA 28-09'!Z:Z,MATCH(B11,'MTA 28-09'!A:A,0))} -> 339039 | R11: {=INDEX('MTA 28-09'!L:L,MATCH(B11,'MTA 28-09'!A:A,0))} -> A | S11: {=INDEX('MTA 28-09'!X:X,MATCH(B11,'MTA 28-09'!A:A,0))} -> REQUISIÇÃO | T11: {=INDEX('MTA 28-09'!W:W,MATCH(B11,'MTA 28-09'!A:A,0))} -> Não | U11: {=INDEX('MTA 28-09'!AE:AE,MATCH(B11,'MTA 28-09'!A:A,0))} -> 46107
A12: T-25 | B12: 10100 | C12: {=INDEX('MTA 28-09'!B:B,MATCH(B12,'MTA 28-09'!A:A,0))} -> SIM | D12: {=INDEX('MTA 28-09'!D:D,MATCH(B12,'MTA 28-09'!A:A,0))} -> 2048 | E12: {=INDEX('MTA 28-09'!F:F,MATCH(B12,'MTA 28-09'!A:A,0))} | F12: {=INDEX('MTA 28-09'!I:I,MATCH(B12,'MTA 28-09'!A:A,0))} | G12: {=INDEX('MTA 28-09'!J:J,MATCH(B12,'MTA 28-09'!A:A,0))} | H12: 46276 | I12: Atender | J12: MOTOR | L12: {=INDEX('MTA 28-09'!S:S,MATCH(B12,'MTA 28-09'!A:A,0))} -> T-25 | M12: {=INDEX('MTA 28-09'!T:T,MATCH(B12,'MTA 28-09'!A:A,0))} -> Requisição CABW | N12: {=INDEX('MTA 28-09'!U:U,MATCH(B12,'MTA 28-09'!A:A,0))} -> Requisição Consumíveis | O12: {=INDEX('MTA 28-09'!AC:AC,MATCH(B12,'MTA 28-09'!A:A,0))} -> 10000 | P12: {=INDEX('MTA 28-09'!N:N,MATCH(B12,'MTA 28-09'!A:A,0))} -> CABW | Q12: {=INDEX('MTA 28-09'!Z:Z,MATCH(B12,'MTA 28-09'!A:A,0))} -> 339030 | R12: {=INDEX('MTA 28-09'!L:L,MATCH(B12,'MTA 28-09'!A:A,0))} -> A | S12: {=INDEX('MTA 28-09'!X:X,MATCH(B12,'MTA 28-09'!A:A,0))} -> REQUISIÇÃO | T12: {=INDEX('MTA 28-09'!W:W,MATCH(B12,'MTA 28-09'!A:A,0))} -> Não | U12: {=INDEX('MTA 28-09'!AE:AE,MATCH(B12,'MTA 28-09'!A:A,0))} -> 46352
A13: T-27 | B13: 10120 | C13: {=INDEX('MTA 28-09'!B:B,MATCH(B13,'MTA 28-09'!A:A,0))} -> SIM | D13: {=INDEX('MTA 28-09'!D:D,MATCH(B13,'MTA 28-09'!A:A,0))} -> 2048 | E13: {=INDEX('MTA 28-09'!F:F,MATCH(B13,'MTA 28-09'!A:A,0))} | F13: {=INDEX('MTA 28-09'!I:I,MATCH(B13,'MTA 28-09'!A:A,0))} | G13: {=INDEX('MTA 28-09'!J:J,MATCH(B13,'MTA 28-09'!A:A,0))} | H13: 46276 | I13: REMANEJAR ATENDER $ 2.000,00 E MUDAR PARA ATUALIZAR GPS PJT A-29. Remanejar R$ 130.000,00 para o ctt 048 Willian | J13: LIVRE | L13: {=INDEX('MTA 28-09'!S:S,MATCH(B13,'MTA 28-09'!A:A,0))} -> T-27 | M13: {=INDEX('MTA 28-09'!T:T,MATCH(B13,'MTA 28-09'!A:A,0))} -> Requisição CABW | N13: {=INDEX('MTA 28-09'!U:U,MATCH(B13,'MTA 28-09'!A:A,0))} -> Atualização de GPS | O13: {=INDEX('MTA 28-09'!AC:AC,MATCH(B13,'MTA 28-09'!A:A,0))} -> 391353.59 | P13: {=INDEX('MTA 28-09'!N:N,MATCH(B13,'MTA 28-09'!A:A,0))} -> CABW | Q13: {=INDEX('MTA 28-09'!Z:Z,MATCH(B13,'MTA 28-09'!A:A,0))} -> 339039 | R13: {=INDEX('MTA 28-09'!L:L,MATCH(B13,'MTA 28-09'!A:A,0))} -> A | S13: {=INDEX('MTA 28-09'!X:X,MATCH(B13,'MTA 28-09'!A:A,0))} -> REQUISIÇÃO | T13: {=INDEX('MTA 28-09'!W:W,MATCH(B13,'MTA 28-09'!A:A,0))} -> Não | U13: {=INDEX('MTA 28-09'!AE:AE,MATCH(B13,'MTA 28-09'!A:A,0))} -> 46291
A14: T-27 | B14: 10121 | C14: {=INDEX('MTA 28-09'!B:B,MATCH(B14,'MTA 28-09'!A:A,0))} -> SIM | D14: {=INDEX('MTA 28-09'!D:D,MATCH(B14,'MTA 28-09'!A:A,0))} -> 2048 | E14: {=INDEX('MTA 28-09'!F:F,MATCH(B14,'MTA 28-09'!A:A,0))} -> ATENDIDO | F14: {=INDEX('MTA 28-09'!I:I,MATCH(B14,'MTA 28-09'!A:A,0))} -> 46098 | G14: {=INDEX('MTA 28-09'!J:J,MATCH(B14,'MTA 28-09'!A:A,0))} -> C26060 | H14: email do dia 11/03 | L14: {=INDEX('MTA 28-09'!S:S,MATCH(B14,'MTA 28-09'!A:A,0))} -> T-27 | M14: {=INDEX('MTA 28-09'!T:T,MATCH(B14,'MTA 28-09'!A:A,0))} -> Requisição CABW | N14: {=INDEX('MTA 28-09'!U:U,MATCH(B14,'MTA 28-09'!A:A,0))} -> Atualização de GPS | O14: {=INDEX('MTA 28-09'!AC:AC,MATCH(B14,'MTA 28-09'!A:A,0))} -> 245262 | P14: {=INDEX('MTA 28-09'!N:N,MATCH(B14,'MTA 28-09'!A:A,0))} -> CABW | Q14: {=INDEX('MTA 28-09'!Z:Z,MATCH(B14,'MTA 28-09'!A:A,0))} -> 339039 | R14: {=INDEX('MTA 28-09'!L:L,MATCH(B14,'MTA 28-09'!A:A,0))} -> A | S14: {=INDEX('MTA 28-09'!X:X,MATCH(B14,'MTA 28-09'!A:A,0))} -> REQUISIÇÃO | T14: {=INDEX('MTA 28-09'!W:W,MATCH(B14,'MTA 28-09'!A:A,0))} -> Não | U14: {=INDEX('MTA 28-09'!AE:AE,MATCH(B14,'MTA 28-09'!A:A,0))} -> 46107
A15: T-27 | B15: 10122 | C15: {=INDEX('MTA 28-09'!B:B,MATCH(B15,'MTA 28-09'!A:A,0))} -> SIM | D15: {=INDEX('MTA 28-09'!D:D,MATCH(B15,'MTA 28-09'!A:A,0))} -> 2048 | E15: {=INDEX('MTA 28-09'!F:F,MATCH(B15,'MTA 28-09'!A:A,0))} -> ATENDIDO | F15: {=INDEX('MTA 28-09'!I:I,MATCH(B15,'MTA 28-09'!A:A,0))} -> 46098 | G15: {=INDEX('MTA 28-09'!J:J,MATCH(B15,'MTA 28-09'!A:A,0))} -> C26153 | H15: email do dia 11/03 | L15: {=INDEX('MTA 28-09'!S:S,MATCH(B15,'MTA 28-09'!A:A,0))} -> T-27 | M15: {=INDEX('MTA 28-09'!T:T,MATCH(B15,'MTA 28-09'!A:A,0))} -> Contrato inexigibilidade EMBRAER | N15: {=INDEX('MTA 28-09'!U:U,MATCH(B15,'MTA 28-09'!A:A,0))} -> Publicação | O15: {=INDEX('MTA 28-09'!AC:AC,MATCH(B15,'MTA 28-09'!A:A,0))} -> 91984.41 | P15: {=INDEX('MTA 28-09'!N:N,MATCH(B15,'MTA 28-09'!A:A,0))} -> CELOG | Q15: {=INDEX('MTA 28-09'!Z:Z,MATCH(B15,'MTA 28-09'!A:A,0))} -> 339039 | R15: {=INDEX('MTA 28-09'!L:L,MATCH(B15,'MTA 28-09'!A:A,0))} -> A | S15: {=INDEX('MTA 28-09'!X:X,MATCH(B15,'MTA 28-09'!A:A,0))} -> REQUISIÇÃO | T15: {=INDEX('MTA 28-09'!W:W,MATCH(B15,'MTA 28-09'!A:A,0))} -> Não | U15: {=INDEX('MTA 28-09'!AE:AE,MATCH(B15,'MTA 28-09'!A:A,0))} -> 46107
A16: T-27 | B16: 10140 | C16: {=INDEX('MTA 28-09'!B:B,MATCH(B16,'MTA 28-09'!A:A,0))} -> SIM | D16: {=INDEX('MTA 28-09'!D:D,MATCH(B16,'MTA 28-09'!A:A,0))} -> 2048 | E16: {=INDEX('MTA 28-09'!F:F,MATCH(B16,'MTA 28-09'!A:A,0))} -> ATENDIDO | F16: {=INDEX('MTA 28-09'!I:I,MATCH(B16,'MTA 28-09'!A:A,0))} -> 46192 | G16: {=INDEX('MTA 28-09'!J:J,MATCH(B16,'MTA 28-09'!A:A,0))} -> C26038 | L16: {=INDEX('MTA 28-09'!S:S,MATCH(B16,'MTA 28-09'!A:A,0))} -> T-27 | M16: {=INDEX('MTA 28-09'!T:T,MATCH(B16,'MTA 28-09'!A:A,0))} -> REQUISIÇÃO SERVIÇO | N16: {=INDEX('MTA 28-09'!U:U,MATCH(B16,'MTA 28-09'!A:A,0))} -> RG Controlador de Torque 3 EA (1/2) | O16: {=INDEX('MTA 28-09'!AC:AC,MATCH(B16,'MTA 28-09'!A:A,0))} -> 60000 | P16: {=INDEX('MTA 28-09'!N:N,MATCH(B16,'MTA 28-09'!A:A,0))} -> CABW | Q16: {=INDEX('MTA 28-09'!Z:Z,MATCH(B16,'MTA 28-09'!A:A,0))} -> 339039 | R16: {=INDEX('MTA 28-09'!L:L,MATCH(B16,'MTA 28-09'!A:A,0))} -> A | S16: {=INDEX('MTA 28-09'!X:X,MATCH(B16,'MTA 28-09'!A:A,0))} -> REQUISIÇÃO | T16: {=INDEX('MTA 28-09'!W:W,MATCH(B16,'MTA 28-09'!A:A,0))} -> SIM | U16: {=INDEX('MTA 28-09'!AE:AE,MATCH(B16,'MTA 28-09'!A:A,0))} -> 46229
A17: A-29 | B17: 10160 | C17: {=INDEX('MTA 28-09'!B:B,MATCH(B17,'MTA 28-09'!A:A,0))} -> SIM | D17: {=INDEX('MTA 28-09'!D:D,MATCH(B17,'MTA 28-09'!A:A,0))} -> 2048 | E17: {=INDEX('MTA 28-09'!F:F,MATCH(B17,'MTA 28-09'!A:A,0))} -> ATENDIDO | F17: {=INDEX('MTA 28-09'!I:I,MATCH(B17,'MTA 28-09'!A:A,0))} -> 46098 | G17: {=INDEX('MTA 28-09'!J:J,MATCH(B17,'MTA 28-09'!A:A,0))} -> C26173 | H17: email do dia 11/03 | L17: {=INDEX('MTA 28-09'!S:S,MATCH(B17,'MTA 28-09'!A:A,0))} -> A-29 | M17: {=INDEX('MTA 28-09'!T:T,MATCH(B17,'MTA 28-09'!A:A,0))} -> Contrato inexigibilidade EMBRAER - CNT 012/CELOG-PAMALS/2026 | N17: {=INDEX('MTA 28-09'!U:U,MATCH(B17,'MTA 28-09'!A:A,0))} -> Publicação | O17: {=INDEX('MTA 28-09'!AC:AC,MATCH(B17,'MTA 28-09'!A:A,0))} -> 1624451.9 | P17: {=INDEX('MTA 28-09'!N:N,MATCH(B17,'MTA 28-09'!A:A,0))} -> CELOG | Q17: {=INDEX('MTA 28-09'!Z:Z,MATCH(B17,'MTA 28-09'!A:A,0))} -> 339039 | R17: {=INDEX('MTA 28-09'!L:L,MATCH(B17,'MTA 28-09'!A:A,0))} -> A | S17: {=INDEX('MTA 28-09'!X:X,MATCH(B17,'MTA 28-09'!A:A,0))} -> REQUISIÇÃO | T17: {=INDEX('MTA 28-09'!W:W,MATCH(B17,'MTA 28-09'!A:A,0))} -> Não | U17: {=INDEX('MTA 28-09'!AE:AE,MATCH(B17,'MTA 28-09'!A:A,0))} -> 46107
A18: A-29 | B18: 10180 | C18: {=INDEX('MTA 28-09'!B:B,MATCH(B18,'MTA 28-09'!A:A,0))} -> SIM | D18: {=INDEX('MTA 28-09'!D:D,MATCH(B18,'MTA 28-09'!A:A,0))} -> 2048 | E18: {=INDEX('MTA 28-09'!F:F,MATCH(B18,'MTA 28-09'!A:A,0))} -> ATENDIDO | F18: {=INDEX('MTA 28-09'!I:I,MATCH(B18,'MTA 28-09'!A:A,0))} -> 46041 | G18: {=INDEX('MTA 28-09'!J:J,MATCH(B18,'MTA 28-09'!A:A,0))} -> C26051 | H18: 1 | L18: {=INDEX('MTA 28-09'!S:S,MATCH(B18,'MTA 28-09'!A:A,0))} -> A-29 | M18: {=INDEX('MTA 28-09'!T:T,MATCH(B18,'MTA 28-09'!A:A,0))} -> CNT 060/CELOG-PAMASP/2023 - PW - HSI/REPARO | N18: {=INDEX('MTA 28-09'!U:U,MATCH(B18,'MTA 28-09'!A:A,0))} -> HSI PT6A-68C 1/4 | O18: {=INDEX('MTA 28-09'!AC:AC,MATCH(B18,'MTA 28-09'!A:A,0))} -> 2500000 | P18: {=INDEX('MTA 28-09'!N:N,MATCH(B18,'MTA 28-09'!A:A,0))} -> CELOG | Q18: {=INDEX('MTA 28-09'!Z:Z,MATCH(B18,'MTA 28-09'!A:A,0))} -> 339039 | R18: {=INDEX('MTA 28-09'!L:L,MATCH(B18,'MTA 28-09'!A:A,0))} -> A | S18: {=INDEX('MTA 28-09'!X:X,MATCH(B18,'MTA 28-09'!A:A,0))} -> SOB DEMANDA | T18: {=INDEX('MTA 28-09'!W:W,MATCH(B18,'MTA 28-09'!A:A,0))} -> SIM | U18: {=INDEX('MTA 28-09'!AE:AE,MATCH(B18,'MTA 28-09'!A:A,0))} -> 46079
A19: A-29 | B19: 10200 | C19: {=INDEX('MTA 28-09'!B:B,MATCH(B19,'MTA 28-09'!A:A,0))} -> SIM | D19: {=INDEX('MTA 28-09'!D:D,MATCH(B19,'MTA 28-09'!A:A,0))} -> 2048 | E19: {=INDEX('MTA 28-09'!F:F,MATCH(B19,'MTA 28-09'!A:A,0))} -> ATENDIDO | F19: {=INDEX('MTA 28-09'!I:I,MATCH(B19,'MTA 28-09'!A:A,0))} -> 46057 | G19: {=INDEX('MTA 28-09'!J:J,MATCH(B19,'MTA 28-09'!A:A,0))} -> C26078 | H19: 1 | L19: {=INDEX('MTA 28-09'!S:S,MATCH(B19,'MTA 28-09'!A:A,0))} -> A-29 | M19: {=INDEX('MTA 28-09'!T:T,MATCH(B19,'MTA 28-09'!A:A,0))} -> CTT 004/CELOG-PAMASP/2025 - PW - AQ. PEÇAS | N19: {=INDEX('MTA 28-09'!U:U,MATCH(B19,'MTA 28-09'!A:A,0))} -> Material para PT6A-68C 1/3 | O19: {=INDEX('MTA 28-09'!AC:AC,MATCH(B19,'MTA 28-09'!A:A,0))} -> 1830599 | P19: {=INDEX('MTA 28-09'!N:N,MATCH(B19,'MTA 28-09'!A:A,0))} -> CELOG | Q19: {=INDEX('MTA 28-09'!Z:Z,MATCH(B19,'MTA 28-09'!A:A,0))} -> 339030 | R19: {=INDEX('MTA 28-09'!L:L,MATCH(B19,'MTA 28-09'!A:A,0))} -> A | S19: {=INDEX('MTA 28-09'!X:X,MATCH(B19,'MTA 28-09'!A:A,0))} -> SOB DEMANDA | T19: {=INDEX('MTA 28-09'!W:W,MATCH(B19,'MTA 28-09'!A:A,0))} -> SIM | U19: {=INDEX('MTA 28-09'!AE:AE,MATCH(B19,'MTA 28-09'!A:A,0))} -> 46079
A20: A-29 | B20: 10201 | C20: {=INDEX('MTA 28-09'!B:B,MATCH(B20,'MTA 28-09'!A:A,0))} -> SIM | D20: {=INDEX('MTA 28-09'!D:D,MATCH(B20,'MTA 28-09'!A:A,0))} -> 2048 | E20: {=INDEX('MTA 28-09'!F:F,MATCH(B20,'MTA 28-09'!A:A,0))} -> ATENDIDO | F20: {=INDEX('MTA 28-09'!I:I,MATCH(B20,'MTA 28-09'!A:A,0))} -> 46052 | G20: {=INDEX('MTA 28-09'!J:J,MATCH(B20,'MTA 28-09'!A:A,0))} -> C26066 | H20: 1 | L20: {=INDEX('MTA 28-09'!S:S,MATCH(B20,'MTA 28-09'!A:A,0))} -> A-29 | M20: {=INDEX('MTA 28-09'!T:T,MATCH(B20,'MTA 28-09'!A:A,0))} -> CTT 004/CELOG-PAMASP/2025 - PW - AQ. PEÇAS | N20: {=INDEX('MTA 28-09'!U:U,MATCH(B20,'MTA 28-09'!A:A,0))} -> Material para PT6A-68C 1/3 | O20: {=INDEX('MTA 28-09'!AC:AC,MATCH(B20,'MTA 28-09'!A:A,0))} -> 1169401 | P20: {=INDEX('MTA 28-09'!N:N,MATCH(B20,'MTA 28-09'!A:A,0))} -> CELOG | Q20: {=INDEX('MTA 28-09'!Z:Z,MATCH(B20,'MTA 28-09'!A:A,0))} -> 339030 | R20: {=INDEX('MTA 28-09'!L:L,MATCH(B20,'MTA 28-09'!A:A,0))} -> A | S20: {=INDEX('MTA 28-09'!X:X,MATCH(B20,'MTA 28-09'!A:A,0))} -> SOB DEMANDA | T20: {=INDEX('MTA 28-09'!W:W,MATCH(B20,'MTA 28-09'!A:A,0))} -> SIM | U20: {=INDEX('MTA 28-09'!AE:AE,MATCH(B20,'MTA 28-09'!A:A,0))} -> 46079
A21: C-95M | B21: 10220 | C21: {=INDEX('MTA 28-09'!B:B,MATCH(B21,'MTA 28-09'!A:A,0))} -> SIM | D21: {=INDEX('MTA 28-09'!D:D,MATCH(B21,'MTA 28-09'!A:A,0))} -> 2048 | E21: {=INDEX('MTA 28-09'!F:F,MATCH(B21,'MTA 28-09'!A:A,0))} | F21: {=INDEX('MTA 28-09'!I:I,MATCH(B21,'MTA 28-09'!A:A,0))} | G21: {=INDEX('MTA 28-09'!J:J,MATCH(B21,'MTA 28-09'!A:A,0))} | H21: 46276 | I21: Atender | J21: LIVRE | L21: {=INDEX('MTA 28-09'!S:S,MATCH(B21,'MTA 28-09'!A:A,0))} -> C-95M | M21: {=INDEX('MTA 28-09'!T:T,MATCH(B21,'MTA 28-09'!A:A,0))} -> Requisição CABW | N21: {=INDEX('MTA 28-09'!U:U,MATCH(B21,'MTA 28-09'!A:A,0))} -> Requisição de Consumíveis | O21: {=INDEX('MTA 28-09'!AC:AC,MATCH(B21,'MTA 28-09'!A:A,0))} -> 149138.2 | P21: {=INDEX('MTA 28-09'!N:N,MATCH(B21,'MTA 28-09'!A:A,0))} -> CABW | Q21: {=INDEX('MTA 28-09'!Z:Z,MATCH(B21,'MTA 28-09'!A:A,0))} -> 339030 | R21: {=INDEX('MTA 28-09'!L:L,MATCH(B21,'MTA 28-09'!A:A,0))} -> A | S21: {=INDEX('MTA 28-09'!X:X,MATCH(B21,'MTA 28-09'!A:A,0))} -> REQUISIÇÃO | T21: {=INDEX('MTA 28-09'!W:W,MATCH(B21,'MTA 28-09'!A:A,0))} -> Não | U21: {=INDEX('MTA 28-09'!AE:AE,MATCH(B21,'MTA 28-09'!A:A,0))} -> 46291
A22: C-95M | B22: 10221 | C22: {=INDEX('MTA 28-09'!B:B,MATCH(B22,'MTA 28-09'!A:A,0))} -> SIM | D22: {=INDEX('MTA 28-09'!D:D,MATCH(B22,'MTA 28-09'!A:A,0))} -> 20XV | E22: {=INDEX('MTA 28-09'!F:F,MATCH(B22,'MTA 28-09'!A:A,0))} -> ATENDIDO | F22: {=INDEX('MTA 28-09'!I:I,MATCH(B22,'MTA 28-09'!A:A,0))} -> 46098 | G22: {=INDEX('MTA 28-09'!J:J,MATCH(B22,'MTA 28-09'!A:A,0))} -> C26062 | H22: email do dia 11/03 | L22: {=INDEX('MTA 28-09'!S:S,MATCH(B22,'MTA 28-09'!A:A,0))} -> C-95M | M22: {=INDEX('MTA 28-09'!T:T,MATCH(B22,'MTA 28-09'!A:A,0))} -> Requisição CABW | N22: {=INDEX('MTA 28-09'!U:U,MATCH(B22,'MTA 28-09'!A:A,0))} -> Atualização de GPS | O22: {=INDEX('MTA 28-09'!AC:AC,MATCH(B22,'MTA 28-09'!A:A,0))} -> 150861.8 | P22: {=INDEX('MTA 28-09'!N:N,MATCH(B22,'MTA 28-09'!A:A,0))} -> CABW | Q22: {=INDEX('MTA 28-09'!Z:Z,MATCH(B22,'MTA 28-09'!A:A,0))} -> 339039 | R22: {=INDEX('MTA 28-09'!L:L,MATCH(B22,'MTA 28-09'!A:A,0))} -> A | S22: {=INDEX('MTA 28-09'!X:X,MATCH(B22,'MTA 28-09'!A:A,0))} -> REQUISIÇÃO | T22: {=INDEX('MTA 28-09'!W:W,MATCH(B22,'MTA 28-09'!A:A,0))} -> Não | U22: {=INDEX('MTA 28-09'!AE:AE,MATCH(B22,'MTA 28-09'!A:A,0))} -> 46107
A23: C-95M | B23: 10240 | C23: {=INDEX('MTA 28-09'!B:B,MATCH(B23,'MTA 28-09'!A:A,0))} -> SIM | D23: {=INDEX('MTA 28-09'!D:D,MATCH(B23,'MTA 28-09'!A:A,0))} -> 2048 | E23: {=INDEX('MTA 28-09'!F:F,MATCH(B23,'MTA 28-09'!A:A,0))} | F23: {=INDEX('MTA 28-09'!I:I,MATCH(B23,'MTA 28-09'!A:A,0))} | G23: {=INDEX('MTA 28-09'!J:J,MATCH(B23,'MTA 28-09'!A:A,0))} | H23: 46276 | I23: Atender | J23: restante livre | L23: {=INDEX('MTA 28-09'!S:S,MATCH(B23,'MTA 28-09'!A:A,0))} -> C-95M | M23: {=INDEX('MTA 28-09'!T:T,MATCH(B23,'MTA 28-09'!A:A,0))} -> Requisição CABW | N23: {=INDEX('MTA 28-09'!U:U,MATCH(B23,'MTA 28-09'!A:A,0))} -> Requisição Consumíveis | O23: {=INDEX('MTA 28-09'!AC:AC,MATCH(B23,'MTA 28-09'!A:A,0))} -> 451164.69 | P23: {=INDEX('MTA 28-09'!N:N,MATCH(B23,'MTA 28-09'!A:A,0))} -> CABW | Q23: {=INDEX('MTA 28-09'!Z:Z,MATCH(B23,'MTA 28-09'!A:A,0))} -> 339030 | R23: {=INDEX('MTA 28-09'!L:L,MATCH(B23,'MTA 28-09'!A:A,0))} -> A | S23: {=INDEX('MTA 28-09'!X:X,MATCH(B23,'MTA 28-09'!A:A,0))} -> REQUISIÇÃO | T23: {=INDEX('MTA 28-09'!W:W,MATCH(B23,'MTA 28-09'!A:A,0))} -> Não | U23: {=INDEX('MTA 28-09'!AE:AE,MATCH(B23,'MTA 28-09'!A:A,0))} -> 46260
A24: C-95M | B24: 10241 | C24: {=INDEX('MTA 28-09'!B:B,MATCH(B24,'MTA 28-09'!A:A,0))} -> SIM | D24: {=INDEX('MTA 28-09'!D:D,MATCH(B24,'MTA 28-09'!A:A,0))} -> 20XV | E24: {=INDEX('MTA 28-09'!F:F,MATCH(B24,'MTA 28-09'!A:A,0))} -> ATENDIDO | F24: {=INDEX('MTA 28-09'!I:I,MATCH(B24,'MTA 28-09'!A:A,0))} -> 46098 | G24: {=INDEX('MTA 28-09'!J:J,MATCH(B24,'MTA 28-09'!A:A,0))} -> C26151 | H24: email do dia 11/03 | L24: {=INDEX('MTA 28-09'!S:S,MATCH(B24,'MTA 28-09'!A:A,0))} -> C-95M | M24: {=INDEX('MTA 28-09'!T:T,MATCH(B24,'MTA 28-09'!A:A,0))} -> Contrato inexigibilidade EMBRAER | N24: {=INDEX('MTA 28-09'!U:U,MATCH(B24,'MTA 28-09'!A:A,0))} -> Publicação | O24: {=INDEX('MTA 28-09'!AC:AC,MATCH(B24,'MTA 28-09'!A:A,0))} -> 15615.31 | P24: {=INDEX('MTA 28-09'!N:N,MATCH(B24,'MTA 28-09'!A:A,0))} -> CELOG | Q24: {=INDEX('MTA 28-09'!Z:Z,MATCH(B24,'MTA 28-09'!A:A,0))} -> 339039 | R24: {=INDEX('MTA 28-09'!L:L,MATCH(B24,'MTA 28-09'!A:A,0))} -> A | S24: {=INDEX('MTA 28-09'!X:X,MATCH(B24,'MTA 28-09'!A:A,0))} -> REQUISIÇÃO | T24: {=INDEX('MTA 28-09'!W:W,MATCH(B24,'MTA 28-09'!A:A,0))} -> Não | U24: {=INDEX('MTA 28-09'!AE:AE,MATCH(B24,'MTA 28-09'!A:A,0))} -> 46107
A25: C-95M | B25: 10242 | C25: {=INDEX('MTA 28-09'!B:B,MATCH(B25,'MTA 28-09'!A:A,0))} -> SIM | D25: {=INDEX('MTA 28-09'!D:D,MATCH(B25,'MTA 28-09'!A:A,0))} -> 2048 | E25: {=INDEX('MTA 28-09'!F:F,MATCH(B25,'MTA 28-09'!A:A,0))} -> ATENDIDO | F25: {=INDEX('MTA 28-09'!I:I,MATCH(B25,'MTA 28-09'!A:A,0))} -> 46209 | G25: {=INDEX('MTA 28-09'!J:J,MATCH(B25,'MTA 28-09'!A:A,0))} -> C26146 | H25: email do dia 19/06 | L25: {=INDEX('MTA 28-09'!S:S,MATCH(B25,'MTA 28-09'!A:A,0))} -> C-95M | M25: {=INDEX('MTA 28-09'!T:T,MATCH(B25,'MTA 28-09'!A:A,0))} -> Requisição CABW | N25: {=INDEX('MTA 28-09'!U:U,MATCH(B25,'MTA 28-09'!A:A,0))} -> Publicação | O25: {=INDEX('MTA 28-09'!AC:AC,MATCH(B25,'MTA 28-09'!A:A,0))} -> 53149.73 | P25: {=INDEX('MTA 28-09'!N:N,MATCH(B25,'MTA 28-09'!A:A,0))} -> CABW | Q25: {=INDEX('MTA 28-09'!Z:Z,MATCH(B25,'MTA 28-09'!A:A,0))} -> 339039 | R25: {=INDEX('MTA 28-09'!L:L,MATCH(B25,'MTA 28-09'!A:A,0))} -> A | S25: {=INDEX('MTA 28-09'!X:X,MATCH(B25,'MTA 28-09'!A:A,0))} -> REQUISIÇÃO | T25: {=INDEX('MTA 28-09'!W:W,MATCH(B25,'MTA 28-09'!A:A,0))} -> Não | U25: {=INDEX('MTA 28-09'!AE:AE,MATCH(B25,'MTA 28-09'!A:A,0))} -> 46260
A26: C-97 | B26: 10260 | C26: {=INDEX('MTA 28-09'!B:B,MATCH(B26,'MTA 28-09'!A:A,0))} -> NÃO | D26: {=INDEX('MTA 28-09'!D:D,MATCH(B26,'MTA 28-09'!A:A,0))} | E26: {=INDEX('MTA 28-09'!F:F,MATCH(B26,'MTA 28-09'!A:A,0))} -> BLOQUEIO | F26: {=INDEX('MTA 28-09'!I:I,MATCH(B26,'MTA 28-09'!A:A,0))} | G26: {=INDEX('MTA 28-09'!J:J,MATCH(B26,'MTA 28-09'!A:A,0))} | J26: LIVRE | L26: {=INDEX('MTA 28-09'!S:S,MATCH(B26,'MTA 28-09'!A:A,0))} -> C-97 | M26: {=INDEX('MTA 28-09'!T:T,MATCH(B26,'MTA 28-09'!A:A,0))} -> Requisição CABW | N26: {=INDEX('MTA 28-09'!U:U,MATCH(B26,'MTA 28-09'!A:A,0))} -> Publicação | O26: {=INDEX('MTA 28-09'!AC:AC,MATCH(B26,'MTA 28-09'!A:A,0))} -> 501640.62 | P26: {=INDEX('MTA 28-09'!N:N,MATCH(B26,'MTA 28-09'!A:A,0))} -> CABW | Q26: {=INDEX('MTA 28-09'!Z:Z,MATCH(B26,'MTA 28-09'!A:A,0))} -> 339039 | R26: {=INDEX('MTA 28-09'!L:L,MATCH(B26,'MTA 28-09'!A:A,0))} -> B | S26: {=INDEX('MTA 28-09'!X:X,MATCH(B26,'MTA 28-09'!A:A,0))} -> REQUISIÇÃO | T26: {=INDEX('MTA 28-09'!W:W,MATCH(B26,'MTA 28-09'!A:A,0))} -> Não | U26: {=INDEX('MTA 28-09'!AE:AE,MATCH(B26,'MTA 28-09'!A:A,0))} -> 46291
A27: C-97 | B27: 10261 | C27: {=INDEX('MTA 28-09'!B:B,MATCH(B27,'MTA 28-09'!A:A,0))} -> SIM | D27: {=INDEX('MTA 28-09'!D:D,MATCH(B27,'MTA 28-09'!A:A,0))} -> 2048 | E27: {=INDEX('MTA 28-09'!F:F,MATCH(B27,'MTA 28-09'!A:A,0))} -> ATENDIDO | F27: {=INDEX('MTA 28-09'!I:I,MATCH(B27,'MTA 28-09'!A:A,0))} -> 46098 | G27: {=INDEX('MTA 28-09'!J:J,MATCH(B27,'MTA 28-09'!A:A,0))} -> C26155 | H27: email do dia 11/03 | L27: {=INDEX('MTA 28-09'!S:S,MATCH(B27,'MTA 28-09'!A:A,0))} -> C-97 | M27: {=INDEX('MTA 28-09'!T:T,MATCH(B27,'MTA 28-09'!A:A,0))} -> Contrato inexigibilidade EMBRAER | N27: {=INDEX('MTA 28-09'!U:U,MATCH(B27,'MTA 28-09'!A:A,0))} -> Publicação | O27: {=INDEX('MTA 28-09'!AC:AC,MATCH(B27,'MTA 28-09'!A:A,0))} -> 48359.38 | P27: {=INDEX('MTA 28-09'!N:N,MATCH(B27,'MTA 28-09'!A:A,0))} -> CELOG | Q27: {=INDEX('MTA 28-09'!Z:Z,MATCH(B27,'MTA 28-09'!A:A,0))} -> 339039 | R27: {=INDEX('MTA 28-09'!L:L,MATCH(B27,'MTA 28-09'!A:A,0))} -> A | S27: {=INDEX('MTA 28-09'!X:X,MATCH(B27,'MTA 28-09'!A:A,0))} -> REQUISIÇÃO | T27: {=INDEX('MTA 28-09'!W:W,MATCH(B27,'MTA 28-09'!A:A,0))} -> Não | U27: {=INDEX('MTA 28-09'!AE:AE,MATCH(B27,'MTA 28-09'!A:A,0))} -> 46107
A28: C-97 | B28: 10280 | C28: {=INDEX('MTA 28-09'!B:B,MATCH(B28,'MTA 28-09'!A:A,0))} -> SIM | D28: {=INDEX('MTA 28-09'!D:D,MATCH(B28,'MTA 28-09'!A:A,0))} -> 2048 | E28: {=INDEX('MTA 28-09'!F:F,MATCH(B28,'MTA 28-09'!A:A,0))} | F28: {=INDEX('MTA 28-09'!I:I,MATCH(B28,'MTA 28-09'!A:A,0))} | G28: {=INDEX('MTA 28-09'!J:J,MATCH(B28,'MTA 28-09'!A:A,0))} | H28: 46276 | I28: Atender | J28: LIVRE | L28: {=INDEX('MTA 28-09'!S:S,MATCH(B28,'MTA 28-09'!A:A,0))} -> C-97 | M28: {=INDEX('MTA 28-09'!T:T,MATCH(B28,'MTA 28-09'!A:A,0))} -> Requisição CABW | N28: {=INDEX('MTA 28-09'!U:U,MATCH(B28,'MTA 28-09'!A:A,0))} -> Requisição Consumíveis | O28: {=INDEX('MTA 28-09'!AC:AC,MATCH(B28,'MTA 28-09'!A:A,0))} -> 235062.94 | P28: {=INDEX('MTA 28-09'!N:N,MATCH(B28,'MTA 28-09'!A:A,0))} -> CABW | Q28: {=INDEX('MTA 28-09'!Z:Z,MATCH(B28,'MTA 28-09'!A:A,0))} -> 339030 | R28: {=INDEX('MTA 28-09'!L:L,MATCH(B28,'MTA 28-09'!A:A,0))} -> A | S28: {=INDEX('MTA 28-09'!X:X,MATCH(B28,'MTA 28-09'!A:A,0))} -> REQUISIÇÃO | T28: {=INDEX('MTA 28-09'!W:W,MATCH(B28,'MTA 28-09'!A:A,0))} -> Não | U28: {=INDEX('MTA 28-09'!AE:AE,MATCH(B28,'MTA 28-09'!A:A,0))} -> 46291
A29: C-97 | B29: 10281 | C29: {=INDEX('MTA 28-09'!B:B,MATCH(B29,'MTA 28-09'!A:A,0))} -> SIM | D29: {=INDEX('MTA 28-09'!D:D,MATCH(B29,'MTA 28-09'!A:A,0))} -> 2048 | E29: {=INDEX('MTA 28-09'!F:F,MATCH(B29,'MTA 28-09'!A:A,0))} -> ATENDIDO | F29: {=INDEX('MTA 28-09'!I:I,MATCH(B29,'MTA 28-09'!A:A,0))} -> 46192 | G29: {=INDEX('MTA 28-09'!J:J,MATCH(B29,'MTA 28-09'!A:A,0))} -> C26121 | H29: email do dia 25/05 | L29: {=INDEX('MTA 28-09'!S:S,MATCH(B29,'MTA 28-09'!A:A,0))} -> C-97 | M29: {=INDEX('MTA 28-09'!T:T,MATCH(B29,'MTA 28-09'!A:A,0))} -> Requisição CABW | N29: {=INDEX('MTA 28-09'!U:U,MATCH(B29,'MTA 28-09'!A:A,0))} -> Atualização de GPS | O29: {=INDEX('MTA 28-09'!AC:AC,MATCH(B29,'MTA 28-09'!A:A,0))} -> 37180 | P29: {=INDEX('MTA 28-09'!N:N,MATCH(B29,'MTA 28-09'!A:A,0))} -> CABW | Q29: {=INDEX('MTA 28-09'!Z:Z,MATCH(B29,'MTA 28-09'!A:A,0))} -> 339039 | R29: {=INDEX('MTA 28-09'!L:L,MATCH(B29,'MTA 28-09'!A:A,0))} -> A | S29: {=INDEX('MTA 28-09'!X:X,MATCH(B29,'MTA 28-09'!A:A,0))} -> REQUISIÇÃO | T29: {=INDEX('MTA 28-09'!W:W,MATCH(B29,'MTA 28-09'!A:A,0))} -> Não | U29: {=INDEX('MTA 28-09'!AE:AE,MATCH(B29,'MTA 28-09'!A:A,0))} -> 46291
A30: C-98 | B30: 10300 | C30: {=INDEX('MTA 28-09'!B:B,MATCH(B30,'MTA 28-09'!A:A,0))} -> SIM | D30: {=INDEX('MTA 28-09'!D:D,MATCH(B30,'MTA 28-09'!A:A,0))} -> 2048 | E30: {=INDEX('MTA 28-09'!F:F,MATCH(B30,'MTA 28-09'!A:A,0))} | F30: {=INDEX('MTA 28-09'!I:I,MATCH(B30,'MTA 28-09'!A:A,0))} | G30: {=INDEX('MTA 28-09'!J:J,MATCH(B30,'MTA 28-09'!A:A,0))} | H30: 46276 | I30: Atender | J30: LIVRE | L30: {=INDEX('MTA 28-09'!S:S,MATCH(B30,'MTA 28-09'!A:A,0))} -> C-98 | M30: {=INDEX('MTA 28-09'!T:T,MATCH(B30,'MTA 28-09'!A:A,0))} -> Requisição CABW | N30: {=INDEX('MTA 28-09'!U:U,MATCH(B30,'MTA 28-09'!A:A,0))} -> Requisição Consumíveis | O30: {=INDEX('MTA 28-09'!AC:AC,MATCH(B30,'MTA 28-09'!A:A,0))} -> 135000 | P30: {=INDEX('MTA 28-09'!N:N,MATCH(B30,'MTA 28-09'!A:A,0))} -> CABW | Q30: {=INDEX('MTA 28-09'!Z:Z,MATCH(B30,'MTA 28-09'!A:A,0))} -> 339030 | R30: {=INDEX('MTA 28-09'!L:L,MATCH(B30,'MTA 28-09'!A:A,0))} -> A | S30: {=INDEX('MTA 28-09'!X:X,MATCH(B30,'MTA 28-09'!A:A,0))} -> REQUISIÇÃO | T30: {=INDEX('MTA 28-09'!W:W,MATCH(B30,'MTA 28-09'!A:A,0))} -> Não | U30: {=INDEX('MTA 28-09'!AE:AE,MATCH(B30,'MTA 28-09'!A:A,0))} -> 46291
A31: IU-93M | B31: 10320 | C31: {=INDEX('MTA 28-09'!B:B,MATCH(B31,'MTA 28-09'!A:A,0))} -> NÃO | D31: {=INDEX('MTA 28-09'!D:D,MATCH(B31,'MTA 28-09'!A:A,0))} | E31: {=INDEX('MTA 28-09'!F:F,MATCH(B31,'MTA 28-09'!A:A,0))} | F31: {=INDEX('MTA 28-09'!I:I,MATCH(B31,'MTA 28-09'!A:A,0))} | G31: {=INDEX('MTA 28-09'!J:J,MATCH(B31,'MTA 28-09'!A:A,0))} | J31: restante livre | L31: {=INDEX('MTA 28-09'!S:S,MATCH(B31,'MTA 28-09'!A:A,0))} -> IU-93M | M31: {=INDEX('MTA 28-09'!T:T,MATCH(B31,'MTA 28-09'!A:A,0))} -> Requisição CABW | N31: {=INDEX('MTA 28-09'!U:U,MATCH(B31,'MTA 28-09'!A:A,0))} -> Atualização de GPS | O31: {=INDEX('MTA 28-09'!AC:AC,MATCH(B31,'MTA 28-09'!A:A,0))} -> 435113.38 | P31: {=INDEX('MTA 28-09'!N:N,MATCH(B31,'MTA 28-09'!A:A,0))} -> CABW | Q31: {=INDEX('MTA 28-09'!Z:Z,MATCH(B31,'MTA 28-09'!A:A,0))} -> 339039 | R31: {=INDEX('MTA 28-09'!L:L,MATCH(B31,'MTA 28-09'!A:A,0))} -> B | S31: {=INDEX('MTA 28-09'!X:X,MATCH(B31,'MTA 28-09'!A:A,0))} -> REQUISIÇÃO | T31: {=INDEX('MTA 28-09'!W:W,MATCH(B31,'MTA 28-09'!A:A,0))} -> Não | U31: {=INDEX('MTA 28-09'!AE:AE,MATCH(B31,'MTA 28-09'!A:A,0))} -> 46260
A32: IU-93M | B32: 10321 | C32: {=INDEX('MTA 28-09'!B:B,MATCH(B32,'MTA 28-09'!A:A,0))} -> SIM | D32: {=INDEX('MTA 28-09'!D:D,MATCH(B32,'MTA 28-09'!A:A,0))} -> 20XV | E32: {=INDEX('MTA 28-09'!F:F,MATCH(B32,'MTA 28-09'!A:A,0))} -> ATENDIDO | F32: {=INDEX('MTA 28-09'!I:I,MATCH(B32,'MTA 28-09'!A:A,0))} -> 46098 | G32: {=INDEX('MTA 28-09'!J:J,MATCH(B32,'MTA 28-09'!A:A,0))} -> C26059 | H32: email do dia 11/03 | L32: {=INDEX('MTA 28-09'!S:S,MATCH(B32,'MTA 28-09'!A:A,0))} -> IU-93M | M32: {=INDEX('MTA 28-09'!T:T,MATCH(B32,'MTA 28-09'!A:A,0))} -> Requisição CABW | N32: {=INDEX('MTA 28-09'!U:U,MATCH(B32,'MTA 28-09'!A:A,0))} -> Atualização de GPS | O32: {=INDEX('MTA 28-09'!AC:AC,MATCH(B32,'MTA 28-09'!A:A,0))} -> 133812 | P32: {=INDEX('MTA 28-09'!N:N,MATCH(B32,'MTA 28-09'!A:A,0))} -> CABW | Q32: {=INDEX('MTA 28-09'!Z:Z,MATCH(B32,'MTA 28-09'!A:A,0))} -> 339039 | R32: {=INDEX('MTA 28-09'!L:L,MATCH(B32,'MTA 28-09'!A:A,0))} -> A | S32: {=INDEX('MTA 28-09'!X:X,MATCH(B32,'MTA 28-09'!A:A,0))} -> REQUISIÇÃO | T32: {=INDEX('MTA 28-09'!W:W,MATCH(B32,'MTA 28-09'!A:A,0))} -> Não | U32: {=INDEX('MTA 28-09'!AE:AE,MATCH(B32,'MTA 28-09'!A:A,0))} -> 46107
A33: IU-93M | B33: 10322 | C33: {=INDEX('MTA 28-09'!B:B,MATCH(B33,'MTA 28-09'!A:A,0))} -> SIM | D33: {=INDEX('MTA 28-09'!D:D,MATCH(B33,'MTA 28-09'!A:A,0))} -> 20XV | E33: {=INDEX('MTA 28-09'!F:F,MATCH(B33,'MTA 28-09'!A:A,0))} -> ATENDIDO | F33: {=INDEX('MTA 28-09'!I:I,MATCH(B33,'MTA 28-09'!A:A,0))} -> 46210 | G33: {=INDEX('MTA 28-09'!J:J,MATCH(B33,'MTA 28-09'!A:A,0))} -> C26059 | H33: email do dia 19/06 | L33: {=INDEX('MTA 28-09'!S:S,MATCH(B33,'MTA 28-09'!A:A,0))} -> IU-93M | M33: {=INDEX('MTA 28-09'!T:T,MATCH(B33,'MTA 28-09'!A:A,0))} -> Requisição CABW | N33: {=INDEX('MTA 28-09'!U:U,MATCH(B33,'MTA 28-09'!A:A,0))} -> Atualização de GPS | O33: {=INDEX('MTA 28-09'!AC:AC,MATCH(B33,'MTA 28-09'!A:A,0))} -> 616082.32 | P33: {=INDEX('MTA 28-09'!N:N,MATCH(B33,'MTA 28-09'!A:A,0))} -> CABW | Q33: {=INDEX('MTA 28-09'!Z:Z,MATCH(B33,'MTA 28-09'!A:A,0))} -> 339039 | R33: {=INDEX('MTA 28-09'!L:L,MATCH(B33,'MTA 28-09'!A:A,0))} -> A | S33: {=INDEX('MTA 28-09'!X:X,MATCH(B33,'MTA 28-09'!A:A,0))} -> REQUISIÇÃO | T33: {=INDEX('MTA 28-09'!W:W,MATCH(B33,'MTA 28-09'!A:A,0))} -> Não | U33: {=INDEX('MTA 28-09'!AE:AE,MATCH(B33,'MTA 28-09'!A:A,0))} -> 46260
A34: IU-93M | B34: 10340 | C34: {=INDEX('MTA 28-09'!B:B,MATCH(B34,'MTA 28-09'!A:A,0))} -> SIM | D34: {=INDEX('MTA 28-09'!D:D,MATCH(B34,'MTA 28-09'!A:A,0))} -> 20XV | E34: {=INDEX('MTA 28-09'!F:F,MATCH(B34,'MTA 28-09'!A:A,0))} -> CANCELADO | F34: {=INDEX('MTA 28-09'!I:I,MATCH(B34,'MTA 28-09'!A:A,0))} | G34: {=INDEX('MTA 28-09'!J:J,MATCH(B34,'MTA 28-09'!A:A,0))} | H34: 1 | L34: {=INDEX('MTA 28-09'!S:S,MATCH(B34,'MTA 28-09'!A:A,0))} -> IU-93M | M34: {=INDEX('MTA 28-09'!T:T,MATCH(B34,'MTA 28-09'!A:A,0))} -> CNT 061/CAE-PAMALS/2020 | N34: {=INDEX('MTA 28-09'!U:U,MATCH(B34,'MTA 28-09'!A:A,0))} -> MPI autorizado pela DIRMAB | O34: {=INDEX('MTA 28-09'!AC:AC,MATCH(B34,'MTA 28-09'!A:A,0))} -> - | P34: {=INDEX('MTA 28-09'!N:N,MATCH(B34,'MTA 28-09'!A:A,0))} -> CELOG | Q34: {=INDEX('MTA 28-09'!Z:Z,MATCH(B34,'MTA 28-09'!A:A,0))} -> 339039 | R34: {=INDEX('MTA 28-09'!L:L,MATCH(B34,'MTA 28-09'!A:A,0))} -> A | S34: {=INDEX('MTA 28-09'!X:X,MATCH(B34,'MTA 28-09'!A:A,0))} -> SOB DEMANDA | T34: {=INDEX('MTA 28-09'!W:W,MATCH(B34,'MTA 28-09'!A:A,0))} -> SIM | U34: {=INDEX('MTA 28-09'!AE:AE,MATCH(B34,'MTA 28-09'!A:A,0))} -> 46107
A35: IU-93M | B35: 10341 | C35: {=INDEX('MTA 28-09'!B:B,MATCH(B35,'MTA 28-09'!A:A,0))} -> SIM | D35: {=INDEX('MTA 28-09'!D:D,MATCH(B35,'MTA 28-09'!A:A,0))} -> 20XV | E35: {=INDEX('MTA 28-09'!F:F,MATCH(B35,'MTA 28-09'!A:A,0))} -> ATENDIDO | F35: {=INDEX('MTA 28-09'!I:I,MATCH(B35,'MTA 28-09'!A:A,0))} -> 46191 | G35: {=INDEX('MTA 28-09'!J:J,MATCH(B35,'MTA 28-09'!A:A,0))} -> C26300 | L35: {=INDEX('MTA 28-09'!S:S,MATCH(B35,'MTA 28-09'!A:A,0))} -> IU-93M | M35: {=INDEX('MTA 28-09'!T:T,MATCH(B35,'MTA 28-09'!A:A,0))} -> CNT 061/CAE-PAMALS/2020 | N35: {=INDEX('MTA 28-09'!U:U,MATCH(B35,'MTA 28-09'!A:A,0))} -> MPI autorizado pela DIRMAB | O35: {=INDEX('MTA 28-09'!AC:AC,MATCH(B35,'MTA 28-09'!A:A,0))} -> 3000000 | P35: {=INDEX('MTA 28-09'!N:N,MATCH(B35,'MTA 28-09'!A:A,0))} -> CELOG | Q35: {=INDEX('MTA 28-09'!Z:Z,MATCH(B35,'MTA 28-09'!A:A,0))} -> 339030 | R35: {=INDEX('MTA 28-09'!L:L,MATCH(B35,'MTA 28-09'!A:A,0))} -> A | S35: {=INDEX('MTA 28-09'!X:X,MATCH(B35,'MTA 28-09'!A:A,0))} -> SOB DEMANDA | T35: {=INDEX('MTA 28-09'!W:W,MATCH(B35,'MTA 28-09'!A:A,0))} -> SIM | U35: {=INDEX('MTA 28-09'!AE:AE,MATCH(B35,'MTA 28-09'!A:A,0))}
A36: SSS | B36: 10360 | C36: {=INDEX('MTA 28-09'!B:B,MATCH(B36,'MTA 28-09'!A:A,0))} -> NÃO | D36: {=INDEX('MTA 28-09'!D:D,MATCH(B36,'MTA 28-09'!A:A,0))} | E36: {=INDEX('MTA 28-09'!F:F,MATCH(B36,'MTA 28-09'!A:A,0))} -> BLOQUEIO | F36: {=INDEX('MTA 28-09'!I:I,MATCH(B36,'MTA 28-09'!A:A,0))} | G36: {=INDEX('MTA 28-09'!J:J,MATCH(B36,'MTA 28-09'!A:A,0))} | L36: {=INDEX('MTA 28-09'!S:S,MATCH(B36,'MTA 28-09'!A:A,0))} -> APOIO | M36: {=INDEX('MTA 28-09'!T:T,MATCH(B36,'MTA 28-09'!A:A,0))} -> REQUISIÇÃO SSS TLV | N36: {=INDEX('MTA 28-09'!U:U,MATCH(B36,'MTA 28-09'!A:A,0))} -> AQUISIÇÃO ITENS SSS COM TEMPO LIMITE DE VIDA (CABW) 1/3 | O36: {=INDEX('MTA 28-09'!AC:AC,MATCH(B36,'MTA 28-09'!A:A,0))} -> 1679899.8 | P36: {=INDEX('MTA 28-09'!N:N,MATCH(B36,'MTA 28-09'!A:A,0))} -> CABW | Q36: {=INDEX('MTA 28-09'!Z:Z,MATCH(B36,'MTA 28-09'!A:A,0))} -> 339030 | R36: {=INDEX('MTA 28-09'!L:L,MATCH(B36,'MTA 28-09'!A:A,0))} -> B | S36: {=INDEX('MTA 28-09'!X:X,MATCH(B36,'MTA 28-09'!A:A,0))} -> REQUISIÇÃO | T36: {=INDEX('MTA 28-09'!W:W,MATCH(B36,'MTA 28-09'!A:A,0))} -> NÃO | U36: {=INDEX('MTA 28-09'!AE:AE,MATCH(B36,'MTA 28-09'!A:A,0))} -> 46049
A37: SSS | B37: 10380 | C37: {=INDEX('MTA 28-09'!B:B,MATCH(B37,'MTA 28-09'!A:A,0))} -> SIM | D37: {=INDEX('MTA 28-09'!D:D,MATCH(B37,'MTA 28-09'!A:A,0))} -> 2048 | E37: {=INDEX('MTA 28-09'!F:F,MATCH(B37,'MTA 28-09'!A:A,0))} -> ATENDIDO | F37: {=INDEX('MTA 28-09'!I:I,MATCH(B37,'MTA 28-09'!A:A,0))} -> 46063 | G37: {=INDEX('MTA 28-09'!J:J,MATCH(B37,'MTA 28-09'!A:A,0))} -> C26015 | H37: 1 | L37: {=INDEX('MTA 28-09'!S:S,MATCH(B37,'MTA 28-09'!A:A,0))} -> APOIO | M37: {=INDEX('MTA 28-09'!T:T,MATCH(B37,'MTA 28-09'!A:A,0))} -> REQUISIÇÃO PTA SSS | N37: {=INDEX('MTA 28-09'!U:U,MATCH(B37,'MTA 28-09'!A:A,0))} -> AQUISIÇÃO ITENS SSS CUMPRIR PTA (CABW) 1/2 | O37: {=INDEX('MTA 28-09'!AC:AC,MATCH(B37,'MTA 28-09'!A:A,0))} -> 760240.53 | P37: {=INDEX('MTA 28-09'!N:N,MATCH(B37,'MTA 28-09'!A:A,0))} -> CABW | Q37: {=INDEX('MTA 28-09'!Z:Z,MATCH(B37,'MTA 28-09'!A:A,0))} -> 339030 | R37: {=INDEX('MTA 28-09'!L:L,MATCH(B37,'MTA 28-09'!A:A,0))} -> A | S37: {=INDEX('MTA 28-09'!X:X,MATCH(B37,'MTA 28-09'!A:A,0))} -> REQUISIÇÃO | T37: {=INDEX('MTA 28-09'!W:W,MATCH(B37,'MTA 28-09'!A:A,0))} -> NÃO | U37: {=INDEX('MTA 28-09'!AE:AE,MATCH(B37,'MTA 28-09'!A:A,0))} -> 46107
A38: SSS | B38: 10400 | C38: {=INDEX('MTA 28-09'!B:B,MATCH(B38,'MTA 28-09'!A:A,0))} -> SIM | D38: {=INDEX('MTA 28-09'!D:D,MATCH(B38,'MTA 28-09'!A:A,0))} -> 2048 | E38: {=INDEX('MTA 28-09'!F:F,MATCH(B38,'MTA 28-09'!A:A,0))} | F38: {=INDEX('MTA 28-09'!I:I,MATCH(B38,'MTA 28-09'!A:A,0))} | G38: {=INDEX('MTA 28-09'!J:J,MATCH(B38,'MTA 28-09'!A:A,0))} | H38: 46276 | I38: Atender | L38: {=INDEX('MTA 28-09'!S:S,MATCH(B38,'MTA 28-09'!A:A,0))} -> APOIO | M38: {=INDEX('MTA 28-09'!T:T,MATCH(B38,'MTA 28-09'!A:A,0))} -> REQUISIÇÃO PTA SSS | N38: {=INDEX('MTA 28-09'!U:U,MATCH(B38,'MTA 28-09'!A:A,0))} -> AQUISIÇÃO DE ITENS SSS PARA CUMPRIR PTA | O38: {=INDEX('MTA 28-09'!AC:AC,MATCH(B38,'MTA 28-09'!A:A,0))} -> 5172.75 | P38: {=INDEX('MTA 28-09'!N:N,MATCH(B38,'MTA 28-09'!A:A,0))} -> CABW | Q38: {=INDEX('MTA 28-09'!Z:Z,MATCH(B38,'MTA 28-09'!A:A,0))} -> 339030 | R38: {=INDEX('MTA 28-09'!L:L,MATCH(B38,'MTA 28-09'!A:A,0))} -> A | S38: {=INDEX('MTA 28-09'!X:X,MATCH(B38,'MTA 28-09'!A:A,0))} -> REQUISIÇÃO | T38: {=INDEX('MTA 28-09'!W:W,MATCH(B38,'MTA 28-09'!A:A,0))} -> NÃO | U38: {=INDEX('MTA 28-09'!AE:AE,MATCH(B38,'MTA 28-09'!A:A,0))} -> 46049
A39: T-27 | B39: 10420 | C39: {=INDEX('MTA 28-09'!B:B,MATCH(B39,'MTA 28-09'!A:A,0))} -> SIM | D39: {=INDEX('MTA 28-09'!D:D,MATCH(B39,'MTA 28-09'!A:A,0))} -> 2048 | E39: {=INDEX('MTA 28-09'!F:F,MATCH(B39,'MTA 28-09'!A:A,0))} -> ATENDIDO | F39: {=INDEX('MTA 28-09'!I:I,MATCH(B39,'MTA 28-09'!A:A,0))} -> 46041 | G39: {=INDEX('MTA 28-09'!J:J,MATCH(B39,'MTA 28-09'!A:A,0))} -> C26054 | H39: 1 | L39: {=INDEX('MTA 28-09'!S:S,MATCH(B39,'MTA 28-09'!A:A,0))} -> T-27 | M39: {=INDEX('MTA 28-09'!T:T,MATCH(B39,'MTA 28-09'!A:A,0))} -> CTT 009/CELOG-PAMALS/2025 – Aquisição de Consumíveis | N39: {=INDEX('MTA 28-09'!U:U,MATCH(B39,'MTA 28-09'!A:A,0))} -> Sob demanda 1/8 | O39: {=INDEX('MTA 28-09'!AC:AC,MATCH(B39,'MTA 28-09'!A:A,0))} -> 1130000 | P39: {=INDEX('MTA 28-09'!N:N,MATCH(B39,'MTA 28-09'!A:A,0))} -> CELOG | Q39: {=INDEX('MTA 28-09'!Z:Z,MATCH(B39,'MTA 28-09'!A:A,0))} -> 339030 | R39: {=INDEX('MTA 28-09'!L:L,MATCH(B39,'MTA 28-09'!A:A,0))} -> A | S39: {=INDEX('MTA 28-09'!X:X,MATCH(B39,'MTA 28-09'!A:A,0))} -> SOB DEMANDA | T39: {=INDEX('MTA 28-09'!W:W,MATCH(B39,'MTA 28-09'!A:A,0))} -> Não | U39: {=INDEX('MTA 28-09'!AE:AE,MATCH(B39,'MTA 28-09'!A:A,0))} -> 46107
A40: A-29 | B40: 10440 | C40: {=INDEX('MTA 28-09'!B:B,MATCH(B40,'MTA 28-09'!A:A,0))} -> SIM | D40: {=INDEX('MTA 28-09'!D:D,MATCH(B40,'MTA 28-09'!A:A,0))} -> 2048 | E40: {=INDEX('MTA 28-09'!F:F,MATCH(B40,'MTA 28-09'!A:A,0))} -> ATENDIDO | F40: {=INDEX('MTA 28-09'!I:I,MATCH(B40,'MTA 28-09'!A:A,0))} -> 46041 | G40: {=INDEX('MTA 28-09'!J:J,MATCH(B40,'MTA 28-09'!A:A,0))} -> C26059 | H40: 1 | L40: {=INDEX('MTA 28-09'!S:S,MATCH(B40,'MTA 28-09'!A:A,0))} -> A-29 | M40: {=INDEX('MTA 28-09'!T:T,MATCH(B40,'MTA 28-09'!A:A,0))} -> CTT 102/CELOG-PAMALS/2023 – EMBRAER - PSLI | N40: {=INDEX('MTA 28-09'!U:U,MATCH(B40,'MTA 28-09'!A:A,0))} -> Módulo Extra - Sob demanda 1/4 | O40: {=INDEX('MTA 28-09'!AC:AC,MATCH(B40,'MTA 28-09'!A:A,0))} -> 1294030.6 | P40: {=INDEX('MTA 28-09'!N:N,MATCH(B40,'MTA 28-09'!A:A,0))} -> CELOG | Q40: {=INDEX('MTA 28-09'!Z:Z,MATCH(B40,'MTA 28-09'!A:A,0))} -> 339039 | R40: {=INDEX('MTA 28-09'!L:L,MATCH(B40,'MTA 28-09'!A:A,0))} -> A | S40: {=INDEX('MTA 28-09'!X:X,MATCH(B40,'MTA 28-09'!A:A,0))} -> SOB DEMANDA | T40: {=INDEX('MTA 28-09'!W:W,MATCH(B40,'MTA 28-09'!A:A,0))} -> Não | U40: {=INDEX('MTA 28-09'!AE:AE,MATCH(B40,'MTA 28-09'!A:A,0))} -> 46107
A41: A-29 | B41: 10460 | C41: {=INDEX('MTA 28-09'!B:B,MATCH(B41,'MTA 28-09'!A:A,0))} -> SIM | D41: {=INDEX('MTA 28-09'!D:D,MATCH(B41,'MTA 28-09'!A:A,0))} -> 2048 PO 02 | E41: {=INDEX('MTA 28-09'!F:F,MATCH(B41,'MTA 28-09'!A:A,0))} -> ATENDER | F41: {=INDEX('MTA 28-09'!I:I,MATCH(B41,'MTA 28-09'!A:A,0))} | G41: {=INDEX('MTA 28-09'!J:J,MATCH(B41,'MTA 28-09'!A:A,0))} | H41: 46276 | I41: Atender | L41: {=INDEX('MTA 28-09'!S:S,MATCH(B41,'MTA 28-09'!A:A,0))} -> A-29 | M41: {=INDEX('MTA 28-09'!T:T,MATCH(B41,'MTA 28-09'!A:A,0))} -> CNT 040/CELOG-PAMALS/2022 - AEL - CLS AVIONICO | N41: {=INDEX('MTA 28-09'!U:U,MATCH(B41,'MTA 28-09'!A:A,0))} -> Módulo Extra - Sob demanda | O41: {=INDEX('MTA 28-09'!AC:AC,MATCH(B41,'MTA 28-09'!A:A,0))} -> 412184.26 | P41: {=INDEX('MTA 28-09'!N:N,MATCH(B41,'MTA 28-09'!A:A,0))} -> CELOG | Q41: {=INDEX('MTA 28-09'!Z:Z,MATCH(B41,'MTA 28-09'!A:A,0))} -> 339039 | R41: {=INDEX('MTA 28-09'!L:L,MATCH(B41,'MTA 28-09'!A:A,0))} -> A | S41: {=INDEX('MTA 28-09'!X:X,MATCH(B41,'MTA 28-09'!A:A,0))} -> SOB DEMANDA | T41: {=INDEX('MTA 28-09'!W:W,MATCH(B41,'MTA 28-09'!A:A,0))} -> Não | U41: {=INDEX('MTA 28-09'!AE:AE,MATCH(B41,'MTA 28-09'!A:A,0))} -> 46321
A42: C-95M | B42: 10480 | C42: {=INDEX('MTA 28-09'!B:B,MATCH(B42,'MTA 28-09'!A:A,0))} -> SIM | D42: {=INDEX('MTA 28-09'!D:D,MATCH(B42,'MTA 28-09'!A:A,0))} -> 20XV | E42: {=INDEX('MTA 28-09'!F:F,MATCH(B42,'MTA 28-09'!A:A,0))} -> ATENDIDO | F42: {=INDEX('MTA 28-09'!I:I,MATCH(B42,'MTA 28-09'!A:A,0))} -> 46176 | G42: {=INDEX('MTA 28-09'!J:J,MATCH(B42,'MTA 28-09'!A:A,0))} -> C26289 | H42: email do dia 25/05 | L42: {=INDEX('MTA 28-09'!S:S,MATCH(B42,'MTA 28-09'!A:A,0))} -> C-95M | M42: {=INDEX('MTA 28-09'!T:T,MATCH(B42,'MTA 28-09'!A:A,0))} -> CTT 028/CELOG-PAMALS/2025 – CLS AVIÔNICOS | N42: {=INDEX('MTA 28-09'!U:U,MATCH(B42,'MTA 28-09'!A:A,0))} -> Módulo Extra - Sob demanda 1/4 | O42: {=INDEX('MTA 28-09'!AC:AC,MATCH(B42,'MTA 28-09'!A:A,0))} -> 525000 | P42: {=INDEX('MTA 28-09'!N:N,MATCH(B42,'MTA 28-09'!A:A,0))} -> CELOG | Q42: {=INDEX('MTA 28-09'!Z:Z,MATCH(B42,'MTA 28-09'!A:A,0))} -> 339030 | R42: {=INDEX('MTA 28-09'!L:L,MATCH(B42,'MTA 28-09'!A:A,0))} -> A | S42: {=INDEX('MTA 28-09'!X:X,MATCH(B42,'MTA 28-09'!A:A,0))} -> SOB DEMANDA | T42: {=INDEX('MTA 28-09'!W:W,MATCH(B42,'MTA 28-09'!A:A,0))} -> Não | U42: {=INDEX('MTA 28-09'!AE:AE,MATCH(B42,'MTA 28-09'!A:A,0))} -> 46107
A43: C-95M | B43: 10500 | C43: {=INDEX('MTA 28-09'!B:B,MATCH(B43,'MTA 28-09'!A:A,0))} -> SIM | D43: {=INDEX('MTA 28-09'!D:D,MATCH(B43,'MTA 28-09'!A:A,0))} -> 20XV | E43: {=INDEX('MTA 28-09'!F:F,MATCH(B43,'MTA 28-09'!A:A,0))} -> ATENDIDO | F43: {=INDEX('MTA 28-09'!I:I,MATCH(B43,'MTA 28-09'!A:A,0))} -> 46066 | G43: {=INDEX('MTA 28-09'!J:J,MATCH(B43,'MTA 28-09'!A:A,0))} -> C26085 | H43: 1 | L43: {=INDEX('MTA 28-09'!S:S,MATCH(B43,'MTA 28-09'!A:A,0))} -> C-95M | M43: {=INDEX('MTA 28-09'!T:T,MATCH(B43,'MTA 28-09'!A:A,0))} -> CTT 049/CELOG-PAMALS/2024 – Aquisição de Consumíveis | N43: {=INDEX('MTA 28-09'!U:U,MATCH(B43,'MTA 28-09'!A:A,0))} -> Sob demanda 1/6 | O43: {=INDEX('MTA 28-09'!AC:AC,MATCH(B43,'MTA 28-09'!A:A,0))} -> 1360000 | P43: {=INDEX('MTA 28-09'!N:N,MATCH(B43,'MTA 28-09'!A:A,0))} -> CELOG | Q43: {=INDEX('MTA 28-09'!Z:Z,MATCH(B43,'MTA 28-09'!A:A,0))} -> 339030 | R43: {=INDEX('MTA 28-09'!L:L,MATCH(B43,'MTA 28-09'!A:A,0))} -> A | S43: {=INDEX('MTA 28-09'!X:X,MATCH(B43,'MTA 28-09'!A:A,0))} -> SOB DEMANDA | T43: {=INDEX('MTA 28-09'!W:W,MATCH(B43,'MTA 28-09'!A:A,0))} -> Não | U43: {=INDEX('MTA 28-09'!AE:AE,MATCH(B43,'MTA 28-09'!A:A,0))} -> 46107
A44: A-29 | B44: 10520 | C44: {=INDEX('MTA 28-09'!B:B,MATCH(B44,'MTA 28-09'!A:A,0))} -> SIM | D44: {=INDEX('MTA 28-09'!D:D,MATCH(B44,'MTA 28-09'!A:A,0))} -> 2048 | E44: {=INDEX('MTA 28-09'!F:F,MATCH(B44,'MTA 28-09'!A:A,0))} -> ATENDIDO | F44: {=INDEX('MTA 28-09'!I:I,MATCH(B44,'MTA 28-09'!A:A,0))} -> 46073 | G44: {=INDEX('MTA 28-09'!J:J,MATCH(B44,'MTA 28-09'!A:A,0))} -> C26109 | H44: 1 | L44: {=INDEX('MTA 28-09'!S:S,MATCH(B44,'MTA 28-09'!A:A,0))} -> A-29 | M44: {=INDEX('MTA 28-09'!T:T,MATCH(B44,'MTA 28-09'!A:A,0))} -> CTT 102/CELOG-PAMALS/2023 – EMBRAER - PSLI | N44: {=INDEX('MTA 28-09'!U:U,MATCH(B44,'MTA 28-09'!A:A,0))} -> Parcela Fixa 02/12 | O44: {=INDEX('MTA 28-09'!AC:AC,MATCH(B44,'MTA 28-09'!A:A,0))} -> 2310000 | P44: {=INDEX('MTA 28-09'!N:N,MATCH(B44,'MTA 28-09'!A:A,0))} -> CELOG | Q44: {=INDEX('MTA 28-09'!Z:Z,MATCH(B44,'MTA 28-09'!A:A,0))} -> 339039 | R44: {=INDEX('MTA 28-09'!L:L,MATCH(B44,'MTA 28-09'!A:A,0))} -> A | S44: {=INDEX('MTA 28-09'!X:X,MATCH(B44,'MTA 28-09'!A:A,0))} -> PARCELA FIXA | T44: {=INDEX('MTA 28-09'!W:W,MATCH(B44,'MTA 28-09'!A:A,0))} -> Não | U44: {=INDEX('MTA 28-09'!AE:AE,MATCH(B44,'MTA 28-09'!A:A,0))} -> 46138
A45: C-97 | B45: 10540 | C45: {=INDEX('MTA 28-09'!B:B,MATCH(B45,'MTA 28-09'!A:A,0))} -> SIM | D45: {=INDEX('MTA 28-09'!D:D,MATCH(B45,'MTA 28-09'!A:A,0))} -> 2048 | E45: {=INDEX('MTA 28-09'!F:F,MATCH(B45,'MTA 28-09'!A:A,0))} -> ATENDIDO | F45: {=INDEX('MTA 28-09'!I:I,MATCH(B45,'MTA 28-09'!A:A,0))} -> 46076 | G45: {=INDEX('MTA 28-09'!J:J,MATCH(B45,'MTA 28-09'!A:A,0))} -> C26110 | H45: 1 | L45: {=INDEX('MTA 28-09'!S:S,MATCH(B45,'MTA 28-09'!A:A,0))} -> C-97 | M45: {=INDEX('MTA 28-09'!T:T,MATCH(B45,'MTA 28-09'!A:A,0))} -> CTT 096/CAE-PAMALS/2021 - CLS C-97 | N45: {=INDEX('MTA 28-09'!U:U,MATCH(B45,'MTA 28-09'!A:A,0))} -> Parcela Fixa 02/12 | O45: {=INDEX('MTA 28-09'!AC:AC,MATCH(B45,'MTA 28-09'!A:A,0))} -> 332718.75 | P45: {=INDEX('MTA 28-09'!N:N,MATCH(B45,'MTA 28-09'!A:A,0))} -> CELOG | Q45: {=INDEX('MTA 28-09'!Z:Z,MATCH(B45,'MTA 28-09'!A:A,0))} -> 339039 | R45: {=INDEX('MTA 28-09'!L:L,MATCH(B45,'MTA 28-09'!A:A,0))} -> A | S45: {=INDEX('MTA 28-09'!X:X,MATCH(B45,'MTA 28-09'!A:A,0))} -> PARCELA FIXA | T45: {=INDEX('MTA 28-09'!W:W,MATCH(B45,'MTA 28-09'!A:A,0))} -> Não | U45: {=INDEX('MTA 28-09'!AE:AE,MATCH(B45,'MTA 28-09'!A:A,0))} -> 46138
A46: A-29 | B46: 10560 | C46: {=INDEX('MTA 28-09'!B:B,MATCH(B46,'MTA 28-09'!A:A,0))} -> SIM | D46: {=INDEX('MTA 28-09'!D:D,MATCH(B46,'MTA 28-09'!A:A,0))} -> 2048 | E46: {=INDEX('MTA 28-09'!F:F,MATCH(B46,'MTA 28-09'!A:A,0))} -> ATENDIDO | F46: {=INDEX('MTA 28-09'!I:I,MATCH(B46,'MTA 28-09'!A:A,0))} -> 46085 | G46: {=INDEX('MTA 28-09'!J:J,MATCH(B46,'MTA 28-09'!A:A,0))} -> C26138 | H46: 1 | L46: {=INDEX('MTA 28-09'!S:S,MATCH(B46,'MTA 28-09'!A:A,0))} -> A-29 | M46: {=INDEX('MTA 28-09'!T:T,MATCH(B46,'MTA 28-09'!A:A,0))} -> CTT 102/CELOG-PAMALS/2023 – EMBRAER - PSLI | N46: {=INDEX('MTA 28-09'!U:U,MATCH(B46,'MTA 28-09'!A:A,0))} -> Hora de Voo 02/10 - 1000 HV | O46: {=INDEX('MTA 28-09'!AC:AC,MATCH(B46,'MTA 28-09'!A:A,0))} -> 4995311 | P46: {=INDEX('MTA 28-09'!N:N,MATCH(B46,'MTA 28-09'!A:A,0))} -> CELOG | Q46: {=INDEX('MTA 28-09'!Z:Z,MATCH(B46,'MTA 28-09'!A:A,0))} -> 339039 | R46: {=INDEX('MTA 28-09'!L:L,MATCH(B46,'MTA 28-09'!A:A,0))} -> A | S46: {=INDEX('MTA 28-09'!X:X,MATCH(B46,'MTA 28-09'!A:A,0))} -> HORA DE VOO | T46: {=INDEX('MTA 28-09'!W:W,MATCH(B46,'MTA 28-09'!A:A,0))} -> Não | U46: {=INDEX('MTA 28-09'!AE:AE,MATCH(B46,'MTA 28-09'!A:A,0))} -> 46168
A47: A-29 | B47: 10561 | C47: {=INDEX('MTA 28-09'!B:B,MATCH(B47,'MTA 28-09'!A:A,0))} -> SIM | D47: {=INDEX('MTA 28-09'!D:D,MATCH(B47,'MTA 28-09'!A:A,0))} -> DESTQ02 | E47: {=INDEX('MTA 28-09'!F:F,MATCH(B47,'MTA 28-09'!A:A,0))} -> ATENDIDO | F47: {=INDEX('MTA 28-09'!I:I,MATCH(B47,'MTA 28-09'!A:A,0))} -> 46085 | G47: {=INDEX('MTA 28-09'!J:J,MATCH(B47,'MTA 28-09'!A:A,0))} -> C26130 | H47: 1 | L47: {=INDEX('MTA 28-09'!S:S,MATCH(B47,'MTA 28-09'!A:A,0))} -> A-29 | M47: {=INDEX('MTA 28-09'!T:T,MATCH(B47,'MTA 28-09'!A:A,0))} -> CTT 102/CELOG-PAMALS/2023 – EMBRAER - PSLI | N47: {=INDEX('MTA 28-09'!U:U,MATCH(B47,'MTA 28-09'!A:A,0))} -> Hora de Voo 02/10 - 1000 HV | O47: {=INDEX('MTA 28-09'!AC:AC,MATCH(B47,'MTA 28-09'!A:A,0))} -> 920987.62 | P47: {=INDEX('MTA 28-09'!N:N,MATCH(B47,'MTA 28-09'!A:A,0))} -> CELOG | Q47: {=INDEX('MTA 28-09'!Z:Z,MATCH(B47,'MTA 28-09'!A:A,0))} -> 339039 | R47: {=INDEX('MTA 28-09'!L:L,MATCH(B47,'MTA 28-09'!A:A,0))} -> A | S47: {=INDEX('MTA 28-09'!X:X,MATCH(B47,'MTA 28-09'!A:A,0))} -> HORA DE VOO | T47: {=INDEX('MTA 28-09'!W:W,MATCH(B47,'MTA 28-09'!A:A,0))} -> Não | U47: {=INDEX('MTA 28-09'!AE:AE,MATCH(B47,'MTA 28-09'!A:A,0))} -> 46168
A48: T-27 | B48: 10580 | C48: {=INDEX('MTA 28-09'!B:B,MATCH(B48,'MTA 28-09'!A:A,0))} -> SIM | D48: {=INDEX('MTA 28-09'!D:D,MATCH(B48,'MTA 28-09'!A:A,0))} -> 2048 | E48: {=INDEX('MTA 28-09'!F:F,MATCH(B48,'MTA 28-09'!A:A,0))} | F48: {=INDEX('MTA 28-09'!I:I,MATCH(B48,'MTA 28-09'!A:A,0))} | G48: {=INDEX('MTA 28-09'!J:J,MATCH(B48,'MTA 28-09'!A:A,0))} | L48: {=INDEX('MTA 28-09'!S:S,MATCH(B48,'MTA 28-09'!A:A,0))} -> T-27 | M48: {=INDEX('MTA 28-09'!T:T,MATCH(B48,'MTA 28-09'!A:A,0))} -> CNT XXX/CELOG-PAMASP/2026 - XX - Material | N48: {=INDEX('MTA 28-09'!U:U,MATCH(B48,'MTA 28-09'!A:A,0))} -> Material reparo PT6A-25C (2/4) | O48: {=INDEX('MTA 28-09'!AC:AC,MATCH(B48,'MTA 28-09'!A:A,0))} -> 750000 | P48: {=INDEX('MTA 28-09'!N:N,MATCH(B48,'MTA 28-09'!A:A,0))} -> CELOG | Q48: {=INDEX('MTA 28-09'!Z:Z,MATCH(B48,'MTA 28-09'!A:A,0))} -> 339030 | R48: {=INDEX('MTA 28-09'!L:L,MATCH(B48,'MTA 28-09'!A:A,0))} -> A | S48: {=INDEX('MTA 28-09'!X:X,MATCH(B48,'MTA 28-09'!A:A,0))} -> SOB DEMANDA | T48: {=INDEX('MTA 28-09'!W:W,MATCH(B48,'MTA 28-09'!A:A,0))} -> SIM | U48: {=INDEX('MTA 28-09'!AE:AE,MATCH(B48,'MTA 28-09'!A:A,0))} -> 46382
A49: T-27 | B49: 10600 | C49: {=INDEX('MTA 28-09'!B:B,MATCH(B49,'MTA 28-09'!A:A,0))} -> SIM | D49: {=INDEX('MTA 28-09'!D:D,MATCH(B49,'MTA 28-09'!A:A,0))} -> 2048 | E49: {=INDEX('MTA 28-09'!F:F,MATCH(B49,'MTA 28-09'!A:A,0))} -> CANCELADO | F49: {=INDEX('MTA 28-09'!I:I,MATCH(B49,'MTA 28-09'!A:A,0))} | G49: {=INDEX('MTA 28-09'!J:J,MATCH(B49,'MTA 28-09'!A:A,0))} | L49: {=INDEX('MTA 28-09'!S:S,MATCH(B49,'MTA 28-09'!A:A,0))} -> T-27 | M49: {=INDEX('MTA 28-09'!T:T,MATCH(B49,'MTA 28-09'!A:A,0))} -> REQUISIÇÃO SERVIÇO | N49: {=INDEX('MTA 28-09'!U:U,MATCH(B49,'MTA 28-09'!A:A,0))} -> RG Flow Divider 6 EA | O49: {=INDEX('MTA 28-09'!AC:AC,MATCH(B49,'MTA 28-09'!A:A,0))} -> - | P49: {=INDEX('MTA 28-09'!N:N,MATCH(B49,'MTA 28-09'!A:A,0))} -> CABW | Q49: {=INDEX('MTA 28-09'!Z:Z,MATCH(B49,'MTA 28-09'!A:A,0))} -> 339039 | R49: {=INDEX('MTA 28-09'!L:L,MATCH(B49,'MTA 28-09'!A:A,0))} -> A | S49: {=INDEX('MTA 28-09'!X:X,MATCH(B49,'MTA 28-09'!A:A,0))} -> REQUISIÇÃO | T49: {=INDEX('MTA 28-09'!W:W,MATCH(B49,'MTA 28-09'!A:A,0))} -> SIM | U49: {=INDEX('MTA 28-09'!AE:AE,MATCH(B49,'MTA 28-09'!A:A,0))} -> 46169
A50: T-27 | B50: 10620 | C50: {=INDEX('MTA 28-09'!B:B,MATCH(B50,'MTA 28-09'!A:A,0))} -> SIM | D50: {=INDEX('MTA 28-09'!D:D,MATCH(B50,'MTA 28-09'!A:A,0))} -> 2048 | E50: {=INDEX('MTA 28-09'!F:F,MATCH(B50,'MTA 28-09'!A:A,0))} -> CANCELADO | F50: {=INDEX('MTA 28-09'!I:I,MATCH(B50,'MTA 28-09'!A:A,0))} | G50: {=INDEX('MTA 28-09'!J:J,MATCH(B50,'MTA 28-09'!A:A,0))} | L50: {=INDEX('MTA 28-09'!S:S,MATCH(B50,'MTA 28-09'!A:A,0))} -> T-27 | M50: {=INDEX('MTA 28-09'!T:T,MATCH(B50,'MTA 28-09'!A:A,0))} -> REQUISIÇÃO SERVIÇO | N50: {=INDEX('MTA 28-09'!U:U,MATCH(B50,'MTA 28-09'!A:A,0))} -> RG Fuel Control Unit 2 EA (1/4) | O50: {=INDEX('MTA 28-09'!AC:AC,MATCH(B50,'MTA 28-09'!A:A,0))} -> - | P50: {=INDEX('MTA 28-09'!N:N,MATCH(B50,'MTA 28-09'!A:A,0))} -> CABW | Q50: {=INDEX('MTA 28-09'!Z:Z,MATCH(B50,'MTA 28-09'!A:A,0))} -> 339039 | R50: {=INDEX('MTA 28-09'!L:L,MATCH(B50,'MTA 28-09'!A:A,0))} -> A | S50: {=INDEX('MTA 28-09'!X:X,MATCH(B50,'MTA 28-09'!A:A,0))} -> REQUISIÇÃO | T50: {=INDEX('MTA 28-09'!W:W,MATCH(B50,'MTA 28-09'!A:A,0))} -> SIM | U50: {=INDEX('MTA 28-09'!AE:AE,MATCH(B50,'MTA 28-09'!A:A,0))} -> 46169
A51: T-25 | B51: 10621 | C51: {=INDEX('MTA 28-09'!B:B,MATCH(B51,'MTA 28-09'!A:A,0))} -> SIM | D51: {=INDEX('MTA 28-09'!D:D,MATCH(B51,'MTA 28-09'!A:A,0))} -> 2048 | E51: {=INDEX('MTA 28-09'!F:F,MATCH(B51,'MTA 28-09'!A:A,0))} -> ATENDIDO | F51: {=INDEX('MTA 28-09'!I:I,MATCH(B51,'MTA 28-09'!A:A,0))} -> 46251 | G51: {=INDEX('MTA 28-09'!J:J,MATCH(B51,'MTA 28-09'!A:A,0))} -> C26183 | H51: 46251 | L51: {=INDEX('MTA 28-09'!S:S,MATCH(B51,'MTA 28-09'!A:A,0))} -> T-25 | M51: {=INDEX('MTA 28-09'!T:T,MATCH(B51,'MTA 28-09'!A:A,0))} -> REQUISIÇÃO CONSUMO | N51: {=INDEX('MTA 28-09'!U:U,MATCH(B51,'MTA 28-09'!A:A,0))} -> Repair KIT | O51: {=INDEX('MTA 28-09'!AC:AC,MATCH(B51,'MTA 28-09'!A:A,0))} -> 81185.35 | P51: {=INDEX('MTA 28-09'!N:N,MATCH(B51,'MTA 28-09'!A:A,0))} -> CABW | Q51: {=INDEX('MTA 28-09'!Z:Z,MATCH(B51,'MTA 28-09'!A:A,0))} -> 339030 | R51: {=INDEX('MTA 28-09'!L:L,MATCH(B51,'MTA 28-09'!A:A,0))} -> A | S51: {=INDEX('MTA 28-09'!X:X,MATCH(B51,'MTA 28-09'!A:A,0))} -> REQUISIÇÃO | T51: {=INDEX('MTA 28-09'!W:W,MATCH(B51,'MTA 28-09'!A:A,0))} -> NÃO | U51: {=INDEX('MTA 28-09'!AE:AE,MATCH(B51,'MTA 28-09'!A:A,0))} -> 46169
A52: T-27 | B52: 10640 | C52: {=INDEX('MTA 28-09'!B:B,MATCH(B52,'MTA 28-09'!A:A,0))} -> SIM | D52: {=INDEX('MTA 28-09'!D:D,MATCH(B52,'MTA 28-09'!A:A,0))} -> 2048 | E52: {=INDEX('MTA 28-09'!F:F,MATCH(B52,'MTA 28-09'!A:A,0))} -> CANCELADO | F52: {=INDEX('MTA 28-09'!I:I,MATCH(B52,'MTA 28-09'!A:A,0))} | G52: {=INDEX('MTA 28-09'!J:J,MATCH(B52,'MTA 28-09'!A:A,0))} | L52: {=INDEX('MTA 28-09'!S:S,MATCH(B52,'MTA 28-09'!A:A,0))} -> T-27 | M52: {=INDEX('MTA 28-09'!T:T,MATCH(B52,'MTA 28-09'!A:A,0))} -> REQUISIÇÃO SERVIÇO | N52: {=INDEX('MTA 28-09'!U:U,MATCH(B52,'MTA 28-09'!A:A,0))} -> RG Fuel Pump 4 EA (1/2) | O52: {=INDEX('MTA 28-09'!AC:AC,MATCH(B52,'MTA 28-09'!A:A,0))} -> - | P52: {=INDEX('MTA 28-09'!N:N,MATCH(B52,'MTA 28-09'!A:A,0))} -> CABW | Q52: {=INDEX('MTA 28-09'!Z:Z,MATCH(B52,'MTA 28-09'!A:A,0))} -> 339039 | R52: {=INDEX('MTA 28-09'!L:L,MATCH(B52,'MTA 28-09'!A:A,0))} -> A | S52: {=INDEX('MTA 28-09'!X:X,MATCH(B52,'MTA 28-09'!A:A,0))} -> REQUISIÇÃO | T52: {=INDEX('MTA 28-09'!W:W,MATCH(B52,'MTA 28-09'!A:A,0))} -> SIM | U52: {=INDEX('MTA 28-09'!AE:AE,MATCH(B52,'MTA 28-09'!A:A,0))} -> 46169
A53: C-95M | B53: 10660 | C53: {=INDEX('MTA 28-09'!B:B,MATCH(B53,'MTA 28-09'!A:A,0))} -> SIM | D53: {=INDEX('MTA 28-09'!D:D,MATCH(B53,'MTA 28-09'!A:A,0))} -> 20XV | E53: {=INDEX('MTA 28-09'!F:F,MATCH(B53,'MTA 28-09'!A:A,0))} -> ATENDIDO | F53: {=INDEX('MTA 28-09'!I:I,MATCH(B53,'MTA 28-09'!A:A,0))} -> 46083 | G53: {=INDEX('MTA 28-09'!J:J,MATCH(B53,'MTA 28-09'!A:A,0))} -> C26049 | L53: {=INDEX('MTA 28-09'!S:S,MATCH(B53,'MTA 28-09'!A:A,0))} -> C-95M | M53: {=INDEX('MTA 28-09'!T:T,MATCH(B53,'MTA 28-09'!A:A,0))} -> REQUISIÇÃO CONSUMO | N53: {=INDEX('MTA 28-09'!U:U,MATCH(B53,'MTA 28-09'!A:A,0))} -> Material para FCU | O53: {=INDEX('MTA 28-09'!AC:AC,MATCH(B53,'MTA 28-09'!A:A,0))} -> 570000 | P53: {=INDEX('MTA 28-09'!N:N,MATCH(B53,'MTA 28-09'!A:A,0))} -> CABW | Q53: {=INDEX('MTA 28-09'!Z:Z,MATCH(B53,'MTA 28-09'!A:A,0))} -> 339030 | R53: {=INDEX('MTA 28-09'!L:L,MATCH(B53,'MTA 28-09'!A:A,0))} -> A | S53: {=INDEX('MTA 28-09'!X:X,MATCH(B53,'MTA 28-09'!A:A,0))} -> REQUISIÇÃO | T53: {=INDEX('MTA 28-09'!W:W,MATCH(B53,'MTA 28-09'!A:A,0))} -> SIM | U53: {=INDEX('MTA 28-09'!AE:AE,MATCH(B53,'MTA 28-09'!A:A,0))} -> 46260
A54: C-95M | B54: 10680 | C54: {=INDEX('MTA 28-09'!B:B,MATCH(B54,'MTA 28-09'!A:A,0))} -> SIM | D54: {=INDEX('MTA 28-09'!D:D,MATCH(B54,'MTA 28-09'!A:A,0))} -> 2048 | E54: {=INDEX('MTA 28-09'!F:F,MATCH(B54,'MTA 28-09'!A:A,0))} -> CANCELADO | F54: {=INDEX('MTA 28-09'!I:I,MATCH(B54,'MTA 28-09'!A:A,0))} | G54: {=INDEX('MTA 28-09'!J:J,MATCH(B54,'MTA 28-09'!A:A,0))} | L54: {=INDEX('MTA 28-09'!S:S,MATCH(B54,'MTA 28-09'!A:A,0))} -> C-95M | M54: {=INDEX('MTA 28-09'!T:T,MATCH(B54,'MTA 28-09'!A:A,0))} -> REQUISIÇÃO SERVIÇO | N54: {=INDEX('MTA 28-09'!U:U,MATCH(B54,'MTA 28-09'!A:A,0))} -> RG Fuel Pump 4 EA (1/2) | O54: {=INDEX('MTA 28-09'!AC:AC,MATCH(B54,'MTA 28-09'!A:A,0))} -> - | P54: {=INDEX('MTA 28-09'!N:N,MATCH(B54,'MTA 28-09'!A:A,0))} -> CABW | Q54: {=INDEX('MTA 28-09'!Z:Z,MATCH(B54,'MTA 28-09'!A:A,0))} -> 339039 | R54: {=INDEX('MTA 28-09'!L:L,MATCH(B54,'MTA 28-09'!A:A,0))} -> A | S54: {=INDEX('MTA 28-09'!X:X,MATCH(B54,'MTA 28-09'!A:A,0))} -> REQUISIÇÃO | T54: {=INDEX('MTA 28-09'!W:W,MATCH(B54,'MTA 28-09'!A:A,0))} -> SIM | U54: {=INDEX('MTA 28-09'!AE:AE,MATCH(B54,'MTA 28-09'!A:A,0))} -> 46169
A55: C-95M | B55: 10700 | C55: {=INDEX('MTA 28-09'!B:B,MATCH(B55,'MTA 28-09'!A:A,0))} -> SIM | D55: {=INDEX('MTA 28-09'!D:D,MATCH(B55,'MTA 28-09'!A:A,0))} -> 2048 | E55: {=INDEX('MTA 28-09'!F:F,MATCH(B55,'MTA 28-09'!A:A,0))} -> ATENDIDO | F55: {=INDEX('MTA 28-09'!I:I,MATCH(B55,'MTA 28-09'!A:A,0))} -> 46073 | G55: {=INDEX('MTA 28-09'!J:J,MATCH(B55,'MTA 28-09'!A:A,0))} -> C26039 | L55: {=INDEX('MTA 28-09'!S:S,MATCH(B55,'MTA 28-09'!A:A,0))} -> C-95M | M55: {=INDEX('MTA 28-09'!T:T,MATCH(B55,'MTA 28-09'!A:A,0))} -> REQUISIÇÃO SERVIÇO | N55: {=INDEX('MTA 28-09'!U:U,MATCH(B55,'MTA 28-09'!A:A,0))} -> Reparo de CTVR 2 EA (1/3) | O55: {=INDEX('MTA 28-09'!AC:AC,MATCH(B55,'MTA 28-09'!A:A,0))} -> 110238 | P55: {=INDEX('MTA 28-09'!N:N,MATCH(B55,'MTA 28-09'!A:A,0))} -> CABW | Q55: {=INDEX('MTA 28-09'!Z:Z,MATCH(B55,'MTA 28-09'!A:A,0))} -> 339039 | R55: {=INDEX('MTA 28-09'!L:L,MATCH(B55,'MTA 28-09'!A:A,0))} -> A | S55: {=INDEX('MTA 28-09'!X:X,MATCH(B55,'MTA 28-09'!A:A,0))} -> REQUISIÇÃO | T55: {=INDEX('MTA 28-09'!W:W,MATCH(B55,'MTA 28-09'!A:A,0))} -> SIM | U55: {=INDEX('MTA 28-09'!AE:AE,MATCH(B55,'MTA 28-09'!A:A,0))} -> 46260
A56: C-95M | B56: 10720 | C56: {=INDEX('MTA 28-09'!B:B,MATCH(B56,'MTA 28-09'!A:A,0))} -> SIM | D56: {=INDEX('MTA 28-09'!D:D,MATCH(B56,'MTA 28-09'!A:A,0))} -> 2048 | E56: {=INDEX('MTA 28-09'!F:F,MATCH(B56,'MTA 28-09'!A:A,0))} -> ATENDIDO | F56: {=INDEX('MTA 28-09'!I:I,MATCH(B56,'MTA 28-09'!A:A,0))} -> 46265 | G56: {=INDEX('MTA 28-09'!J:J,MATCH(B56,'MTA 28-09'!A:A,0))} -> C26195 | L56: {=INDEX('MTA 28-09'!S:S,MATCH(B56,'MTA 28-09'!A:A,0))} -> C-95M | M56: {=INDEX('MTA 28-09'!T:T,MATCH(B56,'MTA 28-09'!A:A,0))} -> REQUISIÇÃO SERVIÇO | N56: {=INDEX('MTA 28-09'!U:U,MATCH(B56,'MTA 28-09'!A:A,0))} -> Reparo de PTVR 3 EA (1/2) | O56: {=INDEX('MTA 28-09'!AC:AC,MATCH(B56,'MTA 28-09'!A:A,0))} -> 107231.58 | P56: {=INDEX('MTA 28-09'!N:N,MATCH(B56,'MTA 28-09'!A:A,0))} -> CABW | Q56: {=INDEX('MTA 28-09'!Z:Z,MATCH(B56,'MTA 28-09'!A:A,0))} -> 339039 | R56: {=INDEX('MTA 28-09'!L:L,MATCH(B56,'MTA 28-09'!A:A,0))} -> A | S56: {=INDEX('MTA 28-09'!X:X,MATCH(B56,'MTA 28-09'!A:A,0))} -> REQUISIÇÃO | T56: {=INDEX('MTA 28-09'!W:W,MATCH(B56,'MTA 28-09'!A:A,0))} -> SIM | U56: {=INDEX('MTA 28-09'!AE:AE,MATCH(B56,'MTA 28-09'!A:A,0))} -> 46169
A57: PN | B57: 10740 | C57: {=INDEX('MTA 28-09'!B:B,MATCH(B57,'MTA 28-09'!A:A,0))} -> SIM | D57: {=INDEX('MTA 28-09'!D:D,MATCH(B57,'MTA 28-09'!A:A,0))} -> 2048 | E57: {=INDEX('MTA 28-09'!F:F,MATCH(B57,'MTA 28-09'!A:A,0))} | F57: {=INDEX('MTA 28-09'!I:I,MATCH(B57,'MTA 28-09'!A:A,0))} | G57: {=INDEX('MTA 28-09'!J:J,MATCH(B57,'MTA 28-09'!A:A,0))} | I57: REMANEJAR | L57: {=INDEX('MTA 28-09'!S:S,MATCH(B57,'MTA 28-09'!A:A,0))} -> APOIO | M57: {=INDEX('MTA 28-09'!T:T,MATCH(B57,'MTA 28-09'!A:A,0))} -> ADQUIRIR PNEUS DE AVIAÇÃO | N57: {=INDEX('MTA 28-09'!U:U,MATCH(B57,'MTA 28-09'!A:A,0))} -> Aquisição de Pneu de Aviação - ARP - 1/5 | O57: {=INDEX('MTA 28-09'!AC:AC,MATCH(B57,'MTA 28-09'!A:A,0))} -> 538000 | P57: {=INDEX('MTA 28-09'!N:N,MATCH(B57,'MTA 28-09'!A:A,0))} -> CELOG | Q57: {=INDEX('MTA 28-09'!Z:Z,MATCH(B57,'MTA 28-09'!A:A,0))} -> 339030 | R57: {=INDEX('MTA 28-09'!L:L,MATCH(B57,'MTA 28-09'!A:A,0))} -> A | S57: {=INDEX('MTA 28-09'!X:X,MATCH(B57,'MTA 28-09'!A:A,0))} -> REQUISIÇÃO | T57: {=INDEX('MTA 28-09'!W:W,MATCH(B57,'MTA 28-09'!A:A,0))} -> NÃO | U57: {=INDEX('MTA 28-09'!AE:AE,MATCH(B57,'MTA 28-09'!A:A,0))} -> 46352
A58: PN | B58: 10741 | C58: {=INDEX('MTA 28-09'!B:B,MATCH(B58,'MTA 28-09'!A:A,0))} -> SIM | D58: {=INDEX('MTA 28-09'!D:D,MATCH(B58,'MTA 28-09'!A:A,0))} -> 2048 | E58: {=INDEX('MTA 28-09'!F:F,MATCH(B58,'MTA 28-09'!A:A,0))} -> ATENDIDO | F58: {=INDEX('MTA 28-09'!I:I,MATCH(B58,'MTA 28-09'!A:A,0))} -> 46042 | G58: {=INDEX('MTA 28-09'!J:J,MATCH(B58,'MTA 28-09'!A:A,0))} -> C26055 | H58: 1 | L58: {=INDEX('MTA 28-09'!S:S,MATCH(B58,'MTA 28-09'!A:A,0))} -> APOIO | M58: {=INDEX('MTA 28-09'!T:T,MATCH(B58,'MTA 28-09'!A:A,0))} -> ADQUIRIR PNEUS DE AVIAÇÃO | N58: {=INDEX('MTA 28-09'!U:U,MATCH(B58,'MTA 28-09'!A:A,0))} -> Aquisição de Pneu de Aviação - ARP - 1/5 | O58: {=INDEX('MTA 28-09'!AC:AC,MATCH(B58,'MTA 28-09'!A:A,0))} -> 462000 | P58: {=INDEX('MTA 28-09'!N:N,MATCH(B58,'MTA 28-09'!A:A,0))} -> CELOG | Q58: {=INDEX('MTA 28-09'!Z:Z,MATCH(B58,'MTA 28-09'!A:A,0))} -> 339030 | R58: {=INDEX('MTA 28-09'!L:L,MATCH(B58,'MTA 28-09'!A:A,0))} -> A | S58: {=INDEX('MTA 28-09'!X:X,MATCH(B58,'MTA 28-09'!A:A,0))} -> REQUISIÇÃO | T58: {=INDEX('MTA 28-09'!W:W,MATCH(B58,'MTA 28-09'!A:A,0))} -> NÃO | U58: {=INDEX('MTA 28-09'!AE:AE,MATCH(B58,'MTA 28-09'!A:A,0))} -> 46107
A59: C-98 | B59: 10760 | C59: {=INDEX('MTA 28-09'!B:B,MATCH(B59,'MTA 28-09'!A:A,0))} -> SIM | D59: {=INDEX('MTA 28-09'!D:D,MATCH(B59,'MTA 28-09'!A:A,0))} -> 2048 | E59: {=INDEX('MTA 28-09'!F:F,MATCH(B59,'MTA 28-09'!A:A,0))} -> CANCELADO | F59: {=INDEX('MTA 28-09'!I:I,MATCH(B59,'MTA 28-09'!A:A,0))} | G59: {=INDEX('MTA 28-09'!J:J,MATCH(B59,'MTA 28-09'!A:A,0))} | L59: {=INDEX('MTA 28-09'!S:S,MATCH(B59,'MTA 28-09'!A:A,0))} -> C-98 | M59: {=INDEX('MTA 28-09'!T:T,MATCH(B59,'MTA 28-09'!A:A,0))} -> Requisição CABW | N59: {=INDEX('MTA 28-09'!U:U,MATCH(B59,'MTA 28-09'!A:A,0))} -> Material reparo acessórios PT6A-114A (1/3) | O59: {=INDEX('MTA 28-09'!AC:AC,MATCH(B59,'MTA 28-09'!A:A,0))} -> - | P59: {=INDEX('MTA 28-09'!N:N,MATCH(B59,'MTA 28-09'!A:A,0))} -> CABW | Q59: {=INDEX('MTA 28-09'!Z:Z,MATCH(B59,'MTA 28-09'!A:A,0))} -> 339030 | R59: {=INDEX('MTA 28-09'!L:L,MATCH(B59,'MTA 28-09'!A:A,0))} -> A | S59: {=INDEX('MTA 28-09'!X:X,MATCH(B59,'MTA 28-09'!A:A,0))} -> REQUISIÇÃO | T59: {=INDEX('MTA 28-09'!W:W,MATCH(B59,'MTA 28-09'!A:A,0))} -> SIM | U59: {=INDEX('MTA 28-09'!AE:AE,MATCH(B59,'MTA 28-09'!A:A,0))} -> 46382
A60: C-98 | B60: 10780 | C60: {=INDEX('MTA 28-09'!B:B,MATCH(B60,'MTA 28-09'!A:A,0))} -> SIM | D60: {=INDEX('MTA 28-09'!D:D,MATCH(B60,'MTA 28-09'!A:A,0))} -> 2048 | E60: {=INDEX('MTA 28-09'!F:F,MATCH(B60,'MTA 28-09'!A:A,0))} -> CANCELADO | F60: {=INDEX('MTA 28-09'!I:I,MATCH(B60,'MTA 28-09'!A:A,0))} | G60: {=INDEX('MTA 28-09'!J:J,MATCH(B60,'MTA 28-09'!A:A,0))} | L60: {=INDEX('MTA 28-09'!S:S,MATCH(B60,'MTA 28-09'!A:A,0))} -> C-98 | M60: {=INDEX('MTA 28-09'!T:T,MATCH(B60,'MTA 28-09'!A:A,0))} -> REQUISIÇÃO SERVIÇO | N60: {=INDEX('MTA 28-09'!U:U,MATCH(B60,'MTA 28-09'!A:A,0))} -> RG FCU 3 EA (1/2) | O60: {=INDEX('MTA 28-09'!AC:AC,MATCH(B60,'MTA 28-09'!A:A,0))} -> - | P60: {=INDEX('MTA 28-09'!N:N,MATCH(B60,'MTA 28-09'!A:A,0))} -> CABW | Q60: {=INDEX('MTA 28-09'!Z:Z,MATCH(B60,'MTA 28-09'!A:A,0))} -> 339039 | R60: {=INDEX('MTA 28-09'!L:L,MATCH(B60,'MTA 28-09'!A:A,0))} -> A | S60: {=INDEX('MTA 28-09'!X:X,MATCH(B60,'MTA 28-09'!A:A,0))} -> REQUISIÇÃO | T60: {=INDEX('MTA 28-09'!W:W,MATCH(B60,'MTA 28-09'!A:A,0))} -> SIM | U60: {=INDEX('MTA 28-09'!AE:AE,MATCH(B60,'MTA 28-09'!A:A,0))} -> 46169
A61: C-98 | B61: 10800 | C61: {=INDEX('MTA 28-09'!B:B,MATCH(B61,'MTA 28-09'!A:A,0))} -> SIM | D61: {=INDEX('MTA 28-09'!D:D,MATCH(B61,'MTA 28-09'!A:A,0))} -> 2048 | E61: {=INDEX('MTA 28-09'!F:F,MATCH(B61,'MTA 28-09'!A:A,0))} -> CANCELADO | F61: {=INDEX('MTA 28-09'!I:I,MATCH(B61,'MTA 28-09'!A:A,0))} | G61: {=INDEX('MTA 28-09'!J:J,MATCH(B61,'MTA 28-09'!A:A,0))} | L61: {=INDEX('MTA 28-09'!S:S,MATCH(B61,'MTA 28-09'!A:A,0))} -> C-98 | M61: {=INDEX('MTA 28-09'!T:T,MATCH(B61,'MTA 28-09'!A:A,0))} -> REQUISIÇÃO SERVIÇO | N61: {=INDEX('MTA 28-09'!U:U,MATCH(B61,'MTA 28-09'!A:A,0))} -> RG Fuel Pump 5 EA (1/1) | O61: {=INDEX('MTA 28-09'!AC:AC,MATCH(B61,'MTA 28-09'!A:A,0))} -> - | P61: {=INDEX('MTA 28-09'!N:N,MATCH(B61,'MTA 28-09'!A:A,0))} -> CABW | Q61: {=INDEX('MTA 28-09'!Z:Z,MATCH(B61,'MTA 28-09'!A:A,0))} -> 339039 | R61: {=INDEX('MTA 28-09'!L:L,MATCH(B61,'MTA 28-09'!A:A,0))} -> A | S61: {=INDEX('MTA 28-09'!X:X,MATCH(B61,'MTA 28-09'!A:A,0))} -> REQUISIÇÃO | T61: {=INDEX('MTA 28-09'!W:W,MATCH(B61,'MTA 28-09'!A:A,0))} -> SIM | U61: {=INDEX('MTA 28-09'!AE:AE,MATCH(B61,'MTA 28-09'!A:A,0))} -> 46169
A62: SSS | B62: 10820 | C62: {=INDEX('MTA 28-09'!B:B,MATCH(B62,'MTA 28-09'!A:A,0))} -> SIM | D62: {=INDEX('MTA 28-09'!D:D,MATCH(B62,'MTA 28-09'!A:A,0))} -> 2048 | E62: {=INDEX('MTA 28-09'!F:F,MATCH(B62,'MTA 28-09'!A:A,0))} | F62: {=INDEX('MTA 28-09'!I:I,MATCH(B62,'MTA 28-09'!A:A,0))} | G62: {=INDEX('MTA 28-09'!J:J,MATCH(B62,'MTA 28-09'!A:A,0))} | H62: 46276 | I62: Atender novembro | L62: {=INDEX('MTA 28-09'!S:S,MATCH(B62,'MTA 28-09'!A:A,0))} -> APOIO | M62: {=INDEX('MTA 28-09'!T:T,MATCH(B62,'MTA 28-09'!A:A,0))} -> REQUISIÇÃO SSS TLV | N62: {=INDEX('MTA 28-09'!U:U,MATCH(B62,'MTA 28-09'!A:A,0))} -> AQUISIÇÃO ITENS SSS COM TEMPO LIMITE DE VIDA (FMS) | O62: {=INDEX('MTA 28-09'!AC:AC,MATCH(B62,'MTA 28-09'!A:A,0))} -> 364240.65 | P62: {=INDEX('MTA 28-09'!N:N,MATCH(B62,'MTA 28-09'!A:A,0))} -> FMS | Q62: {=INDEX('MTA 28-09'!Z:Z,MATCH(B62,'MTA 28-09'!A:A,0))} -> 339030 | R62: {=INDEX('MTA 28-09'!L:L,MATCH(B62,'MTA 28-09'!A:A,0))} -> A | S62: {=INDEX('MTA 28-09'!X:X,MATCH(B62,'MTA 28-09'!A:A,0))} -> REQUISIÇÃO | T62: {=INDEX('MTA 28-09'!W:W,MATCH(B62,'MTA 28-09'!A:A,0))} -> NÃO | U62: {=INDEX('MTA 28-09'!AE:AE,MATCH(B62,'MTA 28-09'!A:A,0))} -> 46352
A63: SSS | B63: 10840 | C63: {=INDEX('MTA 28-09'!B:B,MATCH(B63,'MTA 28-09'!A:A,0))} -> SIM | D63: {=INDEX('MTA 28-09'!D:D,MATCH(B63,'MTA 28-09'!A:A,0))} -> 2048 | E63: {=INDEX('MTA 28-09'!F:F,MATCH(B63,'MTA 28-09'!A:A,0))} | F63: {=INDEX('MTA 28-09'!I:I,MATCH(B63,'MTA 28-09'!A:A,0))} | G63: {=INDEX('MTA 28-09'!J:J,MATCH(B63,'MTA 28-09'!A:A,0))} | H63: 46276 | I63: Atender | L63: {=INDEX('MTA 28-09'!S:S,MATCH(B63,'MTA 28-09'!A:A,0))} -> APOIO | M63: {=INDEX('MTA 28-09'!T:T,MATCH(B63,'MTA 28-09'!A:A,0))} -> REQUISIÇÃO SSS TLV | N63: {=INDEX('MTA 28-09'!U:U,MATCH(B63,'MTA 28-09'!A:A,0))} -> AQUISIÇÃO ITENS SSS COM TEMPO LIMITE DE VIDA (CELOG) | O63: {=INDEX('MTA 28-09'!AC:AC,MATCH(B63,'MTA 28-09'!A:A,0))} -> 216272.2 | P63: {=INDEX('MTA 28-09'!N:N,MATCH(B63,'MTA 28-09'!A:A,0))} -> CELOG | Q63: {=INDEX('MTA 28-09'!Z:Z,MATCH(B63,'MTA 28-09'!A:A,0))} -> 339030 | R63: {=INDEX('MTA 28-09'!L:L,MATCH(B63,'MTA 28-09'!A:A,0))} -> A | S63: {=INDEX('MTA 28-09'!X:X,MATCH(B63,'MTA 28-09'!A:A,0))} -> REQUISIÇÃO | T63: {=INDEX('MTA 28-09'!W:W,MATCH(B63,'MTA 28-09'!A:A,0))} -> NÃO | U63: {=INDEX('MTA 28-09'!AE:AE,MATCH(B63,'MTA 28-09'!A:A,0))} -> 46352
A64: SSS | B64: 10841 | C64: {=INDEX('MTA 28-09'!B:B,MATCH(B64,'MTA 28-09'!A:A,0))} -> SIM | D64: {=INDEX('MTA 28-09'!D:D,MATCH(B64,'MTA 28-09'!A:A,0))} -> 2048 | E64: {=INDEX('MTA 28-09'!F:F,MATCH(B64,'MTA 28-09'!A:A,0))} -> ATENDIDO | F64: {=INDEX('MTA 28-09'!I:I,MATCH(B64,'MTA 28-09'!A:A,0))} -> 46279 | G64: {=INDEX('MTA 28-09'!J:J,MATCH(B64,'MTA 28-09'!A:A,0))} -> C26455 | M64: {=INDEX('MTA 28-09'!T:T,MATCH(B64,'MTA 28-09'!A:A,0))} -> REQUISIÇÃO SSS TLV | N64: {=INDEX('MTA 28-09'!U:U,MATCH(B64,'MTA 28-09'!A:A,0))} -> AQUISIÇÃO ITENS SSS COM TEMPO LIMITE DE VIDA (CELOG) | O64: {=INDEX('MTA 28-09'!AC:AC,MATCH(B64,'MTA 28-09'!A:A,0))} -> 3581.99 | P64: {=INDEX('MTA 28-09'!N:N,MATCH(B64,'MTA 28-09'!A:A,0))} -> CELOG | Q64: {=INDEX('MTA 28-09'!Z:Z,MATCH(B64,'MTA 28-09'!A:A,0))} -> 339030 | R64: {=INDEX('MTA 28-09'!L:L,MATCH(B64,'MTA 28-09'!A:A,0))} -> A | S64: {=INDEX('MTA 28-09'!X:X,MATCH(B64,'MTA 28-09'!A:A,0))} -> REQUISIÇÃO | T64: {=INDEX('MTA 28-09'!W:W,MATCH(B64,'MTA 28-09'!A:A,0))} -> NÃO | U64: {=INDEX('MTA 28-09'!AE:AE,MATCH(B64,'MTA 28-09'!A:A,0))} -> 46352
A65: SSS | B65: 10860 | C65: {=INDEX('MTA 28-09'!B:B,MATCH(B65,'MTA 28-09'!A:A,0))} -> SIM | D65: {=INDEX('MTA 28-09'!D:D,MATCH(B65,'MTA 28-09'!A:A,0))} -> 2048 | E65: {=INDEX('MTA 28-09'!F:F,MATCH(B65,'MTA 28-09'!A:A,0))} -> ATENDIDO | F65: {=INDEX('MTA 28-09'!I:I,MATCH(B65,'MTA 28-09'!A:A,0))} -> 46073 | G65: {=INDEX('MTA 28-09'!J:J,MATCH(B65,'MTA 28-09'!A:A,0))} -> C26033 | H65: 1 | L65: {=INDEX('MTA 28-09'!S:S,MATCH(B65,'MTA 28-09'!A:A,0))} -> APOIO | M65: {=INDEX('MTA 28-09'!T:T,MATCH(B65,'MTA 28-09'!A:A,0))} -> REQUISIÇÃO PTA SSS | N65: {=INDEX('MTA 28-09'!U:U,MATCH(B65,'MTA 28-09'!A:A,0))} -> AQUISIÇÃO ITENS SSS CUMPRIR PTA (CABW) 2/2 | O65: {=INDEX('MTA 28-09'!AC:AC,MATCH(B65,'MTA 28-09'!A:A,0))} -> 760240.53 | P65: {=INDEX('MTA 28-09'!N:N,MATCH(B65,'MTA 28-09'!A:A,0))} -> CABW | Q65: {=INDEX('MTA 28-09'!Z:Z,MATCH(B65,'MTA 28-09'!A:A,0))} -> 339030 | R65: {=INDEX('MTA 28-09'!L:L,MATCH(B65,'MTA 28-09'!A:A,0))} -> A | S65: {=INDEX('MTA 28-09'!X:X,MATCH(B65,'MTA 28-09'!A:A,0))} -> REQUISIÇÃO | T65: {=INDEX('MTA 28-09'!W:W,MATCH(B65,'MTA 28-09'!A:A,0))} -> NÃO | U65: {=INDEX('MTA 28-09'!AE:AE,MATCH(B65,'MTA 28-09'!A:A,0))} -> 46138
A66: SSS | B66: 10880 | C66: {=INDEX('MTA 28-09'!B:B,MATCH(B66,'MTA 28-09'!A:A,0))} -> NÃO | D66: {=INDEX('MTA 28-09'!D:D,MATCH(B66,'MTA 28-09'!A:A,0))} | E66: {=INDEX('MTA 28-09'!F:F,MATCH(B66,'MTA 28-09'!A:A,0))} | F66: {=INDEX('MTA 28-09'!I:I,MATCH(B66,'MTA 28-09'!A:A,0))} | G66: {=INDEX('MTA 28-09'!J:J,MATCH(B66,'MTA 28-09'!A:A,0))} | L66: {=INDEX('MTA 28-09'!S:S,MATCH(B66,'MTA 28-09'!A:A,0))} -> APOIO | M66: {=INDEX('MTA 28-09'!T:T,MATCH(B66,'MTA 28-09'!A:A,0))} -> REQUISIÇÃO PTA SSS | N66: {=INDEX('MTA 28-09'!U:U,MATCH(B66,'MTA 28-09'!A:A,0))} -> AQUISIÇÃO ITENS SSS CUMPRIR PTA (FMS) | O66: {=INDEX('MTA 28-09'!AC:AC,MATCH(B66,'MTA 28-09'!A:A,0))} -> 139975.96 | P66: {=INDEX('MTA 28-09'!N:N,MATCH(B66,'MTA 28-09'!A:A,0))} -> FMS | Q66: {=INDEX('MTA 28-09'!Z:Z,MATCH(B66,'MTA 28-09'!A:A,0))} -> 339030 | R66: {=INDEX('MTA 28-09'!L:L,MATCH(B66,'MTA 28-09'!A:A,0))} -> B | S66: {=INDEX('MTA 28-09'!X:X,MATCH(B66,'MTA 28-09'!A:A,0))} -> REQUISIÇÃO | T66: {=INDEX('MTA 28-09'!W:W,MATCH(B66,'MTA 28-09'!A:A,0))} -> NÃO | U66: {=INDEX('MTA 28-09'!AE:AE,MATCH(B66,'MTA 28-09'!A:A,0))} -> 46352
A67: SSS | B67: 10881 | C67: {=INDEX('MTA 28-09'!B:B,MATCH(B67,'MTA 28-09'!A:A,0))} -> SIM | D67: {=INDEX('MTA 28-09'!D:D,MATCH(B67,'MTA 28-09'!A:A,0))} -> 20XV | E67: {=INDEX('MTA 28-09'!F:F,MATCH(B67,'MTA 28-09'!A:A,0))} -> ATENDIDO | F67: {=INDEX('MTA 28-09'!I:I,MATCH(B67,'MTA 28-09'!A:A,0))} -> 46224 | G67: {=INDEX('MTA 28-09'!J:J,MATCH(B67,'MTA 28-09'!A:A,0))} -> C26154 | L67: {=INDEX('MTA 28-09'!S:S,MATCH(B67,'MTA 28-09'!A:A,0))} -> APOIO | M67: {=INDEX('MTA 28-09'!T:T,MATCH(B67,'MTA 28-09'!A:A,0))} -> REQUISIÇÃO PTA SSS | N67: {=INDEX('MTA 28-09'!U:U,MATCH(B67,'MTA 28-09'!A:A,0))} -> AQUISIÇÃO ITENS SSS CUMPRIR PTA (FMS) | O67: {=INDEX('MTA 28-09'!AC:AC,MATCH(B67,'MTA 28-09'!A:A,0))} -> 660464.25 | P67: {=INDEX('MTA 28-09'!N:N,MATCH(B67,'MTA 28-09'!A:A,0))} -> FMS | Q67: {=INDEX('MTA 28-09'!Z:Z,MATCH(B67,'MTA 28-09'!A:A,0))} -> 339030 | R67: {=INDEX('MTA 28-09'!L:L,MATCH(B67,'MTA 28-09'!A:A,0))} -> A | S67: {=INDEX('MTA 28-09'!X:X,MATCH(B67,'MTA 28-09'!A:A,0))} -> REQUISIÇÃO | T67: {=INDEX('MTA 28-09'!W:W,MATCH(B67,'MTA 28-09'!A:A,0))} -> NÃO | U67: {=INDEX('MTA 28-09'!AE:AE,MATCH(B67,'MTA 28-09'!A:A,0))} -> 46352
A68: SSS | B68: 10900 | C68: {=INDEX('MTA 28-09'!B:B,MATCH(B68,'MTA 28-09'!A:A,0))} -> NÃO | D68: {=INDEX('MTA 28-09'!D:D,MATCH(B68,'MTA 28-09'!A:A,0))} | E68: {=INDEX('MTA 28-09'!F:F,MATCH(B68,'MTA 28-09'!A:A,0))} -> BLOQUEIO | F68: {=INDEX('MTA 28-09'!I:I,MATCH(B68,'MTA 28-09'!A:A,0))} | G68: {=INDEX('MTA 28-09'!J:J,MATCH(B68,'MTA 28-09'!A:A,0))} | L68: {=INDEX('MTA 28-09'!S:S,MATCH(B68,'MTA 28-09'!A:A,0))} -> APOIO | M68: {=INDEX('MTA 28-09'!T:T,MATCH(B68,'MTA 28-09'!A:A,0))} -> REQUISIÇÃO LOTAÇÃO SSS | N68: {=INDEX('MTA 28-09'!U:U,MATCH(B68,'MTA 28-09'!A:A,0))} -> AQUISIÇÃO ITENS SSS ATENDER 100% DA LOTAÇÃO (FMS) | O68: {=INDEX('MTA 28-09'!AC:AC,MATCH(B68,'MTA 28-09'!A:A,0))} -> 1488230 | P68: {=INDEX('MTA 28-09'!N:N,MATCH(B68,'MTA 28-09'!A:A,0))} -> FMS | Q68: {=INDEX('MTA 28-09'!Z:Z,MATCH(B68,'MTA 28-09'!A:A,0))} -> 339030 | R68: {=INDEX('MTA 28-09'!L:L,MATCH(B68,'MTA 28-09'!A:A,0))} -> B | S68: {=INDEX('MTA 28-09'!X:X,MATCH(B68,'MTA 28-09'!A:A,0))} -> REQUISIÇÃO | T68: {=INDEX('MTA 28-09'!W:W,MATCH(B68,'MTA 28-09'!A:A,0))} -> NÃO | U68: {=INDEX('MTA 28-09'!AE:AE,MATCH(B68,'MTA 28-09'!A:A,0))} -> 46291
A69: A-29 | B69: 10920 | C69: {=INDEX('MTA 28-09'!B:B,MATCH(B69,'MTA 28-09'!A:A,0))} -> SIM | D69: {=INDEX('MTA 28-09'!D:D,MATCH(B69,'MTA 28-09'!A:A,0))} -> 2048 | E69: {=INDEX('MTA 28-09'!F:F,MATCH(B69,'MTA 28-09'!A:A,0))} -> ATENDIDO | F69: {=INDEX('MTA 28-09'!I:I,MATCH(B69,'MTA 28-09'!A:A,0))} -> 46098 | G69: {=INDEX('MTA 28-09'!J:J,MATCH(B69,'MTA 28-09'!A:A,0))} -> C26156 | H69: 1 | L69: {=INDEX('MTA 28-09'!S:S,MATCH(B69,'MTA 28-09'!A:A,0))} -> A-29 | M69: {=INDEX('MTA 28-09'!T:T,MATCH(B69,'MTA 28-09'!A:A,0))} -> CTT 102/CELOG-PAMALS/2023 – EMBRAER - PSLI | N69: {=INDEX('MTA 28-09'!U:U,MATCH(B69,'MTA 28-09'!A:A,0))} -> Parcela Fixa 03/12 | O69: {=INDEX('MTA 28-09'!AC:AC,MATCH(B69,'MTA 28-09'!A:A,0))} -> 2310000 | P69: {=INDEX('MTA 28-09'!N:N,MATCH(B69,'MTA 28-09'!A:A,0))} -> CELOG | Q69: {=INDEX('MTA 28-09'!Z:Z,MATCH(B69,'MTA 28-09'!A:A,0))} -> 339039 | R69: {=INDEX('MTA 28-09'!L:L,MATCH(B69,'MTA 28-09'!A:A,0))} -> A | S69: {=INDEX('MTA 28-09'!X:X,MATCH(B69,'MTA 28-09'!A:A,0))} -> PARCELA FIXA | T69: {=INDEX('MTA 28-09'!W:W,MATCH(B69,'MTA 28-09'!A:A,0))} -> Não | U69: {=INDEX('MTA 28-09'!AE:AE,MATCH(B69,'MTA 28-09'!A:A,0))} -> 46168
A70: C-97 | B70: 10940 | C70: {=INDEX('MTA 28-09'!B:B,MATCH(B70,'MTA 28-09'!A:A,0))} -> SIM | D70: {=INDEX('MTA 28-09'!D:D,MATCH(B70,'MTA 28-09'!A:A,0))} -> 2048 | E70: {=INDEX('MTA 28-09'!F:F,MATCH(B70,'MTA 28-09'!A:A,0))} -> ATENDIDO | F70: {=INDEX('MTA 28-09'!I:I,MATCH(B70,'MTA 28-09'!A:A,0))} -> 46098 | G70: {=INDEX('MTA 28-09'!J:J,MATCH(B70,'MTA 28-09'!A:A,0))} -> C26154 | H70: 1 | L70: {=INDEX('MTA 28-09'!S:S,MATCH(B70,'MTA 28-09'!A:A,0))} -> C-97 | M70: {=INDEX('MTA 28-09'!T:T,MATCH(B70,'MTA 28-09'!A:A,0))} -> CTT 096/CAE-PAMALS/2021 - CLS C-97 | N70: {=INDEX('MTA 28-09'!U:U,MATCH(B70,'MTA 28-09'!A:A,0))} -> Parcela Fixa 03/12 | O70: {=INDEX('MTA 28-09'!AC:AC,MATCH(B70,'MTA 28-09'!A:A,0))} -> 332718.75 | P70: {=INDEX('MTA 28-09'!N:N,MATCH(B70,'MTA 28-09'!A:A,0))} -> CELOG | Q70: {=INDEX('MTA 28-09'!Z:Z,MATCH(B70,'MTA 28-09'!A:A,0))} -> 339039 | R70: {=INDEX('MTA 28-09'!L:L,MATCH(B70,'MTA 28-09'!A:A,0))} -> A | S70: {=INDEX('MTA 28-09'!X:X,MATCH(B70,'MTA 28-09'!A:A,0))} -> PARCELA FIXA | T70: {=INDEX('MTA 28-09'!W:W,MATCH(B70,'MTA 28-09'!A:A,0))} -> Não | U70: {=INDEX('MTA 28-09'!AE:AE,MATCH(B70,'MTA 28-09'!A:A,0))} -> 46168
A71: C-97 | B71: 10941 | C71: {=INDEX('MTA 28-09'!B:B,MATCH(B71,'MTA 28-09'!A:A,0))} -> SIM | D71: {=INDEX('MTA 28-09'!D:D,MATCH(B71,'MTA 28-09'!A:A,0))} -> 2048 | E71: {=INDEX('MTA 28-09'!F:F,MATCH(B71,'MTA 28-09'!A:A,0))} -> ATENDIDO | F71: {=INDEX('MTA 28-09'!I:I,MATCH(B71,'MTA 28-09'!A:A,0))} -> 46098 | G71: {=INDEX('MTA 28-09'!J:J,MATCH(B71,'MTA 28-09'!A:A,0))} -> C26154 | L71: {=INDEX('MTA 28-09'!S:S,MATCH(B71,'MTA 28-09'!A:A,0))} -> C-97 | M71: {=INDEX('MTA 28-09'!T:T,MATCH(B71,'MTA 28-09'!A:A,0))} -> CTT 096/CAE-PAMALS/2021 - CLS C-97 | N71: {=INDEX('MTA 28-09'!U:U,MATCH(B71,'MTA 28-09'!A:A,0))} -> Parcela Fixa 03/12 | O71: {=INDEX('MTA 28-09'!AC:AC,MATCH(B71,'MTA 28-09'!A:A,0))} -> 28040.56 | P71: {=INDEX('MTA 28-09'!N:N,MATCH(B71,'MTA 28-09'!A:A,0))} -> CELOG | Q71: {=INDEX('MTA 28-09'!Z:Z,MATCH(B71,'MTA 28-09'!A:A,0))} -> 339039 | R71: {=INDEX('MTA 28-09'!L:L,MATCH(B71,'MTA 28-09'!A:A,0))} -> A | S71: {=INDEX('MTA 28-09'!X:X,MATCH(B71,'MTA 28-09'!A:A,0))} -> PARCELA FIXA | T71: {=INDEX('MTA 28-09'!W:W,MATCH(B71,'MTA 28-09'!A:A,0))} -> Não | U71: {=INDEX('MTA 28-09'!AE:AE,MATCH(B71,'MTA 28-09'!A:A,0))} -> 46168
A72: A-29 | B72: 10960 | C72: {=INDEX('MTA 28-09'!B:B,MATCH(B72,'MTA 28-09'!A:A,0))} -> SIM | D72: {=INDEX('MTA 28-09'!D:D,MATCH(B72,'MTA 28-09'!A:A,0))} -> 2048 | E72: {=INDEX('MTA 28-09'!F:F,MATCH(B72,'MTA 28-09'!A:A,0))} -> ATENDIDO | F72: {=INDEX('MTA 28-09'!I:I,MATCH(B72,'MTA 28-09'!A:A,0))} -> 46118 | G72: {=INDEX('MTA 28-09'!J:J,MATCH(B72,'MTA 28-09'!A:A,0))} -> C26192 | H72: email do dia 19/03 | L72: {=INDEX('MTA 28-09'!S:S,MATCH(B72,'MTA 28-09'!A:A,0))} -> A-29 | M72: {=INDEX('MTA 28-09'!T:T,MATCH(B72,'MTA 28-09'!A:A,0))} -> CNT 040/CELOG-PAMALS/2022 - AEL - CLS AVIONICO | N72: {=INDEX('MTA 28-09'!U:U,MATCH(B72,'MTA 28-09'!A:A,0))} -> Hora de Voo 02/10 - 1000 HV | O72: {=INDEX('MTA 28-09'!AC:AC,MATCH(B72,'MTA 28-09'!A:A,0))} -> 853419.45 | P72: {=INDEX('MTA 28-09'!N:N,MATCH(B72,'MTA 28-09'!A:A,0))} -> CELOG | Q72: {=INDEX('MTA 28-09'!Z:Z,MATCH(B72,'MTA 28-09'!A:A,0))} -> 339039 | R72: {=INDEX('MTA 28-09'!L:L,MATCH(B72,'MTA 28-09'!A:A,0))} -> A | S72: {=INDEX('MTA 28-09'!X:X,MATCH(B72,'MTA 28-09'!A:A,0))} -> HORA DE VOO | T72: {=INDEX('MTA 28-09'!W:W,MATCH(B72,'MTA 28-09'!A:A,0))} -> Não | U72: {=INDEX('MTA 28-09'!AE:AE,MATCH(B72,'MTA 28-09'!A:A,0))} -> 46168
A73: C-95M | B73: 10980 | C73: {=INDEX('MTA 28-09'!B:B,MATCH(B73,'MTA 28-09'!A:A,0))} -> SIM | D73: {=INDEX('MTA 28-09'!D:D,MATCH(B73,'MTA 28-09'!A:A,0))} -> 2048 | E73: {=INDEX('MTA 28-09'!F:F,MATCH(B73,'MTA 28-09'!A:A,0))} -> ATENDIDO | F73: {=INDEX('MTA 28-09'!I:I,MATCH(B73,'MTA 28-09'!A:A,0))} -> 46098 | G73: {=INDEX('MTA 28-09'!J:J,MATCH(B73,'MTA 28-09'!A:A,0))} -> C26157 | H73: 1 | L73: {=INDEX('MTA 28-09'!S:S,MATCH(B73,'MTA 28-09'!A:A,0))} -> C-95M | M73: {=INDEX('MTA 28-09'!T:T,MATCH(B73,'MTA 28-09'!A:A,0))} -> CTT 028/CELOG-PAMALS/2025 – CLS AVIÔNICOS | N73: {=INDEX('MTA 28-09'!U:U,MATCH(B73,'MTA 28-09'!A:A,0))} -> Hora de Voo 02/09 - 1000 HV | O73: {=INDEX('MTA 28-09'!AC:AC,MATCH(B73,'MTA 28-09'!A:A,0))} -> 635270.89 | P73: {=INDEX('MTA 28-09'!N:N,MATCH(B73,'MTA 28-09'!A:A,0))} -> CELOG | Q73: {=INDEX('MTA 28-09'!Z:Z,MATCH(B73,'MTA 28-09'!A:A,0))} -> 339039 | R73: {=INDEX('MTA 28-09'!L:L,MATCH(B73,'MTA 28-09'!A:A,0))} -> A | S73: {=INDEX('MTA 28-09'!X:X,MATCH(B73,'MTA 28-09'!A:A,0))} -> HORA DE VOO | T73: {=INDEX('MTA 28-09'!W:W,MATCH(B73,'MTA 28-09'!A:A,0))} -> Não | U73: {=INDEX('MTA 28-09'!AE:AE,MATCH(B73,'MTA 28-09'!A:A,0))} -> 46168
A74: C-97 | B74: 11000 | C74: {=INDEX('MTA 28-09'!B:B,MATCH(B74,'MTA 28-09'!A:A,0))} -> SIM | D74: {=INDEX('MTA 28-09'!D:D,MATCH(B74,'MTA 28-09'!A:A,0))} -> 2048 | E74: {=INDEX('MTA 28-09'!F:F,MATCH(B74,'MTA 28-09'!A:A,0))} -> ATENDIDO | F74: {=INDEX('MTA 28-09'!I:I,MATCH(B74,'MTA 28-09'!A:A,0))} -> 46098 | G74: {=INDEX('MTA 28-09'!J:J,MATCH(B74,'MTA 28-09'!A:A,0))} -> C26154 | H74: 1 | L74: {=INDEX('MTA 28-09'!S:S,MATCH(B74,'MTA 28-09'!A:A,0))} -> C-97 | M74: {=INDEX('MTA 28-09'!T:T,MATCH(B74,'MTA 28-09'!A:A,0))} -> CTT 096/CAE-PAMALS/2021 - CLS C-97 | N74: {=INDEX('MTA 28-09'!U:U,MATCH(B74,'MTA 28-09'!A:A,0))} -> Hora de Voo 02/09 (500HV) | O74: {=INDEX('MTA 28-09'!AC:AC,MATCH(B74,'MTA 28-09'!A:A,0))} -> 2572500 | P74: {=INDEX('MTA 28-09'!N:N,MATCH(B74,'MTA 28-09'!A:A,0))} -> CELOG | Q74: {=INDEX('MTA 28-09'!Z:Z,MATCH(B74,'MTA 28-09'!A:A,0))} -> 339039 | R74: {=INDEX('MTA 28-09'!L:L,MATCH(B74,'MTA 28-09'!A:A,0))} -> A | S74: {=INDEX('MTA 28-09'!X:X,MATCH(B74,'MTA 28-09'!A:A,0))} -> HORA DE VOO | T74: {=INDEX('MTA 28-09'!W:W,MATCH(B74,'MTA 28-09'!A:A,0))} -> Não | U74: {=INDEX('MTA 28-09'!AE:AE,MATCH(B74,'MTA 28-09'!A:A,0))} -> 46168
A75: IU-93M | B75: 11020 | C75: {=INDEX('MTA 28-09'!B:B,MATCH(B75,'MTA 28-09'!A:A,0))} -> SIM | D75: {=INDEX('MTA 28-09'!D:D,MATCH(B75,'MTA 28-09'!A:A,0))} -> 20XV | E75: {=INDEX('MTA 28-09'!F:F,MATCH(B75,'MTA 28-09'!A:A,0))} -> ATENDIDO | F75: {=INDEX('MTA 28-09'!I:I,MATCH(B75,'MTA 28-09'!A:A,0))} -> 46065 | G75: {=INDEX('MTA 28-09'!J:J,MATCH(B75,'MTA 28-09'!A:A,0))} -> C26088 | H75: 1 | L75: {=INDEX('MTA 28-09'!S:S,MATCH(B75,'MTA 28-09'!A:A,0))} -> IU-93M | M75: {=INDEX('MTA 28-09'!T:T,MATCH(B75,'MTA 28-09'!A:A,0))} -> CNT 024/CELOG-PAMALS/2022 - VEE ONE | N75: {=INDEX('MTA 28-09'!U:U,MATCH(B75,'MTA 28-09'!A:A,0))} -> Hora de Voo 03/12 (100HV) | O75: {=INDEX('MTA 28-09'!AC:AC,MATCH(B75,'MTA 28-09'!A:A,0))} -> 2303463 | P75: {=INDEX('MTA 28-09'!N:N,MATCH(B75,'MTA 28-09'!A:A,0))} -> CELOG | Q75: {=INDEX('MTA 28-09'!Z:Z,MATCH(B75,'MTA 28-09'!A:A,0))} -> 339039 | R75: {=INDEX('MTA 28-09'!L:L,MATCH(B75,'MTA 28-09'!A:A,0))} -> A | S75: {=INDEX('MTA 28-09'!X:X,MATCH(B75,'MTA 28-09'!A:A,0))} -> HORA DE VOO | T75: {=INDEX('MTA 28-09'!W:W,MATCH(B75,'MTA 28-09'!A:A,0))} -> Não | U75: {=INDEX('MTA 28-09'!AE:AE,MATCH(B75,'MTA 28-09'!A:A,0))} -> 46168
A76: T-25 | B76: 11040 | C76: {=INDEX('MTA 28-09'!B:B,MATCH(B76,'MTA 28-09'!A:A,0))} -> SIM | D76: {=INDEX('MTA 28-09'!D:D,MATCH(B76,'MTA 28-09'!A:A,0))} -> 2048 | E76: {=INDEX('MTA 28-09'!F:F,MATCH(B76,'MTA 28-09'!A:A,0))} -> ATENDIDO | F76: {=INDEX('MTA 28-09'!I:I,MATCH(B76,'MTA 28-09'!A:A,0))} -> 46224 | G76: {=INDEX('MTA 28-09'!J:J,MATCH(B76,'MTA 28-09'!A:A,0))} -> C26156 | H76: email do dia 09/07 | L76: {=INDEX('MTA 28-09'!S:S,MATCH(B76,'MTA 28-09'!A:A,0))} -> T-25 | M76: {=INDEX('MTA 28-09'!T:T,MATCH(B76,'MTA 28-09'!A:A,0))} -> Requisição FMS | N76: {=INDEX('MTA 28-09'!U:U,MATCH(B76,'MTA 28-09'!A:A,0))} -> Requisições Consumíveis 1/4 | O76: {=INDEX('MTA 28-09'!AC:AC,MATCH(B76,'MTA 28-09'!A:A,0))} -> 272054 | P76: {=INDEX('MTA 28-09'!N:N,MATCH(B76,'MTA 28-09'!A:A,0))} -> CABW | Q76: {=INDEX('MTA 28-09'!Z:Z,MATCH(B76,'MTA 28-09'!A:A,0))} -> 339030 | R76: {=INDEX('MTA 28-09'!L:L,MATCH(B76,'MTA 28-09'!A:A,0))} -> A | S76: {=INDEX('MTA 28-09'!X:X,MATCH(B76,'MTA 28-09'!A:A,0))} -> REQUISIÇÃO | T76: {=INDEX('MTA 28-09'!W:W,MATCH(B76,'MTA 28-09'!A:A,0))} -> Não | U76: {=INDEX('MTA 28-09'!AE:AE,MATCH(B76,'MTA 28-09'!A:A,0))} -> 46291
A77: T-25 | B77: 11060 | C77: {=INDEX('MTA 28-09'!B:B,MATCH(B77,'MTA 28-09'!A:A,0))} -> SIM | D77: {=INDEX('MTA 28-09'!D:D,MATCH(B77,'MTA 28-09'!A:A,0))} -> 2048 | E77: {=INDEX('MTA 28-09'!F:F,MATCH(B77,'MTA 28-09'!A:A,0))} -> ATENDIDO | F77: {=INDEX('MTA 28-09'!I:I,MATCH(B77,'MTA 28-09'!A:A,0))} -> 46213 | G77: {=INDEX('MTA 28-09'!J:J,MATCH(B77,'MTA 28-09'!A:A,0))} -> C26156 | H77: email do dia 09/07 | L77: {=INDEX('MTA 28-09'!S:S,MATCH(B77,'MTA 28-09'!A:A,0))} -> T-25 | M77: {=INDEX('MTA 28-09'!T:T,MATCH(B77,'MTA 28-09'!A:A,0))} -> Requisição CABW | N77: {=INDEX('MTA 28-09'!U:U,MATCH(B77,'MTA 28-09'!A:A,0))} -> Requisições Consumíveis 1/4 | O77: {=INDEX('MTA 28-09'!AC:AC,MATCH(B77,'MTA 28-09'!A:A,0))} -> 403533.01 | P77: {=INDEX('MTA 28-09'!N:N,MATCH(B77,'MTA 28-09'!A:A,0))} -> CABW | Q77: {=INDEX('MTA 28-09'!Z:Z,MATCH(B77,'MTA 28-09'!A:A,0))} -> 339030 | R77: {=INDEX('MTA 28-09'!L:L,MATCH(B77,'MTA 28-09'!A:A,0))} -> A | S77: {=INDEX('MTA 28-09'!X:X,MATCH(B77,'MTA 28-09'!A:A,0))} -> REQUISIÇÃO | T77: {=INDEX('MTA 28-09'!W:W,MATCH(B77,'MTA 28-09'!A:A,0))} -> Não | U77: {=INDEX('MTA 28-09'!AE:AE,MATCH(B77,'MTA 28-09'!A:A,0))} -> 46352
A78: T-25 | B78: 11061 | C78: {=INDEX('MTA 28-09'!B:B,MATCH(B78,'MTA 28-09'!A:A,0))} -> SIM | D78: {=INDEX('MTA 28-09'!D:D,MATCH(B78,'MTA 28-09'!A:A,0))} -> 2048 | E78: {=INDEX('MTA 28-09'!F:F,MATCH(B78,'MTA 28-09'!A:A,0))} -> ATENDIDO | F78: {=INDEX('MTA 28-09'!I:I,MATCH(B78,'MTA 28-09'!A:A,0))} -> 46055 | G78: {=INDEX('MTA 28-09'!J:J,MATCH(B78,'MTA 28-09'!A:A,0))} -> C26010 | H78: 1 | L78: {=INDEX('MTA 28-09'!S:S,MATCH(B78,'MTA 28-09'!A:A,0))} -> T-25 | M78: {=INDEX('MTA 28-09'!T:T,MATCH(B78,'MTA 28-09'!A:A,0))} -> Requisição CABW | N78: {=INDEX('MTA 28-09'!U:U,MATCH(B78,'MTA 28-09'!A:A,0))} -> Requisições Consumíveis 1/4 | O78: {=INDEX('MTA 28-09'!AC:AC,MATCH(B78,'MTA 28-09'!A:A,0))} -> 1300000 | P78: {=INDEX('MTA 28-09'!N:N,MATCH(B78,'MTA 28-09'!A:A,0))} -> CABW | Q78: {=INDEX('MTA 28-09'!Z:Z,MATCH(B78,'MTA 28-09'!A:A,0))} -> 339030 | R78: {=INDEX('MTA 28-09'!L:L,MATCH(B78,'MTA 28-09'!A:A,0))} -> A | S78: {=INDEX('MTA 28-09'!X:X,MATCH(B78,'MTA 28-09'!A:A,0))} -> REQUISIÇÃO | T78: {=INDEX('MTA 28-09'!W:W,MATCH(B78,'MTA 28-09'!A:A,0))} -> Não | U78: {=INDEX('MTA 28-09'!AE:AE,MATCH(B78,'MTA 28-09'!A:A,0))} -> 46107
A79: T-25 | B79: 11062 | C79: {=INDEX('MTA 28-09'!B:B,MATCH(B79,'MTA 28-09'!A:A,0))} -> SIM | D79: {=INDEX('MTA 28-09'!D:D,MATCH(B79,'MTA 28-09'!A:A,0))} -> 2048 | E79: {=INDEX('MTA 28-09'!F:F,MATCH(B79,'MTA 28-09'!A:A,0))} -> ATENDIDO | F79: {=INDEX('MTA 28-09'!I:I,MATCH(B79,'MTA 28-09'!A:A,0))} -> 46118 | G79: {=INDEX('MTA 28-09'!J:J,MATCH(B79,'MTA 28-09'!A:A,0))} -> C26075 | H79: email do dia 19/03 | L79: {=INDEX('MTA 28-09'!S:S,MATCH(B79,'MTA 28-09'!A:A,0))} -> T-25 | M79: {=INDEX('MTA 28-09'!T:T,MATCH(B79,'MTA 28-09'!A:A,0))} -> Requisição CABW | N79: {=INDEX('MTA 28-09'!U:U,MATCH(B79,'MTA 28-09'!A:A,0))} -> Requisições Consumíveis 1/4 | O79: {=INDEX('MTA 28-09'!AC:AC,MATCH(B79,'MTA 28-09'!A:A,0))} -> 119775.39 | P79: {=INDEX('MTA 28-09'!N:N,MATCH(B79,'MTA 28-09'!A:A,0))} -> CABW | Q79: {=INDEX('MTA 28-09'!Z:Z,MATCH(B79,'MTA 28-09'!A:A,0))} -> 339030 | R79: {=INDEX('MTA 28-09'!L:L,MATCH(B79,'MTA 28-09'!A:A,0))} -> A | S79: {=INDEX('MTA 28-09'!X:X,MATCH(B79,'MTA 28-09'!A:A,0))} -> REQUISIÇÃO | T79: {=INDEX('MTA 28-09'!W:W,MATCH(B79,'MTA 28-09'!A:A,0))} -> Não | U79: {=INDEX('MTA 28-09'!AE:AE,MATCH(B79,'MTA 28-09'!A:A,0))} -> 46168
A80: T-25 | B80: 11063 | C80: {=INDEX('MTA 28-09'!B:B,MATCH(B80,'MTA 28-09'!A:A,0))} -> SIM | D80: {=INDEX('MTA 28-09'!D:D,MATCH(B80,'MTA 28-09'!A:A,0))} -> 2048 | E80: {=INDEX('MTA 28-09'!F:F,MATCH(B80,'MTA 28-09'!A:A,0))} -> ATENDIDO | F80: {=INDEX('MTA 28-09'!I:I,MATCH(B80,'MTA 28-09'!A:A,0))} -> 46192 | G80: {=INDEX('MTA 28-09'!J:J,MATCH(B80,'MTA 28-09'!A:A,0))} -> C26124 | H80: email do dia 24/04 | L80: {=INDEX('MTA 28-09'!S:S,MATCH(B80,'MTA 28-09'!A:A,0))} -> T-25 | M80: {=INDEX('MTA 28-09'!T:T,MATCH(B80,'MTA 28-09'!A:A,0))} -> Requisição CABW | N80: {=INDEX('MTA 28-09'!U:U,MATCH(B80,'MTA 28-09'!A:A,0))} -> Requisições Consumíveis 1/4 | O80: {=INDEX('MTA 28-09'!AC:AC,MATCH(B80,'MTA 28-09'!A:A,0))} -> 670330 | P80: {=INDEX('MTA 28-09'!N:N,MATCH(B80,'MTA 28-09'!A:A,0))} -> CABW | Q80: {=INDEX('MTA 28-09'!Z:Z,MATCH(B80,'MTA 28-09'!A:A,0))} -> 339030 | R80: {=INDEX('MTA 28-09'!L:L,MATCH(B80,'MTA 28-09'!A:A,0))} -> A | S80: {=INDEX('MTA 28-09'!X:X,MATCH(B80,'MTA 28-09'!A:A,0))} -> REQUISIÇÃO | T80: {=INDEX('MTA 28-09'!W:W,MATCH(B80,'MTA 28-09'!A:A,0))} -> Não | U80: {=INDEX('MTA 28-09'!AE:AE,MATCH(B80,'MTA 28-09'!A:A,0))} -> 46260
A81: T-25 | B81: 11080 | C81: {=INDEX('MTA 28-09'!B:B,MATCH(B81,'MTA 28-09'!A:A,0))} -> NÃO | D81: {=INDEX('MTA 28-09'!D:D,MATCH(B81,'MTA 28-09'!A:A,0))} | E81: {=INDEX('MTA 28-09'!F:F,MATCH(B81,'MTA 28-09'!A:A,0))} -> BLOQUEIO | F81: {=INDEX('MTA 28-09'!I:I,MATCH(B81,'MTA 28-09'!A:A,0))} | G81: {=INDEX('MTA 28-09'!J:J,MATCH(B81,'MTA 28-09'!A:A,0))} | L81: {=INDEX('MTA 28-09'!S:S,MATCH(B81,'MTA 28-09'!A:A,0))} -> T-25 | M81: {=INDEX('MTA 28-09'!T:T,MATCH(B81,'MTA 28-09'!A:A,0))} -> Requisição CABW | N81: {=INDEX('MTA 28-09'!U:U,MATCH(B81,'MTA 28-09'!A:A,0))} -> Requisições Consumíveis 3/4 | O81: {=INDEX('MTA 28-09'!AC:AC,MATCH(B81,'MTA 28-09'!A:A,0))} -> 2500000 | P81: {=INDEX('MTA 28-09'!N:N,MATCH(B81,'MTA 28-09'!A:A,0))} -> CABW | Q81: {=INDEX('MTA 28-09'!Z:Z,MATCH(B81,'MTA 28-09'!A:A,0))} -> 339030 | R81: {=INDEX('MTA 28-09'!L:L,MATCH(B81,'MTA 28-09'!A:A,0))} -> B | S81: {=INDEX('MTA 28-09'!X:X,MATCH(B81,'MTA 28-09'!A:A,0))} -> REQUISIÇÃO | T81: {=INDEX('MTA 28-09'!W:W,MATCH(B81,'MTA 28-09'!A:A,0))} -> Não | U81: {=INDEX('MTA 28-09'!AE:AE,MATCH(B81,'MTA 28-09'!A:A,0))} -> 46049
A82: T-25 | B82: 11100 | C82: {=INDEX('MTA 28-09'!B:B,MATCH(B82,'MTA 28-09'!A:A,0))} -> SIM | D82: {=INDEX('MTA 28-09'!D:D,MATCH(B82,'MTA 28-09'!A:A,0))} -> 2048 | E82: {=INDEX('MTA 28-09'!F:F,MATCH(B82,'MTA 28-09'!A:A,0))} -> ATENDIDO | F82: {=INDEX('MTA 28-09'!I:I,MATCH(B82,'MTA 28-09'!A:A,0))} -> 46213 | G82: {=INDEX('MTA 28-09'!J:J,MATCH(B82,'MTA 28-09'!A:A,0))} -> C26156 | H82: email do dia 09/07 | L82: {=INDEX('MTA 28-09'!S:S,MATCH(B82,'MTA 28-09'!A:A,0))} -> T-25 | M82: {=INDEX('MTA 28-09'!T:T,MATCH(B82,'MTA 28-09'!A:A,0))} -> Requisição CABW | N82: {=INDEX('MTA 28-09'!U:U,MATCH(B82,'MTA 28-09'!A:A,0))} -> Requisições Serviço 1/4 | O82: {=INDEX('MTA 28-09'!AC:AC,MATCH(B82,'MTA 28-09'!A:A,0))} -> 97898.07 | P82: {=INDEX('MTA 28-09'!N:N,MATCH(B82,'MTA 28-09'!A:A,0))} -> CABW | Q82: {=INDEX('MTA 28-09'!Z:Z,MATCH(B82,'MTA 28-09'!A:A,0))} -> 339030 | R82: {=INDEX('MTA 28-09'!L:L,MATCH(B82,'MTA 28-09'!A:A,0))} -> A | S82: {=INDEX('MTA 28-09'!X:X,MATCH(B82,'MTA 28-09'!A:A,0))} -> REQUISIÇÃO | T82: {=INDEX('MTA 28-09'!W:W,MATCH(B82,'MTA 28-09'!A:A,0))} -> Não | U82: {=INDEX('MTA 28-09'!AE:AE,MATCH(B82,'MTA 28-09'!A:A,0))} -> 46049
A83: T-25 | B83: 11120 | C83: {=INDEX('MTA 28-09'!B:B,MATCH(B83,'MTA 28-09'!A:A,0))} -> SIM | D83: {=INDEX('MTA 28-09'!D:D,MATCH(B83,'MTA 28-09'!A:A,0))} -> 2048 | E83: {=INDEX('MTA 28-09'!F:F,MATCH(B83,'MTA 28-09'!A:A,0))} -> ATENDIDO | F83: {=INDEX('MTA 28-09'!I:I,MATCH(B83,'MTA 28-09'!A:A,0))} -> 46213 | G83: {=INDEX('MTA 28-09'!J:J,MATCH(B83,'MTA 28-09'!A:A,0))} -> C26156 | H83: email do dia 09/07 | J83: MOTOR | L83: {=INDEX('MTA 28-09'!S:S,MATCH(B83,'MTA 28-09'!A:A,0))} -> T-25 | M83: {=INDEX('MTA 28-09'!T:T,MATCH(B83,'MTA 28-09'!A:A,0))} -> Requisição CABW | N83: {=INDEX('MTA 28-09'!U:U,MATCH(B83,'MTA 28-09'!A:A,0))} -> Requisições Serviço 3/4 | O83: {=INDEX('MTA 28-09'!AC:AC,MATCH(B83,'MTA 28-09'!A:A,0))} -> 95152.41 | P83: {=INDEX('MTA 28-09'!N:N,MATCH(B83,'MTA 28-09'!A:A,0))} -> CABW | Q83: {=INDEX('MTA 28-09'!Z:Z,MATCH(B83,'MTA 28-09'!A:A,0))} -> 339030 | R83: {=INDEX('MTA 28-09'!L:L,MATCH(B83,'MTA 28-09'!A:A,0))} -> A | S83: {=INDEX('MTA 28-09'!X:X,MATCH(B83,'MTA 28-09'!A:A,0))} -> REQUISIÇÃO | T83: {=INDEX('MTA 28-09'!W:W,MATCH(B83,'MTA 28-09'!A:A,0))} -> Não | U83: {=INDEX('MTA 28-09'!AE:AE,MATCH(B83,'MTA 28-09'!A:A,0))} -> 46049
A84: T-27 | B84: 11121 | C84: {=INDEX('MTA 28-09'!B:B,MATCH(B84,'MTA 28-09'!A:A,0))} -> SIM | D84: {=INDEX('MTA 28-09'!D:D,MATCH(B84,'MTA 28-09'!A:A,0))} -> 2048 | E84: {=INDEX('MTA 28-09'!F:F,MATCH(B84,'MTA 28-09'!A:A,0))} -> ATENDIDO | F84: {=INDEX('MTA 28-09'!I:I,MATCH(B84,'MTA 28-09'!A:A,0))} -> 46251 | G84: {=INDEX('MTA 28-09'!J:J,MATCH(B84,'MTA 28-09'!A:A,0))} -> - | H84: email do dia 09/07 | L84: {=INDEX('MTA 28-09'!S:S,MATCH(B84,'MTA 28-09'!A:A,0))} -> T-27 | M84: {=INDEX('MTA 28-09'!T:T,MATCH(B84,'MTA 28-09'!A:A,0))} -> ATA AR CONDICIONADO | N84: {=INDEX('MTA 28-09'!U:U,MATCH(B84,'MTA 28-09'!A:A,0))} -> Requisições Serviço 3/4 | O84: {=INDEX('MTA 28-09'!AC:AC,MATCH(B84,'MTA 28-09'!A:A,0))} -> 3402 | P84: {=INDEX('MTA 28-09'!N:N,MATCH(B84,'MTA 28-09'!A:A,0))} -> EEAR | Q84: {=INDEX('MTA 28-09'!Z:Z,MATCH(B84,'MTA 28-09'!A:A,0))} -> 339030 | R84: {=INDEX('MTA 28-09'!L:L,MATCH(B84,'MTA 28-09'!A:A,0))} -> A | S84: {=INDEX('MTA 28-09'!X:X,MATCH(B84,'MTA 28-09'!A:A,0))} -> REQUISIÇÃO | T84: {=INDEX('MTA 28-09'!W:W,MATCH(B84,'MTA 28-09'!A:A,0))} -> Não | U84: {=INDEX('MTA 28-09'!AE:AE,MATCH(B84,'MTA 28-09'!A:A,0))} -> 46260
A85: T-27 | B85: 11140 | C85: {=INDEX('MTA 28-09'!B:B,MATCH(B85,'MTA 28-09'!A:A,0))} -> SIM | D85: {=INDEX('MTA 28-09'!D:D,MATCH(B85,'MTA 28-09'!A:A,0))} -> 2048 | E85: {=INDEX('MTA 28-09'!F:F,MATCH(B85,'MTA 28-09'!A:A,0))} | F85: {=INDEX('MTA 28-09'!I:I,MATCH(B85,'MTA 28-09'!A:A,0))} | G85: {=INDEX('MTA 28-09'!J:J,MATCH(B85,'MTA 28-09'!A:A,0))} | H85: 46276 | I85: Atender | L85: {=INDEX('MTA 28-09'!S:S,MATCH(B85,'MTA 28-09'!A:A,0))} -> T-27 | M85: {=INDEX('MTA 28-09'!T:T,MATCH(B85,'MTA 28-09'!A:A,0))} -> Requisição CABW | N85: {=INDEX('MTA 28-09'!U:U,MATCH(B85,'MTA 28-09'!A:A,0))} -> Requisições Consumíveis | O85: {=INDEX('MTA 28-09'!AC:AC,MATCH(B85,'MTA 28-09'!A:A,0))} -> 266598 | P85: {=INDEX('MTA 28-09'!N:N,MATCH(B85,'MTA 28-09'!A:A,0))} -> CABW | Q85: {=INDEX('MTA 28-09'!Z:Z,MATCH(B85,'MTA 28-09'!A:A,0))} -> 339030 | R85: {=INDEX('MTA 28-09'!L:L,MATCH(B85,'MTA 28-09'!A:A,0))} -> A | S85: {=INDEX('MTA 28-09'!X:X,MATCH(B85,'MTA 28-09'!A:A,0))} -> REQUISIÇÃO | T85: {=INDEX('MTA 28-09'!W:W,MATCH(B85,'MTA 28-09'!A:A,0))} -> Não | U85: {=INDEX('MTA 28-09'!AE:AE,MATCH(B85,'MTA 28-09'!A:A,0))} -> 46352
A86: T-27 | B86: 11141 | C86: {=INDEX('MTA 28-09'!B:B,MATCH(B86,'MTA 28-09'!A:A,0))} -> SIM | D86: {=INDEX('MTA 28-09'!D:D,MATCH(B86,'MTA 28-09'!A:A,0))} -> 2048 | E86: {=INDEX('MTA 28-09'!F:F,MATCH(B86,'MTA 28-09'!A:A,0))} -> ATENDIDO | F86: {=INDEX('MTA 28-09'!I:I,MATCH(B86,'MTA 28-09'!A:A,0))} -> 46205 | G86: {=INDEX('MTA 28-09'!J:J,MATCH(B86,'MTA 28-09'!A:A,0))} -> C26135 | L86: {=INDEX('MTA 28-09'!S:S,MATCH(B86,'MTA 28-09'!A:A,0))} -> T-25 | M86: {=INDEX('MTA 28-09'!T:T,MATCH(B86,'MTA 28-09'!A:A,0))} -> Requisição FMS | N86: {=INDEX('MTA 28-09'!U:U,MATCH(B86,'MTA 28-09'!A:A,0))} -> Requisições Consumíveis 1/4 | O86: {=INDEX('MTA 28-09'!AC:AC,MATCH(B86,'MTA 28-09'!A:A,0))} -> 3085.07 | P86: {=INDEX('MTA 28-09'!N:N,MATCH(B86,'MTA 28-09'!A:A,0))} -> CABW | Q86: {=INDEX('MTA 28-09'!Z:Z,MATCH(B86,'MTA 28-09'!A:A,0))} -> 339030 | R86: {=INDEX('MTA 28-09'!L:L,MATCH(B86,'MTA 28-09'!A:A,0))} -> A | S86: {=INDEX('MTA 28-09'!X:X,MATCH(B86,'MTA 28-09'!A:A,0))} -> REQUISIÇÃO | T86: {=INDEX('MTA 28-09'!W:W,MATCH(B86,'MTA 28-09'!A:A,0))} -> Não | U86: {=INDEX('MTA 28-09'!AE:AE,MATCH(B86,'MTA 28-09'!A:A,0))} -> 46260
A87: T-27 | B87: 11160 | C87: {=INDEX('MTA 28-09'!B:B,MATCH(B87,'MTA 28-09'!A:A,0))} -> SIM | D87: {=INDEX('MTA 28-09'!D:D,MATCH(B87,'MTA 28-09'!A:A,0))} -> 2048 | E87: {=INDEX('MTA 28-09'!F:F,MATCH(B87,'MTA 28-09'!A:A,0))} -> ATENDIDO | F87: {=INDEX('MTA 28-09'!I:I,MATCH(B87,'MTA 28-09'!A:A,0))} -> 46091 | G87: {=INDEX('MTA 28-09'!J:J,MATCH(B87,'MTA 28-09'!A:A,0))} -> C26035 | H87: 1 | L87: {=INDEX('MTA 28-09'!S:S,MATCH(B87,'MTA 28-09'!A:A,0))} -> T-27 | M87: {=INDEX('MTA 28-09'!T:T,MATCH(B87,'MTA 28-09'!A:A,0))} -> Requisição CABW | N87: {=INDEX('MTA 28-09'!U:U,MATCH(B87,'MTA 28-09'!A:A,0))} -> Requisições Consumíveis 1/4 | O87: {=INDEX('MTA 28-09'!AC:AC,MATCH(B87,'MTA 28-09'!A:A,0))} -> 1059188.1 | P87: {=INDEX('MTA 28-09'!N:N,MATCH(B87,'MTA 28-09'!A:A,0))} -> CABW | Q87: {=INDEX('MTA 28-09'!Z:Z,MATCH(B87,'MTA 28-09'!A:A,0))} -> 339030 | R87: {=INDEX('MTA 28-09'!L:L,MATCH(B87,'MTA 28-09'!A:A,0))} -> A | S87: {=INDEX('MTA 28-09'!X:X,MATCH(B87,'MTA 28-09'!A:A,0))} -> REQUISIÇÃO | T87: {=INDEX('MTA 28-09'!W:W,MATCH(B87,'MTA 28-09'!A:A,0))} -> Não | U87: {=INDEX('MTA 28-09'!AE:AE,MATCH(B87,'MTA 28-09'!A:A,0))} -> 46107
A88: T-27 | B88: 11180 | C88: {=INDEX('MTA 28-09'!B:B,MATCH(B88,'MTA 28-09'!A:A,0))} -> SIM | D88: {=INDEX('MTA 28-09'!D:D,MATCH(B88,'MTA 28-09'!A:A,0))} -> 2048 | E88: {=INDEX('MTA 28-09'!F:F,MATCH(B88,'MTA 28-09'!A:A,0))} -> ATENDIDO | F88: {=INDEX('MTA 28-09'!I:I,MATCH(B88,'MTA 28-09'!A:A,0))} -> 46072 | G88: {=INDEX('MTA 28-09'!J:J,MATCH(B88,'MTA 28-09'!A:A,0))} -> C26035 | H88: 1 | L88: {=INDEX('MTA 28-09'!S:S,MATCH(B88,'MTA 28-09'!A:A,0))} -> T-27 | M88: {=INDEX('MTA 28-09'!T:T,MATCH(B88,'MTA 28-09'!A:A,0))} -> Requisição CABW | N88: {=INDEX('MTA 28-09'!U:U,MATCH(B88,'MTA 28-09'!A:A,0))} -> Requisições Consumíveis 3/4 | O88: {=INDEX('MTA 28-09'!AC:AC,MATCH(B88,'MTA 28-09'!A:A,0))} -> 1000000 | P88: {=INDEX('MTA 28-09'!N:N,MATCH(B88,'MTA 28-09'!A:A,0))} -> CABW | Q88: {=INDEX('MTA 28-09'!Z:Z,MATCH(B88,'MTA 28-09'!A:A,0))} -> 339030 | R88: {=INDEX('MTA 28-09'!L:L,MATCH(B88,'MTA 28-09'!A:A,0))} -> A | S88: {=INDEX('MTA 28-09'!X:X,MATCH(B88,'MTA 28-09'!A:A,0))} -> REQUISIÇÃO | T88: {=INDEX('MTA 28-09'!W:W,MATCH(B88,'MTA 28-09'!A:A,0))} -> Não | U88: {=INDEX('MTA 28-09'!AE:AE,MATCH(B88,'MTA 28-09'!A:A,0))} -> 46107
A89: T-27 | B89: 11200 | C89: {=INDEX('MTA 28-09'!B:B,MATCH(B89,'MTA 28-09'!A:A,0))} -> SIM | D89: {=INDEX('MTA 28-09'!D:D,MATCH(B89,'MTA 28-09'!A:A,0))} -> 2048 | E89: {=INDEX('MTA 28-09'!F:F,MATCH(B89,'MTA 28-09'!A:A,0))} -> ATENDIDO | F89: {=INDEX('MTA 28-09'!I:I,MATCH(B89,'MTA 28-09'!A:A,0))} -> 46073 | G89: {=INDEX('MTA 28-09'!J:J,MATCH(B89,'MTA 28-09'!A:A,0))} -> C26108 | L89: {=INDEX('MTA 28-09'!S:S,MATCH(B89,'MTA 28-09'!A:A,0))} -> T-27 | M89: {=INDEX('MTA 28-09'!T:T,MATCH(B89,'MTA 28-09'!A:A,0))} -> CNT 048/CELOG-PAMASP/2022 - PW - Material | N89: {=INDEX('MTA 28-09'!U:U,MATCH(B89,'MTA 28-09'!A:A,0))} -> Material HSI PT6A-25C (1/7) | O89: {=INDEX('MTA 28-09'!AC:AC,MATCH(B89,'MTA 28-09'!A:A,0))} -> 750000 | P89: {=INDEX('MTA 28-09'!N:N,MATCH(B89,'MTA 28-09'!A:A,0))} -> CELOG | Q89: {=INDEX('MTA 28-09'!Z:Z,MATCH(B89,'MTA 28-09'!A:A,0))} -> 339030 | R89: {=INDEX('MTA 28-09'!L:L,MATCH(B89,'MTA 28-09'!A:A,0))} -> A | S89: {=INDEX('MTA 28-09'!X:X,MATCH(B89,'MTA 28-09'!A:A,0))} -> SOB DEMANDA | T89: {=INDEX('MTA 28-09'!W:W,MATCH(B89,'MTA 28-09'!A:A,0))} -> SIM | U89: {=INDEX('MTA 28-09'!AE:AE,MATCH(B89,'MTA 28-09'!A:A,0))} -> 46260
A90: T-27 | B90: 11220 | C90: {=INDEX('MTA 28-09'!B:B,MATCH(B90,'MTA 28-09'!A:A,0))} -> SIM | D90: {=INDEX('MTA 28-09'!D:D,MATCH(B90,'MTA 28-09'!A:A,0))} -> 2048 | E90: {=INDEX('MTA 28-09'!F:F,MATCH(B90,'MTA 28-09'!A:A,0))} | F90: {=INDEX('MTA 28-09'!I:I,MATCH(B90,'MTA 28-09'!A:A,0))} | G90: {=INDEX('MTA 28-09'!J:J,MATCH(B90,'MTA 28-09'!A:A,0))} | L90: {=INDEX('MTA 28-09'!S:S,MATCH(B90,'MTA 28-09'!A:A,0))} -> T-27 | M90: {=INDEX('MTA 28-09'!T:T,MATCH(B90,'MTA 28-09'!A:A,0))} -> REQUISIÇÃO CONSUMO | N90: {=INDEX('MTA 28-09'!U:U,MATCH(B90,'MTA 28-09'!A:A,0))} -> Material acessórios PT6A-25C (1/3) | O90: {=INDEX('MTA 28-09'!AC:AC,MATCH(B90,'MTA 28-09'!A:A,0))} -> - | P90: {=INDEX('MTA 28-09'!N:N,MATCH(B90,'MTA 28-09'!A:A,0))} -> CABW | Q90: {=INDEX('MTA 28-09'!Z:Z,MATCH(B90,'MTA 28-09'!A:A,0))} -> 339030 | R90: {=INDEX('MTA 28-09'!L:L,MATCH(B90,'MTA 28-09'!A:A,0))} -> A | S90: {=INDEX('MTA 28-09'!X:X,MATCH(B90,'MTA 28-09'!A:A,0))} -> REQUISIÇÃO | T90: {=INDEX('MTA 28-09'!W:W,MATCH(B90,'MTA 28-09'!A:A,0))} -> SIM | U90: {=INDEX('MTA 28-09'!AE:AE,MATCH(B90,'MTA 28-09'!A:A,0))} -> 46168
A91: T-27 | B91: 11221 | C91: {=INDEX('MTA 28-09'!B:B,MATCH(B91,'MTA 28-09'!A:A,0))} -> SIM | D91: {=INDEX('MTA 28-09'!D:D,MATCH(B91,'MTA 28-09'!A:A,0))} -> 2048 | E91: {=INDEX('MTA 28-09'!F:F,MATCH(B91,'MTA 28-09'!A:A,0))} -> ATENDIDO | F91: {=INDEX('MTA 28-09'!I:I,MATCH(B91,'MTA 28-09'!A:A,0))} -> 46247 | G91: {=INDEX('MTA 28-09'!J:J,MATCH(B91,'MTA 28-09'!A:A,0))} -> C26038 | L91: {=INDEX('MTA 28-09'!S:S,MATCH(B91,'MTA 28-09'!A:A,0))} -> T-27 | M91: {=INDEX('MTA 28-09'!T:T,MATCH(B91,'MTA 28-09'!A:A,0))} -> REQUISIÇÃO SERVIÇO | N91: {=INDEX('MTA 28-09'!U:U,MATCH(B91,'MTA 28-09'!A:A,0))} -> REPARO PTVR | O91: {=INDEX('MTA 28-09'!AC:AC,MATCH(B91,'MTA 28-09'!A:A,0))} -> 261544.32 | P91: {=INDEX('MTA 28-09'!N:N,MATCH(B91,'MTA 28-09'!A:A,0))} -> CABW | Q91: {=INDEX('MTA 28-09'!Z:Z,MATCH(B91,'MTA 28-09'!A:A,0))} -> 339039 | R91: {=INDEX('MTA 28-09'!L:L,MATCH(B91,'MTA 28-09'!A:A,0))} -> A | S91: {=INDEX('MTA 28-09'!X:X,MATCH(B91,'MTA 28-09'!A:A,0))} -> REQUISIÇÃO | T91: {=INDEX('MTA 28-09'!W:W,MATCH(B91,'MTA 28-09'!A:A,0))} -> SIM | U91: {=INDEX('MTA 28-09'!AE:AE,MATCH(B91,'MTA 28-09'!A:A,0))} -> 46168
A92: T-27 | B92: 11240 | C92: {=INDEX('MTA 28-09'!B:B,MATCH(B92,'MTA 28-09'!A:A,0))} -> SIM | D92: {=INDEX('MTA 28-09'!D:D,MATCH(B92,'MTA 28-09'!A:A,0))} -> 2048 | E92: {=INDEX('MTA 28-09'!F:F,MATCH(B92,'MTA 28-09'!A:A,0))} -> CANCELADO | F92: {=INDEX('MTA 28-09'!I:I,MATCH(B92,'MTA 28-09'!A:A,0))} | G92: {=INDEX('MTA 28-09'!J:J,MATCH(B92,'MTA 28-09'!A:A,0))} | L92: {=INDEX('MTA 28-09'!S:S,MATCH(B92,'MTA 28-09'!A:A,0))} -> T-27 | M92: {=INDEX('MTA 28-09'!T:T,MATCH(B92,'MTA 28-09'!A:A,0))} -> REQUISIÇÃO SERVIÇO | N92: {=INDEX('MTA 28-09'!U:U,MATCH(B92,'MTA 28-09'!A:A,0))} -> RG Controlador de Torque 3 EA (2/2) | O92: {=INDEX('MTA 28-09'!AC:AC,MATCH(B92,'MTA 28-09'!A:A,0))} -> - | P92: {=INDEX('MTA 28-09'!N:N,MATCH(B92,'MTA 28-09'!A:A,0))} -> CABW | Q92: {=INDEX('MTA 28-09'!Z:Z,MATCH(B92,'MTA 28-09'!A:A,0))} -> 339039 | R92: {=INDEX('MTA 28-09'!L:L,MATCH(B92,'MTA 28-09'!A:A,0))} -> A | S92: {=INDEX('MTA 28-09'!X:X,MATCH(B92,'MTA 28-09'!A:A,0))} -> REQUISIÇÃO | T92: {=INDEX('MTA 28-09'!W:W,MATCH(B92,'MTA 28-09'!A:A,0))} -> SIM | U92: {=INDEX('MTA 28-09'!AE:AE,MATCH(B92,'MTA 28-09'!A:A,0))} -> 46200
A93: T-27 | B93: 11260 | C93: {=INDEX('MTA 28-09'!B:B,MATCH(B93,'MTA 28-09'!A:A,0))} -> SIM | D93: {=INDEX('MTA 28-09'!D:D,MATCH(B93,'MTA 28-09'!A:A,0))} -> 2048 | E93: {=INDEX('MTA 28-09'!F:F,MATCH(B93,'MTA 28-09'!A:A,0))} -> CANCELADO | F93: {=INDEX('MTA 28-09'!I:I,MATCH(B93,'MTA 28-09'!A:A,0))} | G93: {=INDEX('MTA 28-09'!J:J,MATCH(B93,'MTA 28-09'!A:A,0))} | L93: {=INDEX('MTA 28-09'!S:S,MATCH(B93,'MTA 28-09'!A:A,0))} -> T-27 | M93: {=INDEX('MTA 28-09'!T:T,MATCH(B93,'MTA 28-09'!A:A,0))} -> REQUISIÇÃO SERVIÇO | N93: {=INDEX('MTA 28-09'!U:U,MATCH(B93,'MTA 28-09'!A:A,0))} -> RG Fuel Control Unit 2 EA (2/4) | O93: {=INDEX('MTA 28-09'!AC:AC,MATCH(B93,'MTA 28-09'!A:A,0))} -> - | P93: {=INDEX('MTA 28-09'!N:N,MATCH(B93,'MTA 28-09'!A:A,0))} -> CABW | Q93: {=INDEX('MTA 28-09'!Z:Z,MATCH(B93,'MTA 28-09'!A:A,0))} -> 339039 | R93: {=INDEX('MTA 28-09'!L:L,MATCH(B93,'MTA 28-09'!A:A,0))} -> A | S93: {=INDEX('MTA 28-09'!X:X,MATCH(B93,'MTA 28-09'!A:A,0))} -> REQUISIÇÃO | T93: {=INDEX('MTA 28-09'!W:W,MATCH(B93,'MTA 28-09'!A:A,0))} -> SIM | U93: {=INDEX('MTA 28-09'!AE:AE,MATCH(B93,'MTA 28-09'!A:A,0))} -> 46200
A94: T-27 | B94: 11280 | C94: {=INDEX('MTA 28-09'!B:B,MATCH(B94,'MTA 28-09'!A:A,0))} -> SIM | D94: {=INDEX('MTA 28-09'!D:D,MATCH(B94,'MTA 28-09'!A:A,0))} -> 2048 | E94: {=INDEX('MTA 28-09'!F:F,MATCH(B94,'MTA 28-09'!A:A,0))} -> CANCELADO | F94: {=INDEX('MTA 28-09'!I:I,MATCH(B94,'MTA 28-09'!A:A,0))} | G94: {=INDEX('MTA 28-09'!J:J,MATCH(B94,'MTA 28-09'!A:A,0))} | L94: {=INDEX('MTA 28-09'!S:S,MATCH(B94,'MTA 28-09'!A:A,0))} -> T-27 | M94: {=INDEX('MTA 28-09'!T:T,MATCH(B94,'MTA 28-09'!A:A,0))} -> REQUISIÇÃO SERVIÇO | N94: {=INDEX('MTA 28-09'!U:U,MATCH(B94,'MTA 28-09'!A:A,0))} -> RG Fuel Pump 4 EA (2/2) | O94: {=INDEX('MTA 28-09'!AC:AC,MATCH(B94,'MTA 28-09'!A:A,0))} -> - | P94: {=INDEX('MTA 28-09'!N:N,MATCH(B94,'MTA 28-09'!A:A,0))} -> CABW | Q94: {=INDEX('MTA 28-09'!Z:Z,MATCH(B94,'MTA 28-09'!A:A,0))} -> 339039 | R94: {=INDEX('MTA 28-09'!L:L,MATCH(B94,'MTA 28-09'!A:A,0))} -> A | S94: {=INDEX('MTA 28-09'!X:X,MATCH(B94,'MTA 28-09'!A:A,0))} -> REQUISIÇÃO | T94: {=INDEX('MTA 28-09'!W:W,MATCH(B94,'MTA 28-09'!A:A,0))} -> SIM | U94: {=INDEX('MTA 28-09'!AE:AE,MATCH(B94,'MTA 28-09'!A:A,0))} -> 46200
A95: A-29 | B95: 11300 | C95: {=INDEX('MTA 28-09'!B:B,MATCH(B95,'MTA 28-09'!A:A,0))} -> SIM | D95: {=INDEX('MTA 28-09'!D:D,MATCH(B95,'MTA 28-09'!A:A,0))} -> 2048 | E95: {=INDEX('MTA 28-09'!F:F,MATCH(B95,'MTA 28-09'!A:A,0))} -> ATENDIDO | F95: {=INDEX('MTA 28-09'!I:I,MATCH(B95,'MTA 28-09'!A:A,0))} -> 46205 | G95: {=INDEX('MTA 28-09'!J:J,MATCH(B95,'MTA 28-09'!A:A,0))} -> C26138 | H95: email do dia 30/06 | L95: {=INDEX('MTA 28-09'!S:S,MATCH(B95,'MTA 28-09'!A:A,0))} -> A-29 | M95: {=INDEX('MTA 28-09'!T:T,MATCH(B95,'MTA 28-09'!A:A,0))} -> Requisição CABW | N95: {=INDEX('MTA 28-09'!U:U,MATCH(B95,'MTA 28-09'!A:A,0))} -> Requisições Consumíveis 1/2 | O95: {=INDEX('MTA 28-09'!AC:AC,MATCH(B95,'MTA 28-09'!A:A,0))} -> 136026.22 | P95: {=INDEX('MTA 28-09'!N:N,MATCH(B95,'MTA 28-09'!A:A,0))} -> CABW | Q95: {=INDEX('MTA 28-09'!Z:Z,MATCH(B95,'MTA 28-09'!A:A,0))} -> 339030 | R95: {=INDEX('MTA 28-09'!L:L,MATCH(B95,'MTA 28-09'!A:A,0))} -> A | S95: {=INDEX('MTA 28-09'!X:X,MATCH(B95,'MTA 28-09'!A:A,0))} -> REQUISIÇÃO | T95: {=INDEX('MTA 28-09'!W:W,MATCH(B95,'MTA 28-09'!A:A,0))} -> Não | U95: {=INDEX('MTA 28-09'!AE:AE,MATCH(B95,'MTA 28-09'!A:A,0))} -> 46260
A96: A-29 | B96: 11320 | C96: {=INDEX('MTA 28-09'!B:B,MATCH(B96,'MTA 28-09'!A:A,0))} -> SIM | D96: {=INDEX('MTA 28-09'!D:D,MATCH(B96,'MTA 28-09'!A:A,0))} -> 20XV | E96: {=INDEX('MTA 28-09'!F:F,MATCH(B96,'MTA 28-09'!A:A,0))} -> ATENDIDO | F96: {=INDEX('MTA 28-09'!I:I,MATCH(B96,'MTA 28-09'!A:A,0))} -> 46176 | G96: {=INDEX('MTA 28-09'!J:J,MATCH(B96,'MTA 28-09'!A:A,0))} -> C26114 | L96: {=INDEX('MTA 28-09'!S:S,MATCH(B96,'MTA 28-09'!A:A,0))} -> A-29 | M96: {=INDEX('MTA 28-09'!T:T,MATCH(B96,'MTA 28-09'!A:A,0))} -> CNT 051/CELOG-PAMASP/2024 - STANDARD AERO - REVISÃO GERAL | N96: {=INDEX('MTA 28-09'!U:U,MATCH(B96,'MTA 28-09'!A:A,0))} -> Revisão Geral PT6A-68C 06/20 | O96: {=INDEX('MTA 28-09'!AC:AC,MATCH(B96,'MTA 28-09'!A:A,0))} -> 2835685.7 | P96: {=INDEX('MTA 28-09'!N:N,MATCH(B96,'MTA 28-09'!A:A,0))} -> CABW | Q96: {=INDEX('MTA 28-09'!Z:Z,MATCH(B96,'MTA 28-09'!A:A,0))} -> 339039 | R96: {=INDEX('MTA 28-09'!L:L,MATCH(B96,'MTA 28-09'!A:A,0))} -> A | S96: {=INDEX('MTA 28-09'!X:X,MATCH(B96,'MTA 28-09'!A:A,0))} -> SOB DEMANDA | T96: {=INDEX('MTA 28-09'!W:W,MATCH(B96,'MTA 28-09'!A:A,0))} -> SIM | U96: {=INDEX('MTA 28-09'!AE:AE,MATCH(B96,'MTA 28-09'!A:A,0))} -> 46260
A97: A-29 | B97: 11321 | C97: {=INDEX('MTA 28-09'!B:B,MATCH(B97,'MTA 28-09'!A:A,0))} -> SIM | D97: {=INDEX('MTA 28-09'!D:D,MATCH(B97,'MTA 28-09'!A:A,0))} -> DESTQ20 | E97: {=INDEX('MTA 28-09'!F:F,MATCH(B97,'MTA 28-09'!A:A,0))} -> ATENDIDO | F97: {=INDEX('MTA 28-09'!I:I,MATCH(B97,'MTA 28-09'!A:A,0))} -> 46176 | G97: {=INDEX('MTA 28-09'!J:J,MATCH(B97,'MTA 28-09'!A:A,0))} -> C26092 | L97: {=INDEX('MTA 28-09'!S:S,MATCH(B97,'MTA 28-09'!A:A,0))} -> A-29 | M97: {=INDEX('MTA 28-09'!T:T,MATCH(B97,'MTA 28-09'!A:A,0))} -> CNT 051/CELOG-PAMASP/2024 - STANDARD AERO - REVISÃO GERAL | N97: {=INDEX('MTA 28-09'!U:U,MATCH(B97,'MTA 28-09'!A:A,0))} -> Revisão Geral PT6A-68C 06/20 | O97: {=INDEX('MTA 28-09'!AC:AC,MATCH(B97,'MTA 28-09'!A:A,0))} -> 2063195.8 | P97: {=INDEX('MTA 28-09'!N:N,MATCH(B97,'MTA 28-09'!A:A,0))} -> CABW | Q97: {=INDEX('MTA 28-09'!Z:Z,MATCH(B97,'MTA 28-09'!A:A,0))} -> 339039 | R97: {=INDEX('MTA 28-09'!L:L,MATCH(B97,'MTA 28-09'!A:A,0))} -> A | S97: {=INDEX('MTA 28-09'!X:X,MATCH(B97,'MTA 28-09'!A:A,0))} -> SOB DEMANDA | T97: {=INDEX('MTA 28-09'!W:W,MATCH(B97,'MTA 28-09'!A:A,0))} -> SIM | U97: {=INDEX('MTA 28-09'!AE:AE,MATCH(B97,'MTA 28-09'!A:A,0))} -> 46260
A98: A-29 | B98: 11322 | C98: {=INDEX('MTA 28-09'!B:B,MATCH(B98,'MTA 28-09'!A:A,0))} -> SIM | D98: {=INDEX('MTA 28-09'!D:D,MATCH(B98,'MTA 28-09'!A:A,0))} -> DESTQ21 | E98: {=INDEX('MTA 28-09'!F:F,MATCH(B98,'MTA 28-09'!A:A,0))} -> ATENDIDO | F98: {=INDEX('MTA 28-09'!I:I,MATCH(B98,'MTA 28-09'!A:A,0))} -> 46176 | G98: {=INDEX('MTA 28-09'!J:J,MATCH(B98,'MTA 28-09'!A:A,0))} -> C26092 | L98: {=INDEX('MTA 28-09'!S:S,MATCH(B98,'MTA 28-09'!A:A,0))} -> A-29 | M98: {=INDEX('MTA 28-09'!T:T,MATCH(B98,'MTA 28-09'!A:A,0))} -> CNT 051/CELOG-PAMASP/2024 - STANDARD AERO - REVISÃO GERAL | N98: {=INDEX('MTA 28-09'!U:U,MATCH(B98,'MTA 28-09'!A:A,0))} -> Revisão Geral PT6A-68C 06/20 | O98: {=INDEX('MTA 28-09'!AC:AC,MATCH(B98,'MTA 28-09'!A:A,0))} -> 478271.48 | P98: {=INDEX('MTA 28-09'!N:N,MATCH(B98,'MTA 28-09'!A:A,0))} -> CABW | Q98: {=INDEX('MTA 28-09'!Z:Z,MATCH(B98,'MTA 28-09'!A:A,0))} -> 339039 | R98: {=INDEX('MTA 28-09'!L:L,MATCH(B98,'MTA 28-09'!A:A,0))} -> A | S98: {=INDEX('MTA 28-09'!X:X,MATCH(B98,'MTA 28-09'!A:A,0))} -> SOB DEMANDA | T98: {=INDEX('MTA 28-09'!W:W,MATCH(B98,'MTA 28-09'!A:A,0))} -> SIM | U98: {=INDEX('MTA 28-09'!AE:AE,MATCH(B98,'MTA 28-09'!A:A,0))} -> 46260
A99: A-29 | B99: 11323 | C99: {=INDEX('MTA 28-09'!B:B,MATCH(B99,'MTA 28-09'!A:A,0))} -> SIM | D99: {=INDEX('MTA 28-09'!D:D,MATCH(B99,'MTA 28-09'!A:A,0))} -> DESTQ22 | E99: {=INDEX('MTA 28-09'!F:F,MATCH(B99,'MTA 28-09'!A:A,0))} -> ATENDIDO | F99: {=INDEX('MTA 28-09'!I:I,MATCH(B99,'MTA 28-09'!A:A,0))} -> 46176 | G99: {=INDEX('MTA 28-09'!J:J,MATCH(B99,'MTA 28-09'!A:A,0))} -> C26092 | L99: {=INDEX('MTA 28-09'!S:S,MATCH(B99,'MTA 28-09'!A:A,0))} -> A-29 | M99: {=INDEX('MTA 28-09'!T:T,MATCH(B99,'MTA 28-09'!A:A,0))} -> CNT 051/CELOG-PAMASP/2024 - STANDARD AERO - REVISÃO GERAL | N99: {=INDEX('MTA 28-09'!U:U,MATCH(B99,'MTA 28-09'!A:A,0))} -> Revisão Geral PT6A-68C 06/20 | O99: {=INDEX('MTA 28-09'!AC:AC,MATCH(B99,'MTA 28-09'!A:A,0))} -> 55298.61 | P99: {=INDEX('MTA 28-09'!N:N,MATCH(B99,'MTA 28-09'!A:A,0))} -> CABW | Q99: {=INDEX('MTA 28-09'!Z:Z,MATCH(B99,'MTA 28-09'!A:A,0))} -> 339039 | R99: {=INDEX('MTA 28-09'!L:L,MATCH(B99,'MTA 28-09'!A:A,0))} -> A | S99: {=INDEX('MTA 28-09'!X:X,MATCH(B99,'MTA 28-09'!A:A,0))} -> SOB DEMANDA | T99: {=INDEX('MTA 28-09'!W:W,MATCH(B99,'MTA 28-09'!A:A,0))} -> SIM | U99: {=INDEX('MTA 28-09'!AE:AE,MATCH(B99,'MTA 28-09'!A:A,0))} -> 46260
A100: A-29 | B100: 11324 | C100: {=INDEX('MTA 28-09'!B:B,MATCH(B100,'MTA 28-09'!A:A,0))} -> SIM | D100: {=INDEX('MTA 28-09'!D:D,MATCH(B100,'MTA 28-09'!A:A,0))} -> DESTQ23 | E100: {=INDEX('MTA 28-09'!F:F,MATCH(B100,'MTA 28-09'!A:A,0))} -> ATENDIDO | F100: {=INDEX('MTA 28-09'!I:I,MATCH(B100,'MTA 28-09'!A:A,0))} -> 46176 | G100: {=INDEX('MTA 28-09'!J:J,MATCH(B100,'MTA 28-09'!A:A,0))} -> C26109 | L100: {=INDEX('MTA 28-09'!S:S,MATCH(B100,'MTA 28-09'!A:A,0))} -> A-29 | M100: {=INDEX('MTA 28-09'!T:T,MATCH(B100,'MTA 28-09'!A:A,0))} -> CNT 051/CELOG-PAMASP/2024 - STANDARD AERO - REVISÃO GERAL | N100: {=INDEX('MTA 28-09'!U:U,MATCH(B100,'MTA 28-09'!A:A,0))} -> Revisão Geral PT6A-68C 06/20 | O100: {=INDEX('MTA 28-09'!AC:AC,MATCH(B100,'MTA 28-09'!A:A,0))} -> 35301.14 | P100: {=INDEX('MTA 28-09'!N:N,MATCH(B100,'MTA 28-09'!A:A,0))} -> CABW | Q100: {=INDEX('MTA 28-09'!Z:Z,MATCH(B100,'MTA 28-09'!A:A,0))} -> 339039 | R100: {=INDEX('MTA 28-09'!L:L,MATCH(B100,'MTA 28-09'!A:A,0))} -> A | S100: {=INDEX('MTA 28-09'!X:X,MATCH(B100,'MTA 28-09'!A:A,0))} -> SOB DEMANDA | T100: {=INDEX('MTA 28-09'!W:W,MATCH(B100,'MTA 28-09'!A:A,0))} -> SIM | U100: {=INDEX('MTA 28-09'!AE:AE,MATCH(B100,'MTA 28-09'!A:A,0))} -> 46260
...

Sheet Indução de material
B1: Previsão Serviço/material induzido SEM orçamento aprovado | C1: Serviço/material induzido COM orçamento aprovado
A2: 124/CAE-PAMALS/2022 | B2: 0 | C2: 1752159.1
A3: 096/CAE-PAMALS/2021 | B3: 1500000 | C3: 1125839.4
A4: 048/CAE-PAMALS/2022 | B4: 0 | C4: 222000.98
A5: 024/CELOG-PAMALS/2022 | B5: 26866.71 | C5: 2318718
A6: 040/CELOG-PAMALS/2022 | B6: 390000 | C6: 0
A7: 012/CELOG-PAMALS/2026
A8: 039/CELOG-PAMALS/2025 | B8: 0 | C8: 26684804
A9: 102/CELOG-PAMALS/2023 | B9: =20000+50000+40000+180000*20+1500000+460000+1000000 -> 6670000 | C9: =6833000+5756655+600000+500000+150000 -> 13839655
A10: 040/CELOG-PAMALS/2025 | B10: 242000 | C10: 288553
A11: 028/CELOG-PAMALS/2025 | B11: 0 | C11: 3671861.8
A12: 049/CELOG-PAMALS/2024 | B12: 0 | C12: 5882093.5
A13: 039/CABW-PAMALS/2024 | B13: 0 | C13: 4185411.6
A14: 005/CELOG-PAMALS/2025 | B14: 0 | C14: 0
A15: 009/CELOG-PAMALS/2025 | B15: 0 | C15: 3251894.3
A16: 016/CELOG-PAMALS/2025 | B16: 0 | C16: 28666.97
A17: 032/CELOG-PAMALS/2025 | B17: 0 | C17: 350432

Sheet PAINEL
A1: Célula
B2: A | C2: B | D2: C | E2: D | F2: Valor já atendido | G2: Valor aprovado | H2: Solicitado | I2: Parcela Fixa/HV não solicitado | J2: Valor a solicitar
A3: A-29 | B3: =SUMIFS('Solicitações'!$O:$O,'Solicitações'!$L:$L,$A3,'Solicitações'!$R:$R,B$2,'Solicitações'!$T:$T,"NÃO")-SUMIFS('Solicitações'!$O:$O,'Solicitações'!$L:$L,$A3,'Solicitações'!$R:$R,B$2,'Solicitações'!$T:$T,"NÃO",'Solicitações'!$C:$C,"RAP)") -> 1.0093971e+08 | C3: =SUMIFS('Solicitações'!$O:$O,'Solicitações'!$L:$L,$A3,'Solicitações'!$R:$R,C$2,'Solicitações'!$T:$T,"NÃO")-SUMIFS('Solicitações'!$O:$O,'Solicitações'!$L:$L,$A3,'Solicitações'!$R:$R,C$2,'Solicitações'!$T:$T,"NÃO",'Solicitações'!$C:$C,"RAP)") -> 150000 | D3: =SUMIFS('Solicitações'!$O:$O,'Solicitações'!$L:$L,$A3,'Solicitações'!$R:$R,D$2,'Solicitações'!$T:$T,"NÃO")-SUMIFS('Solicitações'!$O:$O,'Solicitações'!$L:$L,$A3,'Solicitações'!$R:$R,D$2,'Solicitações'!$T:$T,"NÃO",'Solicitações'!$C:$C,"RAP)") -> 23712543 | E3: =SUMIFS('Solicitações'!$O:$O,'Solicitações'!$L:$L,$A3,'Solicitações'!$R:$R,E$2,'Solicitações'!$T:$T,"NÃO")-SUMIFS('Solicitações'!$O:$O,'Solicitações'!$L:$L,$A3,'Solicitações'!$R:$R,E$2,'Solicitações'!$T:$T,"NÃO",'Solicitações'!$C:$C,"RAP)") -> 8561736.7 | F3: =SUMIFS('Solicitações'!$O:$O,'Solicitações'!$L:$L,$A3,'Solicitações'!$T:$T,"NÃO",'Solicitações'!E:E,"ATENDIDO")-SUMIFS('Solicitações'!$O:$O,'Solicitações'!$L:$L,$A3,'Solicitações'!$T:$T,"NÃO",'Solicitações'!E:E,"ATENDIDO",'Solicitações'!$R:$R,"RAP") -> 68490679 | G3: =SUMIFS('Solicitações'!$O:$O,'Solicitações'!$L:$L,$A3,'Solicitações'!$T:$T,"NÃO",'Solicitações'!C:C,"SIM")-SUMIFS('Solicitações'!$O:$O,'Solicitações'!$L:$L,$A3,'Solicitações'!$R:$R,"RAP",'Solicitações'!$T:$T,"NÃO") -> 1.0950145e+08 | H3: =SUMIFS('Solicitações'!$O:$O,'Solicitações'!$L:$L,$A3,'Solicitações'!$T:$T,"NÃO",'Solicitações'!E:E,"<>ATENDIDO",'Solicitações'!I:I,"<>",'Solicitações'!C:C,"SIM") -> 38672034 | I3: =SUMIFS('Solicitações'!$O:$O,'Solicitações'!$L:$L,$A3,'Solicitações'!$T:$T,"NÃO",'Solicitações'!E:E,"<>ATENDIDO",'Solicitações'!I:I,"",'Solicitações'!S:S,"HORA DE VOO",'Solicitações'!C:C,"SIM")+SUMIFS('Solicitações'!$O:$O,'Solicitações'!$L:$L,$A3,'Solicitações'!$T:$T,"NÃO",'Solicitações'!E:E,"<>ATENDIDO",'Solicitações'!I:I,"",'Solicitações'!S:S,"PARCELA FIXA",'Solicitações'!C:C,"SIM")-(SUMIFS('Solicitações'!$O:$O,'Solicitações'!$L:$L,$A3,'Solicitações'!$T:$T,"NÃO",'Solicitações'!E:E,"<>ATENDIDO",'Solicitações'!I:I,"",'Solicitações'!S:S,"HORA DE VOO",'Solicitações'!C:C,"SIM",'Solicitações'!$R:$R,"RAP")+SUMIFS('Solicitações'!$O:$O,'Solicitações'!$L:$L,$A3,'Solicitações'!$T:$T,"NÃO",'Solicitações'!E:E,"<>ATENDIDO",'Solicitações'!I:I,"",'Solicitações'!S:S,"PARCELA FIXA",'Solicitações'!C:C,"SIM",'Solicitações'!$R:$R,"RAP")) -> 2310000 | J3: =G3-F3-H3-I3 -> 28736.69
A4: C-95M | B4: =SUMIFS('Solicitações'!$O:$O,'Solicitações'!$L:$L,$A4,'Solicitações'!$R:$R,B$2,'Solicitações'!$T:$T,"NÃO")-SUMIFS('Solicitações'!$O:$O,'Solicitações'!$L:$L,$A4,'Solicitações'!$R:$R,B$2,'Solicitações'!$T:$T,"NÃO",'Solicitações'!$C:$C,"RAP)") -> 20604593 | C4: =SUMIFS('Solicitações'!$O:$O,'Solicitações'!$L:$L,$A4,'Solicitações'!$R:$R,C$2,'Solicitações'!$T:$T,"NÃO")-SUMIFS('Solicitações'!$O:$O,'Solicitações'!$L:$L,$A4,'Solicitações'!$R:$R,C$2,'Solicitações'!$T:$T,"NÃO",'Solicitações'!$C:$C,"RAP)") -> 8657582.3 | D4: =SUMIFS('Solicitações'!$O:$O,'Solicitações'!$L:$L,$A4,'Solicitações'!$R:$R,D$2,'Solicitações'!$T:$T,"NÃO")-SUMIFS('Solicitações'!$O:$O,'Solicitações'!$L:$L,$A4,'Solicitações'!$R:$R,D$2,'Solicitações'!$T:$T,"NÃO",'Solicitações'!$C:$C,"RAP)") -> 15993894 | E4: =SUMIFS('Solicitações'!$O:$O,'Solicitações'!$L:$L,$A4,'Solicitações'!$R:$R,E$2,'Solicitações'!$T:$T,"NÃO")-SUMIFS('Solicitações'!$O:$O,'Solicitações'!$L:$L,$A4,'Solicitações'!$R:$R,E$2,'Solicitações'!$T:$T,"NÃO",'Solicitações'!$C:$C,"RAP)") -> 0 | F4: =SUMIFS('Solicitações'!$O:$O,'Solicitações'!$L:$L,$A4,'Solicitações'!$T:$T,"NÃO",'Solicitações'!E:E,"ATENDIDO")-SUMIFS('Solicitações'!$O:$O,'Solicitações'!$L:$L,$A4,'Solicitações'!$T:$T,"NÃO",'Solicitações'!E:E,"ATENDIDO",'Solicitações'!$R:$R,"RAP") -> 18284399 | G4: =SUMIFS('Solicitações'!$O:$O,'Solicitações'!$L:$L,$A4,'Solicitações'!$T:$T,"NÃO",'Solicitações'!C:C,"SIM")-SUMIFS('Solicitações'!$O:$O,'Solicitações'!$L:$L,$A4,'Solicitações'!$R:$R,"RAP",'Solicitações'!$T:$T,"NÃO") -> 20604593 | H4: =SUMIFS('Solicitações'!$O:$O,'Solicitações'!$L:$L,$A4,'Solicitações'!$T:$T,"NÃO",'Solicitações'!E:E,"<>ATENDIDO",'Solicitações'!I:I,"<>",'Solicitações'!C:C,"SIM") -> 2320194.4 | I4: =SUMIFS('Solicitações'!$O:$O,'Solicitações'!$L:$L,$A4,'Solicitações'!$T:$T,"NÃO",'Solicitações'!E:E,"<>ATENDIDO",'Solicitações'!I:I,"",'Solicitações'!S:S,"HORA DE VOO",'Solicitações'!C:C,"SIM")+SUMIFS('Solicitações'!$O:$O,'Solicitações'!$L:$L,$A4,'Solicitações'!$T:$T,"NÃO",'Solicitações'!E:E,"<>ATENDIDO",'Solicitações'!I:I,"",'Solicitações'!S:S,"PARCELA FIXA",'Solicitações'!C:C,"SIM")-(SUMIFS('Solicitações'!$O:$O,'Solicitações'!$L:$L,$A4,'Solicitações'!$T:$T,"NÃO",'Solicitações'!E:E,"<>ATENDIDO",'Solicitações'!I:I,"",'Solicitações'!S:S,"HORA DE VOO",'Solicitações'!C:C,"SIM",'Solicitações'!$R:$R,"RAP")+SUMIFS('Solicitações'!$O:$O,'Solicitações'!$L:$L,$A4,'Solicitações'!$T:$T,"NÃO",'Solicitações'!E:E,"<>ATENDIDO",'Solicitações'!I:I,"",'Solicitações'!S:S,"PARCELA FIXA",'Solicitações'!C:C,"SIM",'Solicitações'!$R:$R,"RAP")) -> 0 | J4: =G4-F4-H4-I4 -> 2.3283064e-09
A5: C-97 | B5: =SUMIFS('Solicitações'!$O:$O,'Solicitações'!$L:$L,$A5,'Solicitações'!$R:$R,B$2,'Solicitações'!$T:$T,"NÃO")-SUMIFS('Solicitações'!$O:$O,'Solicitações'!$L:$L,$A5,'Solicitações'!$R:$R,B$2,'Solicitações'!$T:$T,"NÃO",'Solicitações'!$C:$C,"RAP)") -> 21882444 | C5: =SUMIFS('Solicitações'!$O:$O,'Solicitações'!$L:$L,$A5,'Solicitações'!$R:$R,C$2,'Solicitações'!$T:$T,"NÃO")-SUMIFS('Solicitações'!$O:$O,'Solicitações'!$L:$L,$A5,'Solicitações'!$R:$R,C$2,'Solicitações'!$T:$T,"NÃO",'Solicitações'!$C:$C,"RAP)") -> 9805560.9 | D5: =SUMIFS('Solicitações'!$O:$O,'Solicitações'!$L:$L,$A5,'Solicitações'!$R:$R,D$2,'Solicitações'!$T:$T,"NÃO")-SUMIFS('Solicitações'!$O:$O,'Solicitações'!$L:$L,$A5,'Solicitações'!$R:$R,D$2,'Solicitações'!$T:$T,"NÃO",'Solicitações'!$C:$C,"RAP)") -> 23958627 | E5: =SUMIFS('Solicitações'!$O:$O,'Solicitações'!$L:$L,$A5,'Solicitações'!$R:$R,E$2,'Solicitações'!$T:$T,"NÃO")-SUMIFS('Solicitações'!$O:$O,'Solicitações'!$L:$L,$A5,'Solicitações'!$R:$R,E$2,'Solicitações'!$T:$T,"NÃO",'Solicitações'!$C:$C,"RAP)") -> 10120308 | F5: =SUMIFS('Solicitações'!$O:$O,'Solicitações'!$L:$L,$A5,'Solicitações'!$T:$T,"NÃO",'Solicitações'!E:E,"ATENDIDO")-SUMIFS('Solicitações'!$O:$O,'Solicitações'!$L:$L,$A5,'Solicitações'!$T:$T,"NÃO",'Solicitações'!E:E,"ATENDIDO",'Solicitações'!$R:$R,"RAP") -> 27192694 | G5: =SUMIFS('Solicitações'!$O:$O,'Solicitações'!$L:$L,$A5,'Solicitações'!$T:$T,"NÃO",'Solicitações'!C:C,"SIM")-SUMIFS('Solicitações'!$O:$O,'Solicitações'!$L:$L,$A5,'Solicitações'!$R:$R,"RAP",'Solicitações'!$T:$T,"NÃO") -> 29512752 | H5: =SUMIFS('Solicitações'!$O:$O,'Solicitações'!$L:$L,$A5,'Solicitações'!$T:$T,"NÃO",'Solicitações'!E:E,"<>ATENDIDO",'Solicitações'!I:I,"<>",'Solicitações'!C:C,"SIM") -> 345782.57 | I5: =SUMIFS('Solicitações'!$O:$O,'Solicitações'!$L:$L,$A5,'Solicitações'!$T:$T,"NÃO",'Solicitações'!E:E,"<>ATENDIDO",'Solicitações'!I:I,"",'Solicitações'!S:S,"HORA DE VOO",'Solicitações'!C:C,"SIM")+SUMIFS('Solicitações'!$O:$O,'Solicitações'!$L:$L,$A5,'Solicitações'!$T:$T,"NÃO",'Solicitações'!E:E,"<>ATENDIDO",'Solicitações'!I:I,"",'Solicitações'!S:S,"PARCELA FIXA",'Solicitações'!C:C,"SIM")-(SUMIFS('Solicitações'!$O:$O,'Solicitações'!$L:$L,$A5,'Solicitações'!$T:$T,"NÃO",'Solicitações'!E:E,"<>ATENDIDO",'Solicitações'!I:I,"",'Solicitações'!S:S,"HORA DE VOO",'Solicitações'!C:C,"SIM",'Solicitações'!$R:$R,"RAP")+SUMIFS('Solicitações'!$O:$O,'Solicitações'!$L:$L,$A5,'Solicitações'!$T:$T,"NÃO",'Solicitações'!E:E,"<>ATENDIDO",'Solicitações'!I:I,"",'Solicitações'!S:S,"PARCELA FIXA",'Solicitações'!C:C,"SIM",'Solicitações'!$R:$R,"RAP")) -> 0 | J5: =G5-F5-H5-I5 -> 1974275.1
A6: C-98 | B6: =SUMIFS('Solicitações'!$O:$O,'Solicitações'!$L:$L,$A6,'Solicitações'!$R:$R,B$2,'Solicitações'!$T:$T,"NÃO")-SUMIFS('Solicitações'!$O:$O,'Solicitações'!$L:$L,$A6,'Solicitações'!$R:$R,B$2,'Solicitações'!$T:$T,"NÃO",'Solicitações'!$C:$C,"RAP)") -> 18111550 | C6: =SUMIFS('Solicitações'!$O:$O,'Solicitações'!$L:$L,$A6,'Solicitações'!$R:$R,C$2,'Solicitações'!$T:$T,"NÃO")-SUMIFS('Solicitações'!$O:$O,'Solicitações'!$L:$L,$A6,'Solicitações'!$R:$R,C$2,'Solicitações'!$T:$T,"NÃO",'Solicitações'!$C:$C,"RAP)") -> 0 | D6: =SUMIFS('Solicitações'!$O:$O,'Solicitações'!$L:$L,$A6,'Solicitações'!$R:$R,D$2,'Solicitações'!$T:$T,"NÃO")-SUMIFS('Solicitações'!$O:$O,'Solicitações'!$L:$L,$A6,'Solicitações'!$R:$R,D$2,'Solicitações'!$T:$T,"NÃO",'Solicitações'!$C:$C,"RAP)") -> 3129713.5 | E6: =SUMIFS('Solicitações'!$O:$O,'Solicitações'!$L:$L,$A6,'Solicitações'!$R:$R,E$2,'Solicitações'!$T:$T,"NÃO")-SUMIFS('Solicitações'!$O:$O,'Solicitações'!$L:$L,$A6,'Solicitações'!$R:$R,E$2,'Solicitações'!$T:$T,"NÃO",'Solicitações'!$C:$C,"RAP)") -> 4460068.7 | F6: =SUMIFS('Solicitações'!$O:$O,'Solicitações'!$L:$L,$A6,'Solicitações'!$T:$T,"NÃO",'Solicitações'!E:E,"ATENDIDO")-SUMIFS('Solicitações'!$O:$O,'Solicitações'!$L:$L,$A6,'Solicitações'!$T:$T,"NÃO",'Solicitações'!E:E,"ATENDIDO",'Solicitações'!$R:$R,"RAP") -> 8992525.3 | G6: =SUMIFS('Solicitações'!$O:$O,'Solicitações'!$L:$L,$A6,'Solicitações'!$T:$T,"NÃO",'Solicitações'!C:C,"SIM")-SUMIFS('Solicitações'!$O:$O,'Solicitações'!$L:$L,$A6,'Solicitações'!$R:$R,"RAP",'Solicitações'!$T:$T,"NÃO") -> 20074528 | H6: =SUMIFS('Solicitações'!$O:$O,'Solicitações'!$L:$L,$A6,'Solicitações'!$T:$T,"NÃO",'Solicitações'!E:E,"<>ATENDIDO",'Solicitações'!I:I,"<>",'Solicitações'!C:C,"SIM") -> 11082002 | I6: =SUMIFS('Solicitações'!$O:$O,'Solicitações'!$L:$L,$A6,'Solicitações'!$T:$T,"NÃO",'Solicitações'!E:E,"<>ATENDIDO",'Solicitações'!I:I,"",'Solicitações'!S:S,"HORA DE VOO",'Solicitações'!C:C,"SIM")+SUMIFS('Solicitações'!$O:$O,'Solicitações'!$L:$L,$A6,'Solicitações'!$T:$T,"NÃO",'Solicitações'!E:E,"<>ATENDIDO",'Solicitações'!I:I,"",'Solicitações'!S:S,"PARCELA FIXA",'Solicitações'!C:C,"SIM")-(SUMIFS('Solicitações'!$O:$O,'Solicitações'!$L:$L,$A6,'Solicitações'!$T:$T,"NÃO",'Solicitações'!E:E,"<>ATENDIDO",'Solicitações'!I:I,"",'Solicitações'!S:S,"HORA DE VOO",'Solicitações'!C:C,"SIM",'Solicitações'!$R:$R,"RAP")+SUMIFS('Solicitações'!$O:$O,'Solicitações'!$L:$L,$A6,'Solicitações'!$T:$T,"NÃO",'Solicitações'!E:E,"<>ATENDIDO",'Solicitações'!I:I,"",'Solicitações'!S:S,"PARCELA FIXA",'Solicitações'!C:C,"SIM",'Solicitações'!$R:$R,"RAP")) -> 0 | J6: =G6-F6-H6-I6 -> 0
A7: T-27 | B7: =SUMIFS('Solicitações'!$O:$O,'Solicitações'!$L:$L,$A7,'Solicitações'!$R:$R,B$2,'Solicitações'!$T:$T,"NÃO")-SUMIFS('Solicitações'!$O:$O,'Solicitações'!$L:$L,$A7,'Solicitações'!$R:$R,B$2,'Solicitações'!$T:$T,"NÃO",'Solicitações'!$C:$C,"RAP)") -> 14322283 | C7: =SUMIFS('Solicitações'!$O:$O,'Solicitações'!$L:$L,$A7,'Solicitações'!$R:$R,C$2,'Solicitações'!$T:$T,"NÃO")-SUMIFS('Solicitações'!$O:$O,'Solicitações'!$L:$L,$A7,'Solicitações'!$R:$R,C$2,'Solicitações'!$T:$T,"NÃO",'Solicitações'!$C:$C,"RAP)") -> 0 | D7: =SUMIFS('Solicitações'!$O:$O,'Solicitações'!$L:$L,$A7,'Solicitações'!$R:$R,D$2,'Solicitações'!$T:$T,"NÃO")-SUMIFS('Solicitações'!$O:$O,'Solicitações'!$L:$L,$A7,'Solicitações'!$R:$R,D$2,'Solicitações'!$T:$T,"NÃO",'Solicitações'!$C:$C,"RAP)") -> 4613603.1 | E7: =SUMIFS('Solicitações'!$O:$O,'Solicitações'!$L:$L,$A7,'Solicitações'!$R:$R,E$2,'Solicitações'!$T:$T,"NÃO")-SUMIFS('Solicitações'!$O:$O,'Solicitações'!$L:$L,$A7,'Solicitações'!$R:$R,E$2,'Solicitações'!$T:$T,"NÃO",'Solicitações'!$C:$C,"RAP)") -> 5073979 | F7: =SUMIFS('Solicitações'!$O:$O,'Solicitações'!$L:$L,$A7,'Solicitações'!$T:$T,"NÃO",'Solicitações'!E:E,"ATENDIDO")-SUMIFS('Solicitações'!$O:$O,'Solicitações'!$L:$L,$A7,'Solicitações'!$T:$T,"NÃO",'Solicitações'!E:E,"ATENDIDO",'Solicitações'!$R:$R,"RAP") -> 9714849.5 | G7: =SUMIFS('Solicitações'!$O:$O,'Solicitações'!$L:$L,$A7,'Solicitações'!$T:$T,"NÃO",'Solicitações'!C:C,"SIM")-SUMIFS('Solicitações'!$O:$O,'Solicitações'!$L:$L,$A7,'Solicitações'!$R:$R,"RAP",'Solicitações'!$T:$T,"NÃO") -> 19396262 | H7: =SUMIFS('Solicitações'!$O:$O,'Solicitações'!$L:$L,$A7,'Solicitações'!$T:$T,"NÃO",'Solicitações'!E:E,"<>ATENDIDO",'Solicitações'!I:I,"<>",'Solicitações'!C:C,"SIM") -> 9681412.2 | I7: =SUMIFS('Solicitações'!$O:$O,'Solicitações'!$L:$L,$A7,'Solicitações'!$T:$T,"NÃO",'Solicitações'!E:E,"<>ATENDIDO",'Solicitações'!I:I,"",'Solicitações'!S:S,"HORA DE VOO",'Solicitações'!C:C,"SIM")+SUMIFS('Solicitações'!$O:$O,'Solicitações'!$L:$L,$A7,'Solicitações'!$T:$T,"NÃO",'Solicitações'!E:E,"<>ATENDIDO",'Solicitações'!I:I,"",'Solicitações'!S:S,"PARCELA FIXA",'Solicitações'!C:C,"SIM")-(SUMIFS('Solicitações'!$O:$O,'Solicitações'!$L:$L,$A7,'Solicitações'!$T:$T,"NÃO",'Solicitações'!E:E,"<>ATENDIDO",'Solicitações'!I:I,"",'Solicitações'!S:S,"HORA DE VOO",'Solicitações'!C:C,"SIM",'Solicitações'!$R:$R,"RAP")+SUMIFS('Solicitações'!$O:$O,'Solicitações'!$L:$L,$A7,'Solicitações'!$T:$T,"NÃO",'Solicitações'!E:E,"<>ATENDIDO",'Solicitações'!I:I,"",'Solicitações'!S:S,"PARCELA FIXA",'Solicitações'!C:C,"SIM",'Solicitações'!$R:$R,"RAP")) -> 0 | J7: =G7-F7-H7-I7 -> 1.8626451e-09
A8: T-25 | B8: =SUMIFS('Solicitações'!$O:$O,'Solicitações'!$L:$L,$A8,'Solicitações'!$R:$R,B$2,'Solicitações'!$T:$T,"NÃO")-SUMIFS('Solicitações'!$O:$O,'Solicitações'!$L:$L,$A8,'Solicitações'!$R:$R,B$2,'Solicitações'!$T:$T,"NÃO",'Solicitações'!$C:$C,"RAP)") -> 5680758.8 | C8: =SUMIFS('Solicitações'!$O:$O,'Solicitações'!$L:$L,$A8,'Solicitações'!$R:$R,C$2,'Solicitações'!$T:$T,"NÃO")-SUMIFS('Solicitações'!$O:$O,'Solicitações'!$L:$L,$A8,'Solicitações'!$R:$R,C$2,'Solicitações'!$T:$T,"NÃO",'Solicitações'!$C:$C,"RAP)") -> 5930000 | D8: =SUMIFS('Solicitações'!$O:$O,'Solicitações'!$L:$L,$A8,'Solicitações'!$R:$R,D$2,'Solicitações'!$T:$T,"NÃO")-SUMIFS('Solicitações'!$O:$O,'Solicitações'!$L:$L,$A8,'Solicitações'!$R:$R,D$2,'Solicitações'!$T:$T,"NÃO",'Solicitações'!$C:$C,"RAP)") -> 450000 | E8: =SUMIFS('Solicitações'!$O:$O,'Solicitações'!$L:$L,$A8,'Solicitações'!$R:$R,E$2,'Solicitações'!$T:$T,"NÃO")-SUMIFS('Solicitações'!$O:$O,'Solicitações'!$L:$L,$A8,'Solicitações'!$R:$R,E$2,'Solicitações'!$T:$T,"NÃO",'Solicitações'!$C:$C,"RAP)") -> 34900000 | F8: =SUMIFS('Solicitações'!$O:$O,'Solicitações'!$L:$L,$A8,'Solicitações'!$T:$T,"NÃO",'Solicitações'!E:E,"ATENDIDO")-SUMIFS('Solicitações'!$O:$O,'Solicitações'!$L:$L,$A8,'Solicitações'!$T:$T,"NÃO",'Solicitações'!E:E,"ATENDIDO",'Solicitações'!$R:$R,"RAP") -> 9079089.5 | G8: =SUMIFS('Solicitações'!$O:$O,'Solicitações'!$L:$L,$A8,'Solicitações'!$T:$T,"NÃO",'Solicitações'!C:C,"SIM")-SUMIFS('Solicitações'!$O:$O,'Solicitações'!$L:$L,$A8,'Solicitações'!$R:$R,"RAP",'Solicitações'!$T:$T,"NÃO") -> 9935639.8 | H8: =SUMIFS('Solicitações'!$O:$O,'Solicitações'!$L:$L,$A8,'Solicitações'!$T:$T,"NÃO",'Solicitações'!E:E,"<>ATENDIDO",'Solicitações'!I:I,"<>",'Solicitações'!C:C,"SIM") -> 856550.33 | I8: =SUMIFS('Solicitações'!$O:$O,'Solicitações'!$L:$L,$A8,'Solicitações'!$T:$T,"NÃO",'Solicitações'!E:E,"<>ATENDIDO",'Solicitações'!I:I,"",'Solicitações'!S:S,"HORA DE VOO",'Solicitações'!C:C,"SIM")+SUMIFS('Solicitações'!$O:$O,'Solicitações'!$L:$L,$A8,'Solicitações'!$T:$T,"NÃO",'Solicitações'!E:E,"<>ATENDIDO",'Solicitações'!I:I,"",'Solicitações'!S:S,"PARCELA FIXA",'Solicitações'!C:C,"SIM")-(SUMIFS('Solicitações'!$O:$O,'Solicitações'!$L:$L,$A8,'Solicitações'!$T:$T,"NÃO",'Solicitações'!E:E,"<>ATENDIDO",'Solicitações'!I:I,"",'Solicitações'!S:S,"HORA DE VOO",'Solicitações'!C:C,"SIM",'Solicitações'!$R:$R,"RAP")+SUMIFS('Solicitações'!$O:$O,'Solicitações'!$L:$L,$A8,'Solicitações'!$T:$T,"NÃO",'Solicitações'!E:E,"<>ATENDIDO",'Solicitações'!I:I,"",'Solicitações'!S:S,"PARCELA FIXA",'Solicitações'!C:C,"SIM",'Solicitações'!$R:$R,"RAP")) -> 0 | J8: =G8-F8-H8-I8 -> 0
A9: G-19 | B9: =SUMIFS('Solicitações'!$O:$O,'Solicitações'!$L:$L,$A9,'Solicitações'!$R:$R,B$2,'Solicitações'!$T:$T,"NÃO")-SUMIFS('Solicitações'!$O:$O,'Solicitações'!$L:$L,$A9,'Solicitações'!$R:$R,B$2,'Solicitações'!$T:$T,"NÃO",'Solicitações'!$C:$C,"RAP)") -> 437136.29 | C9: =SUMIFS('Solicitações'!$O:$O,'Solicitações'!$L:$L,$A9,'Solicitações'!$R:$R,C$2,'Solicitações'!$T:$T,"NÃO")-SUMIFS('Solicitações'!$O:$O,'Solicitações'!$L:$L,$A9,'Solicitações'!$R:$R,C$2,'Solicitações'!$T:$T,"NÃO",'Solicitações'!$C:$C,"RAP)") -> 90000 | D9: =SUMIFS('Solicitações'!$O:$O,'Solicitações'!$L:$L,$A9,'Solicitações'!$R:$R,D$2,'Solicitações'!$T:$T,"NÃO")-SUMIFS('Solicitações'!$O:$O,'Solicitações'!$L:$L,$A9,'Solicitações'!$R:$R,D$2,'Solicitações'!$T:$T,"NÃO",'Solicitações'!$C:$C,"RAP)") -> 520000 | E9: =SUMIFS('Solicitações'!$O:$O,'Solicitações'!$L:$L,$A9,'Solicitações'!$R:$R,E$2,'Solicitações'!$T:$T,"NÃO")-SUMIFS('Solicitações'!$O:$O,'Solicitações'!$L:$L,$A9,'Solicitações'!$R:$R,E$2,'Solicitações'!$T:$T,"NÃO",'Solicitações'!$C:$C,"RAP)") -> 0 | F9: =SUMIFS('Solicitações'!$O:$O,'Solicitações'!$L:$L,$A9,'Solicitações'!$T:$T,"NÃO",'Solicitações'!E:E,"ATENDIDO")-SUMIFS('Solicitações'!$O:$O,'Solicitações'!$L:$L,$A9,'Solicitações'!$T:$T,"NÃO",'Solicitações'!E:E,"ATENDIDO",'Solicitações'!$R:$R,"RAP") -> 272136.29 | G9: =SUMIFS('Solicitações'!$O:$O,'Solicitações'!$L:$L,$A9,'Solicitações'!$T:$T,"NÃO",'Solicitações'!C:C,"SIM")-SUMIFS('Solicitações'!$O:$O,'Solicitações'!$L:$L,$A9,'Solicitações'!$R:$R,"RAP",'Solicitações'!$T:$T,"NÃO") -> 437136.29 | H9: =SUMIFS('Solicitações'!$O:$O,'Solicitações'!$L:$L,$A9,'Solicitações'!$T:$T,"NÃO",'Solicitações'!E:E,"<>ATENDIDO",'Solicitações'!I:I,"<>",'Solicitações'!C:C,"SIM") -> 165000 | I9: =SUMIFS('Solicitações'!$O:$O,'Solicitações'!$L:$L,$A9,'Solicitações'!$T:$T,"NÃO",'Solicitações'!E:E,"<>ATENDIDO",'Solicitações'!I:I,"",'Solicitações'!S:S,"HORA DE VOO",'Solicitações'!C:C,"SIM")+SUMIFS('Solicitações'!$O:$O,'Solicitações'!$L:$L,$A9,'Solicitações'!$T:$T,"NÃO",'Solicitações'!E:E,"<>ATENDIDO",'Solicitações'!I:I,"",'Solicitações'!S:S,"PARCELA FIXA",'Solicitações'!C:C,"SIM")-(SUMIFS('Solicitações'!$O:$O,'Solicitações'!$L:$L,$A9,'Solicitações'!$T:$T,"NÃO",'Solicitações'!E:E,"<>ATENDIDO",'Solicitações'!I:I,"",'Solicitações'!S:S,"HORA DE VOO",'Solicitações'!C:C,"SIM",'Solicitações'!$R:$R,"RAP")+SUMIFS('Solicitações'!$O:$O,'Solicitações'!$L:$L,$A9,'Solicitações'!$T:$T,"NÃO",'Solicitações'!E:E,"<>ATENDIDO",'Solicitações'!I:I,"",'Solicitações'!S:S,"PARCELA FIXA",'Solicitações'!C:C,"SIM",'Solicitações'!$R:$R,"RAP")) -> 0 | J9: =G9-F9-H9-I9 -> 0
A10: IU-93M | B10: =SUMIFS('Solicitações'!$O:$O,'Solicitações'!$L:$L,$A10,'Solicitações'!$R:$R,B$2,'Solicitações'!$T:$T,"NÃO")-SUMIFS('Solicitações'!$O:$O,'Solicitações'!$L:$L,$A10,'Solicitações'!$R:$R,B$2,'Solicitações'!$T:$T,"NÃO",'Solicitações'!$C:$C,"RAP)") -> 23299617 | C10: =SUMIFS('Solicitações'!$O:$O,'Solicitações'!$L:$L,$A10,'Solicitações'!$R:$R,C$2,'Solicitações'!$T:$T,"NÃO")-SUMIFS('Solicitações'!$O:$O,'Solicitações'!$L:$L,$A10,'Solicitações'!$R:$R,C$2,'Solicitações'!$T:$T,"NÃO",'Solicitações'!$C:$C,"RAP)") -> 435113.38 | D10: =SUMIFS('Solicitações'!$O:$O,'Solicitações'!$L:$L,$A10,'Solicitações'!$R:$R,D$2,'Solicitações'!$T:$T,"NÃO")-SUMIFS('Solicitações'!$O:$O,'Solicitações'!$L:$L,$A10,'Solicitações'!$R:$R,D$2,'Solicitações'!$T:$T,"NÃO",'Solicitações'!$C:$C,"RAP)") -> 21349999 | E10: =SUMIFS('Solicitações'!$O:$O,'Solicitações'!$L:$L,$A10,'Solicitações'!$R:$R,E$2,'Solicitações'!$T:$T,"NÃO")-SUMIFS('Solicitações'!$O:$O,'Solicitações'!$L:$L,$A10,'Solicitações'!$R:$R,E$2,'Solicitações'!$T:$T,"NÃO",'Solicitações'!$C:$C,"RAP)") -> 0 | F10: =SUMIFS('Solicitações'!$O:$O,'Solicitações'!$L:$L,$A10,'Solicitações'!$T:$T,"NÃO",'Solicitações'!E:E,"ATENDIDO")-SUMIFS('Solicitações'!$O:$O,'Solicitações'!$L:$L,$A10,'Solicitações'!$T:$T,"NÃO",'Solicitações'!E:E,"ATENDIDO",'Solicitações'!$R:$R,"RAP") -> 37491736 | G10: =SUMIFS('Solicitações'!$O:$O,'Solicitações'!$L:$L,$A10,'Solicitações'!$T:$T,"NÃO",'Solicitações'!C:C,"SIM")-SUMIFS('Solicitações'!$O:$O,'Solicitações'!$L:$L,$A10,'Solicitações'!$R:$R,"RAP",'Solicitações'!$T:$T,"NÃO") -> 43779616 | H10: =SUMIFS('Solicitações'!$O:$O,'Solicitações'!$L:$L,$A10,'Solicitações'!$T:$T,"NÃO",'Solicitações'!E:E,"<>ATENDIDO",'Solicitações'!I:I,"<>",'Solicitações'!C:C,"SIM") -> 4320125 | I10: =SUMIFS('Solicitações'!$O:$O,'Solicitações'!$L:$L,$A10,'Solicitações'!$T:$T,"NÃO",'Solicitações'!E:E,"<>ATENDIDO",'Solicitações'!I:I,"",'Solicitações'!S:S,"HORA DE VOO",'Solicitações'!C:C,"SIM")+SUMIFS('Solicitações'!$O:$O,'Solicitações'!$L:$L,$A10,'Solicitações'!$T:$T,"NÃO",'Solicitações'!E:E,"<>ATENDIDO",'Solicitações'!I:I,"",'Solicitações'!S:S,"PARCELA FIXA",'Solicitações'!C:C,"SIM")-(SUMIFS('Solicitações'!$O:$O,'Solicitações'!$L:$L,$A10,'Solicitações'!$T:$T,"NÃO",'Solicitações'!E:E,"<>ATENDIDO",'Solicitações'!I:I,"",'Solicitações'!S:S,"HORA DE VOO",'Solicitações'!C:C,"SIM",'Solicitações'!$R:$R,"RAP")+SUMIFS('Solicitações'!$O:$O,'Solicitações'!$L:$L,$A10,'Solicitações'!$T:$T,"NÃO",'Solicitações'!E:E,"<>ATENDIDO",'Solicitações'!I:I,"",'Solicitações'!S:S,"PARCELA FIXA",'Solicitações'!C:C,"SIM",'Solicitações'!$R:$R,"RAP")) -> 0 | J10: =G10-F10-H10-I10 -> 1967755
A11: APOIO | B11: =SUMIFS('Solicitações'!$O:$O,'Solicitações'!$L:$L,$A11,'Solicitações'!$R:$R,B$2,'Solicitações'!$T:$T,"NÃO")-SUMIFS('Solicitações'!$O:$O,'Solicitações'!$L:$L,$A11,'Solicitações'!$R:$R,B$2,'Solicitações'!$T:$T,"NÃO",'Solicitações'!$C:$C,"RAP)") -> 25990564 | C11: =SUMIFS('Solicitações'!$O:$O,'Solicitações'!$L:$L,$A11,'Solicitações'!$R:$R,C$2,'Solicitações'!$T:$T,"NÃO")-SUMIFS('Solicitações'!$O:$O,'Solicitações'!$L:$L,$A11,'Solicitações'!$R:$R,C$2,'Solicitações'!$T:$T,"NÃO",'Solicitações'!$C:$C,"RAP)") -> 10181158 | D11: =SUMIFS('Solicitações'!$O:$O,'Solicitações'!$L:$L,$A11,'Solicitações'!$R:$R,D$2,'Solicitações'!$T:$T,"NÃO")-SUMIFS('Solicitações'!$O:$O,'Solicitações'!$L:$L,$A11,'Solicitações'!$R:$R,D$2,'Solicitações'!$T:$T,"NÃO",'Solicitações'!$C:$C,"RAP)") -> 59507656 | E11: =SUMIFS('Solicitações'!$O:$O,'Solicitações'!$L:$L,$A11,'Solicitações'!$R:$R,E$2,'Solicitações'!$T:$T,"NÃO")-SUMIFS('Solicitações'!$O:$O,'Solicitações'!$L:$L,$A11,'Solicitações'!$R:$R,E$2,'Solicitações'!$T:$T,"NÃO",'Solicitações'!$C:$C,"RAP)") -> 0 | F11: =SUMIFS('Solicitações'!$O:$O,'Solicitações'!$L:$L,$A11,'Solicitações'!$T:$T,"NÃO",'Solicitações'!E:E,"ATENDIDO")-SUMIFS('Solicitações'!$O:$O,'Solicitações'!$L:$L,$A11,'Solicitações'!$T:$T,"NÃO",'Solicitações'!E:E,"ATENDIDO",'Solicitações'!$R:$R,"RAP") -> 13022163 | G11: =SUMIFS('Solicitações'!$O:$O,'Solicitações'!$L:$L,$A11,'Solicitações'!$T:$T,"NÃO",'Solicitações'!C:C,"SIM")-SUMIFS('Solicitações'!$O:$O,'Solicitações'!$L:$L,$A11,'Solicitações'!$R:$R,"RAP",'Solicitações'!$T:$T,"NÃO") -> 39711034 | H11: =SUMIFS('Solicitações'!$O:$O,'Solicitações'!$L:$L,$A11,'Solicitações'!$T:$T,"NÃO",'Solicitações'!E:E,"<>ATENDIDO",'Solicitações'!I:I,"<>",'Solicitações'!C:C,"SIM") -> 18309871 | I11: =SUMIFS('Solicitações'!$O:$O,'Solicitações'!$L:$L,$A11,'Solicitações'!$T:$T,"NÃO",'Solicitações'!E:E,"<>ATENDIDO",'Solicitações'!I:I,"",'Solicitações'!S:S,"HORA DE VOO",'Solicitações'!C:C,"SIM")+SUMIFS('Solicitações'!$O:$O,'Solicitações'!$L:$L,$A11,'Solicitações'!$T:$T,"NÃO",'Solicitações'!E:E,"<>ATENDIDO",'Solicitações'!I:I,"",'Solicitações'!S:S,"PARCELA FIXA",'Solicitações'!C:C,"SIM")-(SUMIFS('Solicitações'!$O:$O,'Solicitações'!$L:$L,$A11,'Solicitações'!$T:$T,"NÃO",'Solicitações'!E:E,"<>ATENDIDO",'Solicitações'!I:I,"",'Solicitações'!S:S,"HORA DE VOO",'Solicitações'!C:C,"SIM",'Solicitações'!$R:$R,"RAP")+SUMIFS('Solicitações'!$O:$O,'Solicitações'!$L:$L,$A11,'Solicitações'!$T:$T,"NÃO",'Solicitações'!E:E,"<>ATENDIDO",'Solicitações'!I:I,"",'Solicitações'!S:S,"PARCELA FIXA",'Solicitações'!C:C,"SIM",'Solicitações'!$R:$R,"RAP")) -> 0 | J11: =G11-F11-H11-I11 -> 8379000
A13: Motores
B14: A | C14: B | D14: C | E14: D | F14: Valor já atendido | G14: Valor aprovado | H14: Solicitado | I14: Parcela Fixa/HV não solicitado | J14: Valor a solicitar
A15: A-29 | B15: =SUMIFS('Solicitações'!$O:$O,'Solicitações'!$L:$L,$A15,'Solicitações'!$R:$R,B$2,'Solicitações'!$T:$T,"SIM") -> 73968553 | C15: =SUMIFS('Solicitações'!$O:$O,'Solicitações'!$L:$L,$A15,'Solicitações'!$R:$R,C$2,'Solicitações'!$T:$T,"SIM") -> 0 | D15: =SUMIFS('Solicitações'!$O:$O,'Solicitações'!$L:$L,$A15,'Solicitações'!$R:$R,D$2,'Solicitações'!$T:$T,"SIM") -> 72516379 | E15: =SUMIFS('Solicitações'!$O:$O,'Solicitações'!$L:$L,$A15,'Solicitações'!$R:$R,E$2,'Solicitações'!$T:$T,"SIM") -> 0 | F15: =SUMIFS('Solicitações'!$O:$O,'Solicitações'!$L:$L,$A15,'Solicitações'!$T:$T,"SIM",'Solicitações'!E:E,"ATENDIDO")-SUMIFS('Solicitações'!$O:$O,'Solicitações'!$L:$L,$A15,'Solicitações'!$T:$T,"SIM",'Solicitações'!E:E,"ATENDIDO",'Solicitações'!$R:$R,"RAP") -> 70972607 | G15: =SUMIFS('Solicitações'!$O:$O,'Solicitações'!$L:$L,$A15,'Solicitações'!$T:$T,"SIM",'Solicitações'!C:C,"SIM")-SUMIFS('Solicitações'!$O:$O,'Solicitações'!$L:$L,$A15,'Solicitações'!$R:$R,"RAP",'Solicitações'!$T:$T,"SIM") -> 1.4648493e+08 | H15: =SUMIFS('Solicitações'!$O:$O,'Solicitações'!$L:$L,$A15,'Solicitações'!$T:$T,"SIM",'Solicitações'!E:E,"<>ATENDIDO",'Solicitações'!I:I,"<>",'Solicitações'!C:C,"SIM") -> 0 | J15: =G15-F15-H15-I15 -> 75512325
A16: C-95M | B16: =SUMIFS('Solicitações'!$O:$O,'Solicitações'!$L:$L,$A16,'Solicitações'!$R:$R,B$2,'Solicitações'!$T:$T,"SIM") -> 24967290 | C16: =SUMIFS('Solicitações'!$O:$O,'Solicitações'!$L:$L,$A16,'Solicitações'!$R:$R,C$2,'Solicitações'!$T:$T,"SIM") -> 0 | D16: =SUMIFS('Solicitações'!$O:$O,'Solicitações'!$L:$L,$A16,'Solicitações'!$R:$R,D$2,'Solicitações'!$T:$T,"SIM") -> 38700000 | E16: =SUMIFS('Solicitações'!$O:$O,'Solicitações'!$L:$L,$A16,'Solicitações'!$R:$R,E$2,'Solicitações'!$T:$T,"SIM") -> 0 | F16: =SUMIFS('Solicitações'!$O:$O,'Solicitações'!$L:$L,$A16,'Solicitações'!$T:$T,"SIM",'Solicitações'!E:E,"ATENDIDO")-SUMIFS('Solicitações'!$O:$O,'Solicitações'!$L:$L,$A16,'Solicitações'!$T:$T,"SIM",'Solicitações'!E:E,"ATENDIDO",'Solicitações'!$R:$R,"RAP") -> 24767290 | G16: =SUMIFS('Solicitações'!$O:$O,'Solicitações'!$L:$L,$A16,'Solicitações'!$T:$T,"SIM",'Solicitações'!C:C,"SIM")-SUMIFS('Solicitações'!$O:$O,'Solicitações'!$L:$L,$A16,'Solicitações'!$R:$R,"RAP",'Solicitações'!$T:$T,"SIM") -> 24967290 | H16: =SUMIFS('Solicitações'!$O:$O,'Solicitações'!$L:$L,$A16,'Solicitações'!$T:$T,"SIM",'Solicitações'!E:E,"<>ATENDIDO",'Solicitações'!I:I,"<>",'Solicitações'!C:C,"SIM") -> 0 | J16: =G16-F16-H16-I16 -> 200000
A17: C-97 | B17: =SUMIFS('Solicitações'!$O:$O,'Solicitações'!$L:$L,$A17,'Solicitações'!$R:$R,B$2,'Solicitações'!$T:$T,"SIM") -> 0 | C17: =SUMIFS('Solicitações'!$O:$O,'Solicitações'!$L:$L,$A17,'Solicitações'!$R:$R,C$2,'Solicitações'!$T:$T,"SIM") -> 10300000 | D17: =SUMIFS('Solicitações'!$O:$O,'Solicitações'!$L:$L,$A17,'Solicitações'!$R:$R,D$2,'Solicitações'!$T:$T,"SIM") -> 6000000 | E17: =SUMIFS('Solicitações'!$O:$O,'Solicitações'!$L:$L,$A17,'Solicitações'!$R:$R,E$2,'Solicitações'!$T:$T,"SIM") -> 0 | F17: =SUMIFS('Solicitações'!$O:$O,'Solicitações'!$L:$L,$A17,'Solicitações'!$T:$T,"SIM",'Solicitações'!E:E,"ATENDIDO")-SUMIFS('Solicitações'!$O:$O,'Solicitações'!$L:$L,$A17,'Solicitações'!$T:$T,"SIM",'Solicitações'!E:E,"ATENDIDO",'Solicitações'!$R:$R,"RAP") -> 0 | G17: =SUMIFS('Solicitações'!$O:$O,'Solicitações'!$L:$L,$A17,'Solicitações'!$T:$T,"SIM",'Solicitações'!C:C,"SIM")-SUMIFS('Solicitações'!$O:$O,'Solicitações'!$L:$L,$A17,'Solicitações'!$R:$R,"RAP",'Solicitações'!$T:$T,"SIM") -> 0 | H17: =SUMIFS('Solicitações'!$O:$O,'Solicitações'!$L:$L,$A17,'Solicitações'!$T:$T,"SIM",'Solicitações'!E:E,"<>ATENDIDO",'Solicitações'!I:I,"<>",'Solicitações'!C:C,"SIM") -> 0 | J17: =G17-F17-H17-I17 -> 0
A18: C-98 | B18: =SUMIFS('Solicitações'!$O:$O,'Solicitações'!$L:$L,$A18,'Solicitações'!$R:$R,B$2,'Solicitações'!$T:$T,"SIM") -> 17430820 | C18: =SUMIFS('Solicitações'!$O:$O,'Solicitações'!$L:$L,$A18,'Solicitações'!$R:$R,C$2,'Solicitações'!$T:$T,"SIM") -> 0 | D18: =SUMIFS('Solicitações'!$O:$O,'Solicitações'!$L:$L,$A18,'Solicitações'!$R:$R,D$2,'Solicitações'!$T:$T,"SIM") -> 12789400 | E18: =SUMIFS('Solicitações'!$O:$O,'Solicitações'!$L:$L,$A18,'Solicitações'!$R:$R,E$2,'Solicitações'!$T:$T,"SIM") -> 0 | F18: =SUMIFS('Solicitações'!$O:$O,'Solicitações'!$L:$L,$A18,'Solicitações'!$T:$T,"SIM",'Solicitações'!E:E,"ATENDIDO")-SUMIFS('Solicitações'!$O:$O,'Solicitações'!$L:$L,$A18,'Solicitações'!$T:$T,"SIM",'Solicitações'!E:E,"ATENDIDO",'Solicitações'!$R:$R,"RAP") -> 12900000 | G18: =SUMIFS('Solicitações'!$O:$O,'Solicitações'!$L:$L,$A18,'Solicitações'!$T:$T,"SIM",'Solicitações'!C:C,"SIM")-SUMIFS('Solicitações'!$O:$O,'Solicitações'!$L:$L,$A18,'Solicitações'!$R:$R,"RAP",'Solicitações'!$T:$T,"SIM") -> 26220220 | H18: =SUMIFS('Solicitações'!$O:$O,'Solicitações'!$L:$L,$A18,'Solicitações'!$T:$T,"SIM",'Solicitações'!E:E,"<>ATENDIDO",'Solicitações'!I:I,"<>",'Solicitações'!C:C,"SIM") -> 0 | J18: =G18-F18-H18-I18 -> 13320220
A19: T-27 | B19: =SUMIFS('Solicitações'!$O:$O,'Solicitações'!$L:$L,$A19,'Solicitações'!$R:$R,B$2,'Solicitações'!$T:$T,"SIM") -> 20109910 | C19: =SUMIFS('Solicitações'!$O:$O,'Solicitações'!$L:$L,$A19,'Solicitações'!$R:$R,C$2,'Solicitações'!$T:$T,"SIM") -> 3000000 | D19: =SUMIFS('Solicitações'!$O:$O,'Solicitações'!$L:$L,$A19,'Solicitações'!$R:$R,D$2,'Solicitações'!$T:$T,"SIM") -> 50040000 | E19: =SUMIFS('Solicitações'!$O:$O,'Solicitações'!$L:$L,$A19,'Solicitações'!$R:$R,E$2,'Solicitações'!$T:$T,"SIM") -> 0 | F19: =SUMIFS('Solicitações'!$O:$O,'Solicitações'!$L:$L,$A19,'Solicitações'!$T:$T,"SIM",'Solicitações'!E:E,"ATENDIDO")-SUMIFS('Solicitações'!$O:$O,'Solicitações'!$L:$L,$A19,'Solicitações'!$T:$T,"SIM",'Solicitações'!E:E,"ATENDIDO",'Solicitações'!$R:$R,"RAP") -> 17317330 | G19: =SUMIFS('Solicitações'!$O:$O,'Solicitações'!$L:$L,$A19,'Solicitações'!$T:$T,"SIM",'Solicitações'!C:C,"SIM")-SUMIFS('Solicitações'!$O:$O,'Solicitações'!$L:$L,$A19,'Solicitações'!$R:$R,"RAP",'Solicitações'!$T:$T,"SIM") -> 20109910 | H19: =SUMIFS('Solicitações'!$O:$O,'Solicitações'!$L:$L,$A19,'Solicitações'!$T:$T,"SIM",'Solicitações'!E:E,"<>ATENDIDO",'Solicitações'!I:I,"<>",'Solicitações'!C:C,"SIM") -> 0 | J19: =G19-F19-H19-I19 -> 2792580.1
A20: IU-93M | B20: =SUMIFS('Solicitações'!$O:$O,'Solicitações'!$L:$L,$A20,'Solicitações'!$R:$R,B$2,'Solicitações'!$T:$T,"SIM") -> 3000000 | C20: =SUMIFS('Solicitações'!$O:$O,'Solicitações'!$L:$L,$A20,'Solicitações'!$R:$R,C$2,'Solicitações'!$T:$T,"SIM") -> 0 | D20: =SUMIFS('Solicitações'!$O:$O,'Solicitações'!$L:$L,$A20,'Solicitações'!$R:$R,D$2,'Solicitações'!$T:$T,"SIM") -> 9980376 | E20: =SUMIFS('Solicitações'!$O:$O,'Solicitações'!$L:$L,$A20,'Solicitações'!$R:$R,E$2,'Solicitações'!$T:$T,"SIM") -> 0 | F20: =SUMIFS('Solicitações'!$O:$O,'Solicitações'!$L:$L,$A20,'Solicitações'!$T:$T,"SIM",'Solicitações'!E:E,"ATENDIDO")-SUMIFS('Solicitações'!$O:$O,'Solicitações'!$L:$L,$A20,'Solicitações'!$T:$T,"SIM",'Solicitações'!E:E,"ATENDIDO",'Solicitações'!$R:$R,"RAP") -> 5500000 | G20: =SUMIFS('Solicitações'!$O:$O,'Solicitações'!$L:$L,$A20,'Solicitações'!$T:$T,"SIM",'Solicitações'!C:C,"SIM")-SUMIFS('Solicitações'!$O:$O,'Solicitações'!$L:$L,$A20,'Solicitações'!$R:$R,"RAP",'Solicitações'!$T:$T,"SIM") -> 5500000 | H20: =SUMIFS('Solicitações'!$O:$O,'Solicitações'!$L:$L,$A20,'Solicitações'!$T:$T,"SIM",'Solicitações'!E:E,"<>ATENDIDO",'Solicitações'!I:I,"<>",'Solicitações'!C:C,"SIM") -> 0 | J20: =G20-F20-H20-I20 -> 0

Sheet Análise do Corte
A1: Célula
B2: Valor a solicitar | C2: Bloqueio Sugerido
A3: A-29 | B3: 10562184 | C3: 0
A4: C-95M | B4: 17383149 | C4: 16411382
A5: C-97 | B5: 3242659.6 | C5: 4175833.9
A6: C-98 | B6: 5065668.5 | C6: 8958040
A7: T-27 | B7: 7942753.6 | C7: 0
A8: T-25 | B8: 10430876 | C8: 9608993
A9: G-19 | B9: 275000 | C9: 90000
A10: IU-93M | B10: 16048152 | C10: 0
A11: APOIO | B11: 36265388 | C11: 9266024.4
A13: Motores
B14: Valor a solicitar | C14: Bloqueio Sugerido
A15: A-29 | B15: 42579946 | C15: 0
A16: C-95M | B16: 5434638.2 | C16: 0
A17: C-97 | B17: 10300000 | C17: 2800000
A18: C-98 | B18: 14428000 | C18: 3000000
A19: T-27 | B19: 17640196 | C19: 0
A20: IU-93M | B20: 0 | C20: 0
A23: Valor a Solicitar | B23: Tarefa | C23: Valor a solicitar | D23: Bloqueio Sugerido não solicitado | E23: Bloqueio de crédito solicitado | F23: Bloqueio total | G23: Saldo | H23: Saldo Total | K23: Diferença disponibilizada no MTA | L23: Linhas Correspondentes
A24: A-29 | B24: 040 - módulo extra | C24: 412184.28 | F24: =D24+E24 -> 0 | G24: =C24-D24-E24 -> 412184.28 | H24: =SUM(G24:G26) -> 10562184
B25: 102 - módulo extra | C25: 1000000 | F25: =D25+E25 -> 0 | G25: =C25-D25-E25 -> 1000000
B26: req cabw (+transparência) | C26: 9150000 | F26: =D26+E26 -> 0 | G26: =C26-D26-E26 -> 9150000 | I26: disponibilizar 3MM (deixar 3 shipsets - +-6MM) | K26: 4063228 | L26: 12900, 12920 e 12880 parcial
A27: C-95 | B27: contrato reparáveis | C27: 4000000 | D27: 4000000 | F27: =D27+E27 -> 4000000 | G27: =C27-D27-E27 -> 0 | H27: =SUM(G27:G29) -> 971766.83 | I27: deixar 1450000 | K27: -2000000 | L27: 12380 e 14420
B28: req cabw | C28: 13383149 | D28: 10159711 | F28: =D28+E28 -> 10159711 | G28: =C28-D28-E28 -> 3223437.7 | I28: deixar XXX (dobro das REQ inseridas) | K28: -3573329.1 | L28: 11400
B29: 028 - módulo extra | E29: 2251670.9 | F29: =D29+E29 -> 2251670.9 | G29: =C29-D29-E29 -> -2251670.9 | I29: deixar FULL 2251000 | K29: -2251670.9 | L29: 13460, 16260 e 17940
A30: C-97 | B30: 096 - módulo extra | C30: =1500000 -> 1500000 | D30: 1500000 | E30: 2675833.9 | F30: =D30+E30 -> 4175833.9 | G30: =C30-D30-E30 -> -2675833.9 | H30: =SUM(G30:G32) -> -933174.3 | I30: deixar 2675000 | K30: -2675833.9 | L30: 11660
B31: req cabw | C31: 930703.56 | F31: =D31+E31 -> 0 | G31: =C31-D31-E31 -> 930703.56 | K31: 501640.62 | L31: 10260
B32: req cabw mod | C32: 811956 | F32: =D32+E32 -> 0 | G32: =C32-D32-E32 -> 811956
A33: C-98 | B33: 005 - módulo extra | C33: 672628.5 | F33: =D33+E33 -> 0 | G33: =C33-D33-E33 -> 672628.5 | H33: =SUM(G33:G34) -> 1107628.5
B34: req cabw | C34: 4393040 | D34: 3958040 | F34: =D34+E34 -> 3958040 | G34: =C34-D34-E34 -> 435000 | I34: DEIXAR TUDO (3,9MM) - FAB 2728 PS | K34: -3958040 | L34: 11820, 11840, 11860 e 17200
A35: G-19 | B35: req cabw | C35: 275000 | D35: 90000 | F35: =D35+E35 -> 90000 | G35: =C35-D35-E35 -> 185000 | H35: =G35 -> 185000
A36: IU-93 | B36: montagem 6053 | C36: 12960375 | F36: =D36+E36 -> 0 | G36: =C36-D36-E36 -> 12960375 | H36: =SUM(G36:G38) -> 16048152
B37: 024 - módulo extra | C37: 1671588.9 | F37: =D37+E37 -> 0 | G37: =C37-D37-E37 -> 1671588.9
B38: rec cabw | C38: 1416188 | F38: =D38+E38 -> 0 | G38: =C38-D38-E38 -> 1416188 | J38: *
A39: T-25 | B39: contrato reparáveis | C39: 1860000 | F39: =D39+E39 -> 0 | G39: =C39-D39-E39 -> 1860000 | H39: =SUM(G39:G40) -> 7930876.2 | K39: 930000 | L39: 12320 14380 e 16160
B40: rec cabw | C40: 8570876.2 | D40: 2500000 | F40: =D40+E40 -> 2500000 | G40: =C40-D40-E40 -> 6070876.2 | K40: 2500000 | L40: 16880
A41: T-27 | B41: contrato reparáveis | C41: 930000 | F41: =D41+E41 -> 0 | G41: =C41-D41-E41 -> 930000 | H41: =SUM(G41:G43) -> 7942753.6
B42: req cabw | C42: 1612753.6 | F42: =D42+E42 -> 0 | G42: =C42-D42-E42 -> 1612753.6
B43: req cabw mod | C43: 5400000 | F43: =D43+E43 -> 0 | G43: =C43-D43-E43 -> 5400000
A44: APOIO AO SOLO | B44: baret | C44: 22099470 | F44: =D44+E44 -> 0 | G44: =C44-D44-E44 -> 22099470 | H44: =SUM(G44:G45) -> 19926558 | I44: devolve 13 MM (compra apenas 1 BARET)
B45: sob demanda | C45: =134088.2 -> 134088.2 | E45: 2307000 | F45: =D45+E45 -> 2307000 | G45: =C45-D45-E45 -> -2172911.8 | I45: deixar tudo 2,3 MM | K45: -2307000 | L45: 12120, 12200, 12280
A46: AD | B46: req cabw | C46: 82000 | F46: =D46+E46 -> 0 | G46: =C46-D46-E46 -> 82000 | H46: =G46 -> 82000 | K46: 82000 | L46: 12040
A47: GL | B47: serv eng | C47: =2586344.13-850350.75 -> 1735993.4 | D47: 1572994.8 | F47: =D47+E47 -> 1572994.8 | G47: =C47-D47-E47 -> 162998.61 | H47: =SUM(G47:G48) -> 919762.79 | I47: Deixa 800.000 | K47: -1572994.8 | L47: 14820,17160, 18000, 23500
B48: internalização | C48: 756764.18 | F48: =D48+E48 -> 0 | G48: =C48-D48-E48 -> 756764.18
A49: PN | B49: sob demanda | C49: 728000 | D49: 538000 | F49: =D49+E49 -> 538000 | G49: =C49-D49-E49 -> 190000 | H49: =G49 -> 190000 | I49: deixar tudo 538k | K49: -538000 | L49: 10740
A50: SSS | B50: capacete | C50: 2367474.5 | F50: =D50+E50 -> 0 | G50: =C50-D50-E50 -> 2367474.5 | H50: =SUM(G50:G51) -> 7398166.2
B51: sob demanda | C51: 9878721.3 | D51: 4848029.6 | F51: =D51+E51 -> 4848029.6 | G51: =C51-D51-E51 -> 5030691.7
A54: Bloqueio de parcela fixa | B54: Valor a solicitar | C54: Bloqueio Sugerido não solicitado | D54: Saldo
A55: mod t-25 | B55: 8217260.2 | C55: 7108993 | D55: =B55-C55 -> 1108267.2
A56: mod c-98 | B56: 9500000 | C56: 5000000 | D56: =B56-C56 -> 4500000
A57: Bloqueio de motor
A58: c-98 | B58: 22028000 | C58: 3000000 | D58: =B58-C58 -> 19028000 | K58: -3000000 | L58: 13200, 16700, 25180
A59: C-97 | B59: 10300000 | C59: 2800000 | D59: =B59-C59 -> 7500000 | K59: =4700000+2800000 -> 7500000 | L59: 11580, 11600
A60: t-27 | K60: 4500000 | L60: 10580, 13860, 18200, 63480, 63500, 63520
A61: a-29 | K61: 1800000 | L61: 24560
B66: Impacto antes do corte (pacote B) | C66: Bloqueio sugerido pela DIRMAB | D66: Ajustes propostos pelo PAMALS
A67: A-29 | B67: 9 RG em C – necessárias paca chegar e TDA de 55 2 HSI em B NA 1 reparo em B NA Sem motor de giro (2 reparos em B) TDA – 55-9-2-1=43 IMPACTO: Espera-se 43 ANV na TDA no final de 2026 | C67: TDA=43 IMPACTO: Espera-se 43 ANV na TDA no final de 2026 | D67: impossibilidade de realização de 1 reparo de motores - que pode ser necessário ou não por ser oriundo de perda não programada. aquisição parcial dos shipset de transparência para trocas TDA = 43-1 = 42ANV IMPACTO: Espera-se 42 ANV na TDA no final de 2026
A68: C/P-95 | B68: 4 FEP em C – necessárias para chegar na TDA de 23 (sem giro) TDA motores – 46-4 = 42 = 21ANV IMPACTO: Espera-se 21 ANV na TDA no final de 2026 | C68: Impossibilidade de arcar com compromissos assumidos em materiais já induzidos no contrato 028/AEL Impossibilidade de revisão de componentes na assinatura do novo contrato de reparáveis, impactanto diretamente na disponibilidade da frota Impacto direto na manutenção do projeto durante o primeiro semestre de 2027, principalmente por atraso no recebimento de materiais oriundos de requisições CABW. IMPACTO: Espera-se 21 ANV na TDA no final de 2026 e disponibilidade média com redução em torno de 2 ou 3 aeronaves (atualmente o PAMALS mantém 55% de disponibilidade no projeto em contraposição à disponibilidade histórica de 40%) | D68: Impossbilidade de revisão de componentes na assinatura do novo contrto de reparáveis, impactanto diretamente da disponibilidade da frota Impactio direto na manutenção do projeto durante o primeiro semestre de 2027, principalmente por atraso em empenho e recebimento de materiais oriundos de requisições CABW IMPACTO: Espera-se 21 ANV na TDA no final de 2026 e disponibilidade média com redução em torno de 1 ou 2 aeronaves (atualmente o PAMALS mantém 55% de disponibilidade no projeto em contraposição à disponibilidade histórica de 40%)
A69: C-97 | B69: Impossibilidade da compra de reparáveis para giro na assinatura do novo contrato CLS, impactando da disponibilidade Mantem TDA=13, podendo impactar na disponibilidade do início de 2027 IMPACTO: Espera-se 12 ANV na TDA no final de 2026 e redução na disponibilidade por falta de item de giro | C69: Não aquisição de consumíveis e reposição de giro de reparáveis, além de material para manutenção programada nível base enquanto não se assina o novo CLS IMPACTO: Espera-se 12 ANV na TDA no final de 2026 e redução em torno de 3 anv na disponibilidade por falta de item de giro | D69: Não aquisição de consumíveis e reposição de giro de reparáveis para manutenção da frota enquanto não se assina o novo CLS Falta de motor sobressalente para substituição em caso de perda por pane (decisão do PAMALS tendo em vista que o projeto está sem contrato para manutenção de motor e que, durante a modernização realizada no PAMALS teremos sempre 1 avião parado com dois motores aplicados podendo servir de spare) IMPACTO: Espera-se 12 ANV na TDA no final de 2026 e redução em torno de 1 anv na disponibilidade por falta de item de giro
A70: C-98 | B70: 1 Exchange em C 1 reparo em B TDA 23-2 = 21 IMPACTO: Espera-se 21 ANV na TDA no final de 2026 | C70: Impossibilidade de reinclusão do FAB 2728 na TDA Impossibilidade de realização de modernização abrangida pelo contrato quando o mesmo for assinado Impossibilidade de realização de 3 reparos de motor TDA=21-3=18ANV IMPACTO: Espera-se 18 ANV na TDA no final de 2026 | D70: Impossibilidade de realização de modernização abrangida pelo contrato quando o mesmo for assinado TDA=21ANV IMPACTO: Espera-se 21 ANV na TDA no final de 2026
A71: T-27 | B71: 1 RG em B e 1 RG em C – necessários para chegar na TDA de 24 TDA=24-2=22 IMPACTO: Espera-se 22 ANV na TDA no final de 2026 | C71: Após atualização de cálculo de consumo de motores, verificou-se a necessidade de realização de 3 HSI a menos (de manutenção estendida por coincidir com TBO). IMPACTO: Espera-se 22 ANV na TDA no final de 2026 | D71: Após atualização de cálculo de consumo de motores, verificou-se a necessidade de realização de 3 HSI a menos (de manutenção estendida por coincidir com TBO). Considerando que o novo contrato de fornecimento de materiais para HSI e Reparo ainda não foi assinado e que o contrato atual tem saldo empenhado, optou-se por bloquear 6 linhas tendo em vista a capacidade produtiva do PAMASP IMPACTO: Espera-se 22 ANV na TDA no final de 2026
A72: T-25 | C72: Impossibilidade de adquirir no tempo previsto os materiais para continuidade da modernização do T-25 Impacto negativo na disponibilidade de consumíveis para realização das manutenções da aeronave no primeiro semestre de 2027 IMPACTO: Espera-se 24 ANV na TDA no final de 2026 e redução na disponibilidade por falta de item de giro e de consumíveis caso o projeto não receba dinheiro para empenho de requisições CABW e para indução de reparo nos contratos de reparáveis no final de 2027/início de 2028. | D72: Impossibilidade de adquirir no tempo previsto os materiais para continuidade da modernização do T-25 Impacto negativo na disponibilidade de consumíveis para realização das manutenções da aeronave no primeiro semestre de 2027 IMPACTO: Espera-se 24 ANV na TDA no final de 2026 e redução na disponibilidade por falta de item de giro e de consumíveis caso o projeto não receba dinheiro para empenho de requisições CABW e para indução de reparo nos contratos de reparáveis em meados de 2027.
A73: G-19 | C73: IMPACTO: redução na disponibilidade por falta de item de giro e de consumíveis caso o projeto não receba dinheiro para empenho de requisições CABW em 2027. | D73: IMPACTO: redução na disponibilidade por falta de item de giro e de consumíveis caso o projeto não receba dinheiro para empenho de requisições CABW em 2027.
A74: IU-93
A75: APOIO | C75: IMPACTOS: Impacto negativo da disponibilidade de consumíveis para realização das manutenções de equipamentos de apoio ao solo no primeiro semestre de 2027 Impossibilidade de compra de pneu de aviação para sustentar as frotas da FAB Impossibilidade de realizar serviços de engenharia com fito na melhora de instalações (Plano Marshall) Impossibilidade de recompletamento de equipamentos de SSS por tempo limite de vida e de atendimento a 100% da lotação | D75: IMPACTOS: Impossibilidade de aquisição de consumíveis para manutenção do projeto AD Impossibilidade de recompletamento de equipamentos de SSS por tempo limite de vida e de atendimento a 100% da lotação

Sheet CFF 2025
B1: 1 | C1: 2 | D1: 3 | E1: 4 | F1: 5 | G1: 6 | H1: 7 | I1: 8 | J1: 9 | K1: 10 | L1: 11 | M1: 12 | N1: 13 | O1: 14 | P1: TOTAL
A2: A-29 | B2: =SUMIFS('Minuta MTA 2025 GR3'!$AF:$AF,'Minuta MTA 2025 GR3'!$AH:$AH,B$1,'Minuta MTA 2025 GR3'!$I:$I,$A2,'Minuta MTA 2025 GR3'!$T:$T,"A")+SUMIFS('Minuta MTA 2025 GR3'!$AF:$AF,'Minuta MTA 2025 GR3'!$AH:$AH,B$1,'Minuta MTA 2025 GR3'!$I:$I,$A2,'Minuta MTA 2025 GR3'!$T:$T,"B") -> #N/A | C2: =SUMIFS('Minuta MTA 2025 GR3'!$AF:$AF,'Minuta MTA 2025 GR3'!$AH:$AH,C$1,'Minuta MTA 2025 GR3'!$I:$I,$A2,'Minuta MTA 2025 GR3'!$T:$T,"A")+SUMIFS('Minuta MTA 2025 GR3'!$AF:$AF,'Minuta MTA 2025 GR3'!$AH:$AH,C$1,'Minuta MTA 2025 GR3'!$I:$I,$A2,'Minuta MTA 2025 GR3'!$T:$T,"B") -> #N/A | D2: =SUMIFS('Minuta MTA 2025 GR3'!$AF:$AF,'Minuta MTA 2025 GR3'!$AH:$AH,D$1,'Minuta MTA 2025 GR3'!$I:$I,$A2,'Minuta MTA 2025 GR3'!$T:$T,"A")+SUMIFS('Minuta MTA 2025 GR3'!$AF:$AF,'Minuta MTA 2025 GR3'!$AH:$AH,D$1,'Minuta MTA 2025 GR3'!$I:$I,$A2,'Minuta MTA 2025 GR3'!$T:$T,"B") -> #N/A | E2: =SUMIFS('Minuta MTA 2025 GR3'!$AF:$AF,'Minuta MTA 2025 GR3'!$AH:$AH,E$1,'Minuta MTA 2025 GR3'!$I:$I,$A2,'Minuta MTA 2025 GR3'!$T:$T,"A")+SUMIFS('Minuta MTA 2025 GR3'!$AF:$AF,'Minuta MTA 2025 GR3'!$AH:$AH,E$1,'Minuta MTA 2025 GR3'!$I:$I,$A2,'Minuta MTA 2025 GR3'!$T:$T,"B") -> #N/A | F2: =SUMIFS('Minuta MTA 2025 GR3'!$AF:$AF,'Minuta MTA 2025 GR3'!$AH:$AH,F$1,'Minuta MTA 2025 GR3'!$I:$I,$A2,'Minuta MTA 2025 GR3'!$T:$T,"A")+SUMIFS('Minuta MTA 2025 GR3'!$AF:$AF,'Minuta MTA 2025 GR3'!$AH:$AH,F$1,'Minuta MTA 2025 GR3'!$I:$I,$A2,'Minuta MTA 2025 GR3'!$T:$T,"B") -> #N/A | G2: =SUMIFS('Minuta MTA 2025 GR3'!$AF:$AF,'Minuta MTA 2025 GR3'!$AH:$AH,G$1,'Minuta MTA 2025 GR3'!$I:$I,$A2,'Minuta MTA 2025 GR3'!$T:$T,"A")+SUMIFS('Minuta MTA 2025 GR3'!$AF:$AF,'Minuta MTA 2025 GR3'!$AH:$AH,G$1,'Minuta MTA 2025 GR3'!$I:$I,$A2,'Minuta MTA 2025 GR3'!$T:$T,"B") -> #N/A | H2: =SUMIFS('Minuta MTA 2025 GR3'!$AF:$AF,'Minuta MTA 2025 GR3'!$AH:$AH,H$1,'Minuta MTA 2025 GR3'!$I:$I,$A2,'Minuta MTA 2025 GR3'!$T:$T,"A")+SUMIFS('Minuta MTA 2025 GR3'!$AF:$AF,'Minuta MTA 2025 GR3'!$AH:$AH,H$1,'Minuta MTA 2025 GR3'!$I:$I,$A2,'Minuta MTA 2025 GR3'!$T:$T,"B") -> #N/A | I2: =SUMIFS('Minuta MTA 2025 GR3'!$AF:$AF,'Minuta MTA 2025 GR3'!$AH:$AH,I$1,'Minuta MTA 2025 GR3'!$I:$I,$A2,'Minuta MTA 2025 GR3'!$T:$T,"A")+SUMIFS('Minuta MTA 2025 GR3'!$AF:$AF,'Minuta MTA 2025 GR3'!$AH:$AH,I$1,'Minuta MTA 2025 GR3'!$I:$I,$A2,'Minuta MTA 2025 GR3'!$T:$T,"B") -> #N/A | ... O2: =SUMIFS('Minuta MTA 2025 GR3'!$AF:$AF,'Minuta MTA 2025 GR3'!$AH:$AH,O$1,'Minuta MTA 2025 GR3'!$I:$I,$A2,'Minuta MTA 2025 GR3'!$T:$T,"A")+SUMIFS('Minuta MTA 2025 GR3'!$AF:$AF,'Minuta MTA 2025 GR3'!$AH:$AH,O$1,'Minuta MTA 2025 GR3'!$I:$I,$A2,'Minuta MTA 2025 GR3'!$T:$T,"B") -> #N/A | P2: =SUM(B2:O2) -> #N/A
A3: C-95 | B3: =SUMIFS('Minuta MTA 2025 GR3'!$AF:$AF,'Minuta MTA 2025 GR3'!$AH:$AH,B$1,'Minuta MTA 2025 GR3'!$I:$I,$A3,'Minuta MTA 2025 GR3'!$T:$T,"A")+SUMIFS('Minuta MTA 2025 GR3'!$AF:$AF,'Minuta MTA 2025 GR3'!$AH:$AH,B$1,'Minuta MTA 2025 GR3'!$I:$I,$A3,'Minuta MTA 2025 GR3'!$T:$T,"B") -> #N/A | C3: =SUMIFS('Minuta MTA 2025 GR3'!$AF:$AF,'Minuta MTA 2025 GR3'!$AH:$AH,C$1,'Minuta MTA 2025 GR3'!$I:$I,$A3,'Minuta MTA 2025 GR3'!$T:$T,"A")+SUMIFS('Minuta MTA 2025 GR3'!$AF:$AF,'Minuta MTA 2025 GR3'!$AH:$AH,C$1,'Minuta MTA 2025 GR3'!$I:$I,$A3,'Minuta MTA 2025 GR3'!$T:$T,"B") -> #N/A | D3: =SUMIFS('Minuta MTA 2025 GR3'!$AF:$AF,'Minuta MTA 2025 GR3'!$AH:$AH,D$1,'Minuta MTA 2025 GR3'!$I:$I,$A3,'Minuta MTA 2025 GR3'!$T:$T,"A")+SUMIFS('Minuta MTA 2025 GR3'!$AF:$AF,'Minuta MTA 2025 GR3'!$AH:$AH,D$1,'Minuta MTA 2025 GR3'!$I:$I,$A3,'Minuta MTA 2025 GR3'!$T:$T,"B") -> #N/A | E3: =SUMIFS('Minuta MTA 2025 GR3'!$AF:$AF,'Minuta MTA 2025 GR3'!$AH:$AH,E$1,'Minuta MTA 2025 GR3'!$I:$I,$A3,'Minuta MTA 2025 GR3'!$T:$T,"A")+SUMIFS('Minuta MTA 2025 GR3'!$AF:$AF,'Minuta MTA 2025 GR3'!$AH:$AH,E$1,'Minuta MTA 2025 GR3'!$I:$I,$A3,'Minuta MTA 2025 GR3'!$T:$T,"B") -> #N/A | F3: =SUMIFS('Minuta MTA 2025 GR3'!$AF:$AF,'Minuta MTA 2025 GR3'!$AH:$AH,F$1,'Minuta MTA 2025 GR3'!$I:$I,$A3,'Minuta MTA 2025 GR3'!$T:$T,"A")+SUMIFS('Minuta MTA 2025 GR3'!$AF:$AF,'Minuta MTA 2025 GR3'!$AH:$AH,F$1,'Minuta MTA 2025 GR3'!$I:$I,$A3,'Minuta MTA 2025 GR3'!$T:$T,"B") -> #N/A | G3: =SUMIFS('Minuta MTA 2025 GR3'!$AF:$AF,'Minuta MTA 2025 GR3'!$AH:$AH,G$1,'Minuta MTA 2025 GR3'!$I:$I,$A3,'Minuta MTA 2025 GR3'!$T:$T,"A")+SUMIFS('Minuta MTA 2025 GR3'!$AF:$AF,'Minuta MTA 2025 GR3'!$AH:$AH,G$1,'Minuta MTA 2025 GR3'!$I:$I,$A3,'Minuta MTA 2025 GR3'!$T:$T,"B") -> #N/A | H3: =SUMIFS('Minuta MTA 2025 GR3'!$AF:$AF,'Minuta MTA 2025 GR3'!$AH:$AH,H$1,'Minuta MTA 2025 GR3'!$I:$I,$A3,'Minuta MTA 2025 GR3'!$T:$T,"A")+SUMIFS('Minuta MTA 2025 GR3'!$AF:$AF,'Minuta MTA 2025 GR3'!$AH:$AH,H$1,'Minuta MTA 2025 GR3'!$I:$I,$A3,'Minuta MTA 2025 GR3'!$T:$T,"B") -> #N/A | I3: =SUMIFS('Minuta MTA 2025 GR3'!$AF:$AF,'Minuta MTA 2025 GR3'!$AH:$AH,I$1,'Minuta MTA 2025 GR3'!$I:$I,$A3,'Minuta MTA 2025 GR3'!$T:$T,"A")+SUMIFS('Minuta MTA 2025 GR3'!$AF:$AF,'Minuta MTA 2025 GR3'!$AH:$AH,I$1,'Minuta MTA 2025 GR3'!$I:$I,$A3,'Minuta MTA 2025 GR3'!$T:$T,"B") -> #N/A | ... O3: =SUMIFS('Minuta MTA 2025 GR3'!$AF:$AF,'Minuta MTA 2025 GR3'!$AH:$AH,O$1,'Minuta MTA 2025 GR3'!$I:$I,$A3,'Minuta MTA 2025 GR3'!$T:$T,"A")+SUMIFS('Minuta MTA 2025 GR3'!$AF:$AF,'Minuta MTA 2025 GR3'!$AH:$AH,O$1,'Minuta MTA 2025 GR3'!$I:$I,$A3,'Minuta MTA 2025 GR3'!$T:$T,"B") -> #N/A | P3: =SUM(B3:O3) -> #N/A
A4: C-97 | B4: =SUMIFS('Minuta MTA 2025 GR3'!$AF:$AF,'Minuta MTA 2025 GR3'!$AH:$AH,B$1,'Minuta MTA 2025 GR3'!$I:$I,$A4,'Minuta MTA 2025 GR3'!$T:$T,"A")+SUMIFS('Minuta MTA 2025 GR3'!$AF:$AF,'Minuta MTA 2025 GR3'!$AH:$AH,B$1,'Minuta MTA 2025 GR3'!$I:$I,$A4,'Minuta MTA 2025 GR3'!$T:$T,"B") -> #N/A | C4: =SUMIFS('Minuta MTA 2025 GR3'!$AF:$AF,'Minuta MTA 2025 GR3'!$AH:$AH,C$1,'Minuta MTA 2025 GR3'!$I:$I,$A4,'Minuta MTA 2025 GR3'!$T:$T,"A")+SUMIFS('Minuta MTA 2025 GR3'!$AF:$AF,'Minuta MTA 2025 GR3'!$AH:$AH,C$1,'Minuta MTA 2025 GR3'!$I:$I,$A4,'Minuta MTA 2025 GR3'!$T:$T,"B") -> #N/A | D4: =SUMIFS('Minuta MTA 2025 GR3'!$AF:$AF,'Minuta MTA 2025 GR3'!$AH:$AH,D$1,'Minuta MTA 2025 GR3'!$I:$I,$A4,'Minuta MTA 2025 GR3'!$T:$T,"A")+SUMIFS('Minuta MTA 2025 GR3'!$AF:$AF,'Minuta MTA 2025 GR3'!$AH:$AH,D$1,'Minuta MTA 2025 GR3'!$I:$I,$A4,'Minuta MTA 2025 GR3'!$T:$T,"B") -> #N/A | E4: =SUMIFS('Minuta MTA 2025 GR3'!$AF:$AF,'Minuta MTA 2025 GR3'!$AH:$AH,E$1,'Minuta MTA 2025 GR3'!$I:$I,$A4,'Minuta MTA 2025 GR3'!$T:$T,"A")+SUMIFS('Minuta MTA 2025 GR3'!$AF:$AF,'Minuta MTA 2025 GR3'!$AH:$AH,E$1,'Minuta MTA 2025 GR3'!$I:$I,$A4,'Minuta MTA 2025 GR3'!$T:$T,"B") -> #N/A | F4: =SUMIFS('Minuta MTA 2025 GR3'!$AF:$AF,'Minuta MTA 2025 GR3'!$AH:$AH,F$1,'Minuta MTA 2025 GR3'!$I:$I,$A4,'Minuta MTA 2025 GR3'!$T:$T,"A")+SUMIFS('Minuta MTA 2025 GR3'!$AF:$AF,'Minuta MTA 2025 GR3'!$AH:$AH,F$1,'Minuta MTA 2025 GR3'!$I:$I,$A4,'Minuta MTA 2025 GR3'!$T:$T,"B") -> #N/A | G4: =SUMIFS('Minuta MTA 2025 GR3'!$AF:$AF,'Minuta MTA 2025 GR3'!$AH:$AH,G$1,'Minuta MTA 2025 GR3'!$I:$I,$A4,'Minuta MTA 2025 GR3'!$T:$T,"A")+SUMIFS('Minuta MTA 2025 GR3'!$AF:$AF,'Minuta MTA 2025 GR3'!$AH:$AH,G$1,'Minuta MTA 2025 GR3'!$I:$I,$A4,'Minuta MTA 2025 GR3'!$T:$T,"B") -> #N/A | H4: =SUMIFS('Minuta MTA 2025 GR3'!$AF:$AF,'Minuta MTA 2025 GR3'!$AH:$AH,H$1,'Minuta MTA 2025 GR3'!$I:$I,$A4,'Minuta MTA 2025 GR3'!$T:$T,"A")+SUMIFS('Minuta MTA 2025 GR3'!$AF:$AF,'Minuta MTA 2025 GR3'!$AH:$AH,H$1,'Minuta MTA 2025 GR3'!$I:$I,$A4,'Minuta MTA 2025 GR3'!$T:$T,"B") -> #N/A | I4: =SUMIFS('Minuta MTA 2025 GR3'!$AF:$AF,'Minuta MTA 2025 GR3'!$AH:$AH,I$1,'Minuta MTA 2025 GR3'!$I:$I,$A4,'Minuta MTA 2025 GR3'!$T:$T,"A")+SUMIFS('Minuta MTA 2025 GR3'!$AF:$AF,'Minuta MTA 2025 GR3'!$AH:$AH,I$1,'Minuta MTA 2025 GR3'!$I:$I,$A4,'Minuta MTA 2025 GR3'!$T:$T,"B") -> #N/A | ... O4: =SUMIFS('Minuta MTA 2025 GR3'!$AF:$AF,'Minuta MTA 2025 GR3'!$AH:$AH,O$1,'Minuta MTA 2025 GR3'!$I:$I,$A4,'Minuta MTA 2025 GR3'!$T:$T,"A")+SUMIFS('Minuta MTA 2025 GR3'!$AF:$AF,'Minuta MTA 2025 GR3'!$AH:$AH,O$1,'Minuta MTA 2025 GR3'!$I:$I,$A4,'Minuta MTA 2025 GR3'!$T:$T,"B") -> #N/A | P4: =SUM(B4:O4) -> #N/A
A5: C-98 | B5: =SUMIFS('Minuta MTA 2025 GR3'!$AF:$AF,'Minuta MTA 2025 GR3'!$AH:$AH,B$1,'Minuta MTA 2025 GR3'!$I:$I,$A5,'Minuta MTA 2025 GR3'!$T:$T,"A")+SUMIFS('Minuta MTA 2025 GR3'!$AF:$AF,'Minuta MTA 2025 GR3'!$AH:$AH,B$1,'Minuta MTA 2025 GR3'!$I:$I,$A5,'Minuta MTA 2025 GR3'!$T:$T,"B") -> #N/A | C5: =SUMIFS('Minuta MTA 2025 GR3'!$AF:$AF,'Minuta MTA 2025 GR3'!$AH:$AH,C$1,'Minuta MTA 2025 GR3'!$I:$I,$A5,'Minuta MTA 2025 GR3'!$T:$T,"A")+SUMIFS('Minuta MTA 2025 GR3'!$AF:$AF,'Minuta MTA 2025 GR3'!$AH:$AH,C$1,'Minuta MTA 2025 GR3'!$I:$I,$A5,'Minuta MTA 2025 GR3'!$T:$T,"B") -> #N/A | D5: =SUMIFS('Minuta MTA 2025 GR3'!$AF:$AF,'Minuta MTA 2025 GR3'!$AH:$AH,D$1,'Minuta MTA 2025 GR3'!$I:$I,$A5,'Minuta MTA 2025 GR3'!$T:$T,"A")+SUMIFS('Minuta MTA 2025 GR3'!$AF:$AF,'Minuta MTA 2025 GR3'!$AH:$AH,D$1,'Minuta MTA 2025 GR3'!$I:$I,$A5,'Minuta MTA 2025 GR3'!$T:$T,"B") -> #N/A | E5: =SUMIFS('Minuta MTA 2025 GR3'!$AF:$AF,'Minuta MTA 2025 GR3'!$AH:$AH,E$1,'Minuta MTA 2025 GR3'!$I:$I,$A5,'Minuta MTA 2025 GR3'!$T:$T,"A")+SUMIFS('Minuta MTA 2025 GR3'!$AF:$AF,'Minuta MTA 2025 GR3'!$AH:$AH,E$1,'Minuta MTA 2025 GR3'!$I:$I,$A5,'Minuta MTA 2025 GR3'!$T:$T,"B") -> #N/A | F5: =SUMIFS('Minuta MTA 2025 GR3'!$AF:$AF,'Minuta MTA 2025 GR3'!$AH:$AH,F$1,'Minuta MTA 2025 GR3'!$I:$I,$A5,'Minuta MTA 2025 GR3'!$T:$T,"A")+SUMIFS('Minuta MTA 2025 GR3'!$AF:$AF,'Minuta MTA 2025 GR3'!$AH:$AH,F$1,'Minuta MTA 2025 GR3'!$I:$I,$A5,'Minuta MTA 2025 GR3'!$T:$T,"B") -> #N/A | G5: =SUMIFS('Minuta MTA 2025 GR3'!$AF:$AF,'Minuta MTA 2025 GR3'!$AH:$AH,G$1,'Minuta MTA 2025 GR3'!$I:$I,$A5,'Minuta MTA 2025 GR3'!$T:$T,"A")+SUMIFS('Minuta MTA 2025 GR3'!$AF:$AF,'Minuta MTA 2025 GR3'!$AH:$AH,G$1,'Minuta MTA 2025 GR3'!$I:$I,$A5,'Minuta MTA 2025 GR3'!$T:$T,"B") -> #N/A | H5: =SUMIFS('Minuta MTA 2025 GR3'!$AF:$AF,'Minuta MTA 2025 GR3'!$AH:$AH,H$1,'Minuta MTA 2025 GR3'!$I:$I,$A5,'Minuta MTA 2025 GR3'!$T:$T,"A")+SUMIFS('Minuta MTA 2025 GR3'!$AF:$AF,'Minuta MTA 2025 GR3'!$AH:$AH,H$1,'Minuta MTA 2025 GR3'!$I:$I,$A5,'Minuta MTA 2025 GR3'!$T:$T,"B") -> #N/A | I5: =SUMIFS('Minuta MTA 2025 GR3'!$AF:$AF,'Minuta MTA 2025 GR3'!$AH:$AH,I$1,'Minuta MTA 2025 GR3'!$I:$I,$A5,'Minuta MTA 2025 GR3'!$T:$T,"A")+SUMIFS('Minuta MTA 2025 GR3'!$AF:$AF,'Minuta MTA 2025 GR3'!$AH:$AH,I$1,'Minuta MTA 2025 GR3'!$I:$I,$A5,'Minuta MTA 2025 GR3'!$T:$T,"B") -> #N/A | ... O5: =SUMIFS('Minuta MTA 2025 GR3'!$AF:$AF,'Minuta MTA 2025 GR3'!$AH:$AH,O$1,'Minuta MTA 2025 GR3'!$I:$I,$A5,'Minuta MTA 2025 GR3'!$T:$T,"A")+SUMIFS('Minuta MTA 2025 GR3'!$AF:$AF,'Minuta MTA 2025 GR3'!$AH:$AH,O$1,'Minuta MTA 2025 GR3'!$I:$I,$A5,'Minuta MTA 2025 GR3'!$T:$T,"B") -> #N/A | P5: =SUM(B5:O5) -> #N/A
A6: T-27 | B6: =SUMIFS('Minuta MTA 2025 GR3'!$AF:$AF,'Minuta MTA 2025 GR3'!$AH:$AH,B$1,'Minuta MTA 2025 GR3'!$I:$I,$A6,'Minuta MTA 2025 GR3'!$T:$T,"A")+SUMIFS('Minuta MTA 2025 GR3'!$AF:$AF,'Minuta MTA 2025 GR3'!$AH:$AH,B$1,'Minuta MTA 2025 GR3'!$I:$I,$A6,'Minuta MTA 2025 GR3'!$T:$T,"B") -> #N/A | C6: =SUMIFS('Minuta MTA 2025 GR3'!$AF:$AF,'Minuta MTA 2025 GR3'!$AH:$AH,C$1,'Minuta MTA 2025 GR3'!$I:$I,$A6,'Minuta MTA 2025 GR3'!$T:$T,"A")+SUMIFS('Minuta MTA 2025 GR3'!$AF:$AF,'Minuta MTA 2025 GR3'!$AH:$AH,C$1,'Minuta MTA 2025 GR3'!$I:$I,$A6,'Minuta MTA 2025 GR3'!$T:$T,"B") -> #N/A | D6: =SUMIFS('Minuta MTA 2025 GR3'!$AF:$AF,'Minuta MTA 2025 GR3'!$AH:$AH,D$1,'Minuta MTA 2025 GR3'!$I:$I,$A6,'Minuta MTA 2025 GR3'!$T:$T,"A")+SUMIFS('Minuta MTA 2025 GR3'!$AF:$AF,'Minuta MTA 2025 GR3'!$AH:$AH,D$1,'Minuta MTA 2025 GR3'!$I:$I,$A6,'Minuta MTA 2025 GR3'!$T:$T,"B") -> #N/A | E6: =SUMIFS('Minuta MTA 2025 GR3'!$AF:$AF,'Minuta MTA 2025 GR3'!$AH:$AH,E$1,'Minuta MTA 2025 GR3'!$I:$I,$A6,'Minuta MTA 2025 GR3'!$T:$T,"A")+SUMIFS('Minuta MTA 2025 GR3'!$AF:$AF,'Minuta MTA 2025 GR3'!$AH:$AH,E$1,'Minuta MTA 2025 GR3'!$I:$I,$A6,'Minuta MTA 2025 GR3'!$T:$T,"B") -> #N/A | F6: =SUMIFS('Minuta MTA 2025 GR3'!$AF:$AF,'Minuta MTA 2025 GR3'!$AH:$AH,F$1,'Minuta MTA 2025 GR3'!$I:$I,$A6,'Minuta MTA 2025 GR3'!$T:$T,"A")+SUMIFS('Minuta MTA 2025 GR3'!$AF:$AF,'Minuta MTA 2025 GR3'!$AH:$AH,F$1,'Minuta MTA 2025 GR3'!$I:$I,$A6,'Minuta MTA 2025 GR3'!$T:$T,"B") -> #N/A | G6: =SUMIFS('Minuta MTA 2025 GR3'!$AF:$AF,'Minuta MTA 2025 GR3'!$AH:$AH,G$1,'Minuta MTA 2025 GR3'!$I:$I,$A6,'Minuta MTA 2025 GR3'!$T:$T,"A")+SUMIFS('Minuta MTA 2025 GR3'!$AF:$AF,'Minuta MTA 2025 GR3'!$AH:$AH,G$1,'Minuta MTA 2025 GR3'!$I:$I,$A6,'Minuta MTA 2025 GR3'!$T:$T,"B") -> #N/A | H6: =SUMIFS('Minuta MTA 2025 GR3'!$AF:$AF,'Minuta MTA 2025 GR3'!$AH:$AH,H$1,'Minuta MTA 2025 GR3'!$I:$I,$A6,'Minuta MTA 2025 GR3'!$T:$T,"A")+SUMIFS('Minuta MTA 2025 GR3'!$AF:$AF,'Minuta MTA 2025 GR3'!$AH:$AH,H$1,'Minuta MTA 2025 GR3'!$I:$I,$A6,'Minuta MTA 2025 GR3'!$T:$T,"B") -> #N/A | I6: =SUMIFS('Minuta MTA 2025 GR3'!$AF:$AF,'Minuta MTA 2025 GR3'!$AH:$AH,I$1,'Minuta MTA 2025 GR3'!$I:$I,$A6,'Minuta MTA 2025 GR3'!$T:$T,"A")+SUMIFS('Minuta MTA 2025 GR3'!$AF:$AF,'Minuta MTA 2025 GR3'!$AH:$AH,I$1,'Minuta MTA 2025 GR3'!$I:$I,$A6,'Minuta MTA 2025 GR3'!$T:$T,"B") -> #N/A | ... O6: =SUMIFS('Minuta MTA 2025 GR3'!$AF:$AF,'Minuta MTA 2025 GR3'!$AH:$AH,O$1,'Minuta MTA 2025 GR3'!$I:$I,$A6,'Minuta MTA 2025 GR3'!$T:$T,"A")+SUMIFS('Minuta MTA 2025 GR3'!$AF:$AF,'Minuta MTA 2025 GR3'!$AH:$AH,O$1,'Minuta MTA 2025 GR3'!$I:$I,$A6,'Minuta MTA 2025 GR3'!$T:$T,"B") -> #N/A | P6: =SUM(B6:O6) -> #N/A
A7: T-25 | B7: =SUMIFS('Minuta MTA 2025 GR3'!$AF:$AF,'Minuta MTA 2025 GR3'!$AH:$AH,B$1,'Minuta MTA 2025 GR3'!$I:$I,$A7,'Minuta MTA 2025 GR3'!$T:$T,"A")+SUMIFS('Minuta MTA 2025 GR3'!$AF:$AF,'Minuta MTA 2025 GR3'!$AH:$AH,B$1,'Minuta MTA 2025 GR3'!$I:$I,$A7,'Minuta MTA 2025 GR3'!$T:$T,"B") -> #N/A | C7: =SUMIFS('Minuta MTA 2025 GR3'!$AF:$AF,'Minuta MTA 2025 GR3'!$AH:$AH,C$1,'Minuta MTA 2025 GR3'!$I:$I,$A7,'Minuta MTA 2025 GR3'!$T:$T,"A")+SUMIFS('Minuta MTA 2025 GR3'!$AF:$AF,'Minuta MTA 2025 GR3'!$AH:$AH,C$1,'Minuta MTA 2025 GR3'!$I:$I,$A7,'Minuta MTA 2025 GR3'!$T:$T,"B") -> #N/A | D7: =SUMIFS('Minuta MTA 2025 GR3'!$AF:$AF,'Minuta MTA 2025 GR3'!$AH:$AH,D$1,'Minuta MTA 2025 GR3'!$I:$I,$A7,'Minuta MTA 2025 GR3'!$T:$T,"A")+SUMIFS('Minuta MTA 2025 GR3'!$AF:$AF,'Minuta MTA 2025 GR3'!$AH:$AH,D$1,'Minuta MTA 2025 GR3'!$I:$I,$A7,'Minuta MTA 2025 GR3'!$T:$T,"B") -> #N/A | E7: =SUMIFS('Minuta MTA 2025 GR3'!$AF:$AF,'Minuta MTA 2025 GR3'!$AH:$AH,E$1,'Minuta MTA 2025 GR3'!$I:$I,$A7,'Minuta MTA 2025 GR3'!$T:$T,"A")+SUMIFS('Minuta MTA 2025 GR3'!$AF:$AF,'Minuta MTA 2025 GR3'!$AH:$AH,E$1,'Minuta MTA 2025 GR3'!$I:$I,$A7,'Minuta MTA 2025 GR3'!$T:$T,"B") -> #N/A | F7: =SUMIFS('Minuta MTA 2025 GR3'!$AF:$AF,'Minuta MTA 2025 GR3'!$AH:$AH,F$1,'Minuta MTA 2025 GR3'!$I:$I,$A7,'Minuta MTA 2025 GR3'!$T:$T,"A")+SUMIFS('Minuta MTA 2025 GR3'!$AF:$AF,'Minuta MTA 2025 GR3'!$AH:$AH,F$1,'Minuta MTA 2025 GR3'!$I:$I,$A7,'Minuta MTA 2025 GR3'!$T:$T,"B") -> #N/A | G7: =SUMIFS('Minuta MTA 2025 GR3'!$AF:$AF,'Minuta MTA 2025 GR3'!$AH:$AH,G$1,'Minuta MTA 2025 GR3'!$I:$I,$A7,'Minuta MTA 2025 GR3'!$T:$T,"A")+SUMIFS('Minuta MTA 2025 GR3'!$AF:$AF,'Minuta MTA 2025 GR3'!$AH:$AH,G$1,'Minuta MTA 2025 GR3'!$I:$I,$A7,'Minuta MTA 2025 GR3'!$T:$T,"B") -> #N/A | H7: =SUMIFS('Minuta MTA 2025 GR3'!$AF:$AF,'Minuta MTA 2025 GR3'!$AH:$AH,H$1,'Minuta MTA 2025 GR3'!$I:$I,$A7,'Minuta MTA 2025 GR3'!$T:$T,"A")+SUMIFS('Minuta MTA 2025 GR3'!$AF:$AF,'Minuta MTA 2025 GR3'!$AH:$AH,H$1,'Minuta MTA 2025 GR3'!$I:$I,$A7,'Minuta MTA 2025 GR3'!$T:$T,"B") -> #N/A | I7: =SUMIFS('Minuta MTA 2025 GR3'!$AF:$AF,'Minuta MTA 2025 GR3'!$AH:$AH,I$1,'Minuta MTA 2025 GR3'!$I:$I,$A7,'Minuta MTA 2025 GR3'!$T:$T,"A")+SUMIFS('Minuta MTA 2025 GR3'!$AF:$AF,'Minuta MTA 2025 GR3'!$AH:$AH,I$1,'Minuta MTA 2025 GR3'!$I:$I,$A7,'Minuta MTA 2025 GR3'!$T:$T,"B") -> #N/A | ... O7: =SUMIFS('Minuta MTA 2025 GR3'!$AF:$AF,'Minuta MTA 2025 GR3'!$AH:$AH,O$1,'Minuta MTA 2025 GR3'!$I:$I,$A7,'Minuta MTA 2025 GR3'!$T:$T,"A")+SUMIFS('Minuta MTA 2025 GR3'!$AF:$AF,'Minuta MTA 2025 GR3'!$AH:$AH,O$1,'Minuta MTA 2025 GR3'!$I:$I,$A7,'Minuta MTA 2025 GR3'!$T:$T,"B") -> #N/A | P7: =SUM(B7:O7) -> #N/A
A8: G-19 | B8: =SUMIFS('Minuta MTA 2025 GR3'!$AF:$AF,'Minuta MTA 2025 GR3'!$AH:$AH,B$1,'Minuta MTA 2025 GR3'!$I:$I,$A8,'Minuta MTA 2025 GR3'!$T:$T,"A")+SUMIFS('Minuta MTA 2025 GR3'!$AF:$AF,'Minuta MTA 2025 GR3'!$AH:$AH,B$1,'Minuta MTA 2025 GR3'!$I:$I,$A8,'Minuta MTA 2025 GR3'!$T:$T,"B") -> #N/A | C8: =SUMIFS('Minuta MTA 2025 GR3'!$AF:$AF,'Minuta MTA 2025 GR3'!$AH:$AH,C$1,'Minuta MTA 2025 GR3'!$I:$I,$A8,'Minuta MTA 2025 GR3'!$T:$T,"A")+SUMIFS('Minuta MTA 2025 GR3'!$AF:$AF,'Minuta MTA 2025 GR3'!$AH:$AH,C$1,'Minuta MTA 2025 GR3'!$I:$I,$A8,'Minuta MTA 2025 GR3'!$T:$T,"B") -> #N/A | D8: =SUMIFS('Minuta MTA 2025 GR3'!$AF:$AF,'Minuta MTA 2025 GR3'!$AH:$AH,D$1,'Minuta MTA 2025 GR3'!$I:$I,$A8,'Minuta MTA 2025 GR3'!$T:$T,"A")+SUMIFS('Minuta MTA 2025 GR3'!$AF:$AF,'Minuta MTA 2025 GR3'!$AH:$AH,D$1,'Minuta MTA 2025 GR3'!$I:$I,$A8,'Minuta MTA 2025 GR3'!$T:$T,"B") -> #N/A | E8: =SUMIFS('Minuta MTA 2025 GR3'!$AF:$AF,'Minuta MTA 2025 GR3'!$AH:$AH,E$1,'Minuta MTA 2025 GR3'!$I:$I,$A8,'Minuta MTA 2025 GR3'!$T:$T,"A")+SUMIFS('Minuta MTA 2025 GR3'!$AF:$AF,'Minuta MTA 2025 GR3'!$AH:$AH,E$1,'Minuta MTA 2025 GR3'!$I:$I,$A8,'Minuta MTA 2025 GR3'!$T:$T,"B") -> #N/A | F8: =SUMIFS('Minuta MTA 2025 GR3'!$AF:$AF,'Minuta MTA 2025 GR3'!$AH:$AH,F$1,'Minuta MTA 2025 GR3'!$I:$I,$A8,'Minuta MTA 2025 GR3'!$T:$T,"A")+SUMIFS('Minuta MTA 2025 GR3'!$AF:$AF,'Minuta MTA 2025 GR3'!$AH:$AH,F$1,'Minuta MTA 2025 GR3'!$I:$I,$A8,'Minuta MTA 2025 GR3'!$T:$T,"B") -> #N/A | G8: =SUMIFS('Minuta MTA 2025 GR3'!$AF:$AF,'Minuta MTA 2025 GR3'!$AH:$AH,G$1,'Minuta MTA 2025 GR3'!$I:$I,$A8,'Minuta MTA 2025 GR3'!$T:$T,"A")+SUMIFS('Minuta MTA 2025 GR3'!$AF:$AF,'Minuta MTA 2025 GR3'!$AH:$AH,G$1,'Minuta MTA 2025 GR3'!$I:$I,$A8,'Minuta MTA 2025 GR3'!$T:$T,"B") -> #N/A | H8: =SUMIFS('Minuta MTA 2025 GR3'!$AF:$AF,'Minuta MTA 2025 GR3'!$AH:$AH,H$1,'Minuta MTA 2025 GR3'!$I:$I,$A8,'Minuta MTA 2025 GR3'!$T:$T,"A")+SUMIFS('Minuta MTA 2025 GR3'!$AF:$AF,'Minuta MTA 2025 GR3'!$AH:$AH,H$1,'Minuta MTA 2025 GR3'!$I:$I,$A8,'Minuta MTA 2025 GR3'!$T:$T,"B") -> #N/A | I8: =SUMIFS('Minuta MTA 2025 GR3'!$AF:$AF,'Minuta MTA 2025 GR3'!$AH:$AH,I$1,'Minuta MTA 2025 GR3'!$I:$I,$A8,'Minuta MTA 2025 GR3'!$T:$T,"A")+SUMIFS('Minuta MTA 2025 GR3'!$AF:$AF,'Minuta MTA 2025 GR3'!$AH:$AH,I$1,'Minuta MTA 2025 GR3'!$I:$I,$A8,'Minuta MTA 2025 GR3'!$T:$T,"B") -> #N/A | ... O8: =SUMIFS('Minuta MTA 2025 GR3'!$AF:$AF,'Minuta MTA 2025 GR3'!$AH:$AH,O$1,'Minuta MTA 2025 GR3'!$I:$I,$A8,'Minuta MTA 2025 GR3'!$T:$T,"A")+SUMIFS('Minuta MTA 2025 GR3'!$AF:$AF,'Minuta MTA 2025 GR3'!$AH:$AH,O$1,'Minuta MTA 2025 GR3'!$I:$I,$A8,'Minuta MTA 2025 GR3'!$T:$T,"B") -> #N/A | P8: =SUM(B8:O8) -> #N/A
A9: AD | B9: =SUMIFS('Minuta MTA 2025 GR3'!$AF:$AF,'Minuta MTA 2025 GR3'!$AH:$AH,B$1,'Minuta MTA 2025 GR3'!$I:$I,$A9,'Minuta MTA 2025 GR3'!$T:$T,"A")+SUMIFS('Minuta MTA 2025 GR3'!$AF:$AF,'Minuta MTA 2025 GR3'!$AH:$AH,B$1,'Minuta MTA 2025 GR3'!$I:$I,$A9,'Minuta MTA 2025 GR3'!$T:$T,"B") -> #N/A | C9: =SUMIFS('Minuta MTA 2025 GR3'!$AF:$AF,'Minuta MTA 2025 GR3'!$AH:$AH,C$1,'Minuta MTA 2025 GR3'!$I:$I,$A9,'Minuta MTA 2025 GR3'!$T:$T,"A")+SUMIFS('Minuta MTA 2025 GR3'!$AF:$AF,'Minuta MTA 2025 GR3'!$AH:$AH,C$1,'Minuta MTA 2025 GR3'!$I:$I,$A9,'Minuta MTA 2025 GR3'!$T:$T,"B") -> #N/A | D9: =SUMIFS('Minuta MTA 2025 GR3'!$AF:$AF,'Minuta MTA 2025 GR3'!$AH:$AH,D$1,'Minuta MTA 2025 GR3'!$I:$I,$A9,'Minuta MTA 2025 GR3'!$T:$T,"A")+SUMIFS('Minuta MTA 2025 GR3'!$AF:$AF,'Minuta MTA 2025 GR3'!$AH:$AH,D$1,'Minuta MTA 2025 GR3'!$I:$I,$A9,'Minuta MTA 2025 GR3'!$T:$T,"B") -> #N/A | E9: =SUMIFS('Minuta MTA 2025 GR3'!$AF:$AF,'Minuta MTA 2025 GR3'!$AH:$AH,E$1,'Minuta MTA 2025 GR3'!$I:$I,$A9,'Minuta MTA 2025 GR3'!$T:$T,"A")+SUMIFS('Minuta MTA 2025 GR3'!$AF:$AF,'Minuta MTA 2025 GR3'!$AH:$AH,E$1,'Minuta MTA 2025 GR3'!$I:$I,$A9,'Minuta MTA 2025 GR3'!$T:$T,"B") -> #N/A | F9: =SUMIFS('Minuta MTA 2025 GR3'!$AF:$AF,'Minuta MTA 2025 GR3'!$AH:$AH,F$1,'Minuta MTA 2025 GR3'!$I:$I,$A9,'Minuta MTA 2025 GR3'!$T:$T,"A")+SUMIFS('Minuta MTA 2025 GR3'!$AF:$AF,'Minuta MTA 2025 GR3'!$AH:$AH,F$1,'Minuta MTA 2025 GR3'!$I:$I,$A9,'Minuta MTA 2025 GR3'!$T:$T,"B") -> #N/A | G9: =SUMIFS('Minuta MTA 2025 GR3'!$AF:$AF,'Minuta MTA 2025 GR3'!$AH:$AH,G$1,'Minuta MTA 2025 GR3'!$I:$I,$A9,'Minuta MTA 2025 GR3'!$T:$T,"A")+SUMIFS('Minuta MTA 2025 GR3'!$AF:$AF,'Minuta MTA 2025 GR3'!$AH:$AH,G$1,'Minuta MTA 2025 GR3'!$I:$I,$A9,'Minuta MTA 2025 GR3'!$T:$T,"B") -> #N/A | H9: =SUMIFS('Minuta MTA 2025 GR3'!$AF:$AF,'Minuta MTA 2025 GR3'!$AH:$AH,H$1,'Minuta MTA 2025 GR3'!$I:$I,$A9,'Minuta MTA 2025 GR3'!$T:$T,"A")+SUMIFS('Minuta MTA 2025 GR3'!$AF:$AF,'Minuta MTA 2025 GR3'!$AH:$AH,H$1,'Minuta MTA 2025 GR3'!$I:$I,$A9,'Minuta MTA 2025 GR3'!$T:$T,"B") -> #N/A | I9: =SUMIFS('Minuta MTA 2025 GR3'!$AF:$AF,'Minuta MTA 2025 GR3'!$AH:$AH,I$1,'Minuta MTA 2025 GR3'!$I:$I,$A9,'Minuta MTA 2025 GR3'!$T:$T,"A")+SUMIFS('Minuta MTA 2025 GR3'!$AF:$AF,'Minuta MTA 2025 GR3'!$AH:$AH,I$1,'Minuta MTA 2025 GR3'!$I:$I,$A9,'Minuta MTA 2025 GR3'!$T:$T,"B") -> #N/A | ... O9: =SUMIFS('Minuta MTA 2025 GR3'!$AF:$AF,'Minuta MTA 2025 GR3'!$AH:$AH,O$1,'Minuta MTA 2025 GR3'!$I:$I,$A9,'Minuta MTA 2025 GR3'!$T:$T,"A")+SUMIFS('Minuta MTA 2025 GR3'!$AF:$AF,'Minuta MTA 2025 GR3'!$AH:$AH,O$1,'Minuta MTA 2025 GR3'!$I:$I,$A9,'Minuta MTA 2025 GR3'!$T:$T,"B") -> #N/A | P9: =SUM(B9:O9) -> #N/A
A10: IU-93 | B10: =SUMIFS('Minuta MTA 2025 GR3'!$AF:$AF,'Minuta MTA 2025 GR3'!$AH:$AH,B$1,'Minuta MTA 2025 GR3'!$I:$I,$A10,'Minuta MTA 2025 GR3'!$T:$T,"A")+SUMIFS('Minuta MTA 2025 GR3'!$AF:$AF,'Minuta MTA 2025 GR3'!$AH:$AH,B$1,'Minuta MTA 2025 GR3'!$I:$I,$A10,'Minuta MTA 2025 GR3'!$T:$T,"B") -> #N/A | C10: =SUMIFS('Minuta MTA 2025 GR3'!$AF:$AF,'Minuta MTA 2025 GR3'!$AH:$AH,C$1,'Minuta MTA 2025 GR3'!$I:$I,$A10,'Minuta MTA 2025 GR3'!$T:$T,"A")+SUMIFS('Minuta MTA 2025 GR3'!$AF:$AF,'Minuta MTA 2025 GR3'!$AH:$AH,C$1,'Minuta MTA 2025 GR3'!$I:$I,$A10,'Minuta MTA 2025 GR3'!$T:$T,"B") -> #N/A | D10: =SUMIFS('Minuta MTA 2025 GR3'!$AF:$AF,'Minuta MTA 2025 GR3'!$AH:$AH,D$1,'Minuta MTA 2025 GR3'!$I:$I,$A10,'Minuta MTA 2025 GR3'!$T:$T,"A")+SUMIFS('Minuta MTA 2025 GR3'!$AF:$AF,'Minuta MTA 2025 GR3'!$AH:$AH,D$1,'Minuta MTA 2025 GR3'!$I:$I,$A10,'Minuta MTA 2025 GR3'!$T:$T,"B") -> #N/A | E10: =SUMIFS('Minuta MTA 2025 GR3'!$AF:$AF,'Minuta MTA 2025 GR3'!$AH:$AH,E$1,'Minuta MTA 2025 GR3'!$I:$I,$A10,'Minuta MTA 2025 GR3'!$T:$T,"A")+SUMIFS('Minuta MTA 2025 GR3'!$AF:$AF,'Minuta MTA 2025 GR3'!$AH:$AH,E$1,'Minuta MTA 2025 GR3'!$I:$I,$A10,'Minuta MTA 2025 GR3'!$T:$T,"B") -> #N/A | F10: =SUMIFS('Minuta MTA 2025 GR3'!$AF:$AF,'Minuta MTA 2025 GR3'!$AH:$AH,F$1,'Minuta MTA 2025 GR3'!$I:$I,$A10,'Minuta MTA 2025 GR3'!$T:$T,"A")+SUMIFS('Minuta MTA 2025 GR3'!$AF:$AF,'Minuta MTA 2025 GR3'!$AH:$AH,F$1,'Minuta MTA 2025 GR3'!$I:$I,$A10,'Minuta MTA 2025 GR3'!$T:$T,"B") -> #N/A | G10: =SUMIFS('Minuta MTA 2025 GR3'!$AF:$AF,'Minuta MTA 2025 GR3'!$AH:$AH,G$1,'Minuta MTA 2025 GR3'!$I:$I,$A10,'Minuta MTA 2025 GR3'!$T:$T,"A")+SUMIFS('Minuta MTA 2025 GR3'!$AF:$AF,'Minuta MTA 2025 GR3'!$AH:$AH,G$1,'Minuta MTA 2025 GR3'!$I:$I,$A10,'Minuta MTA 2025 GR3'!$T:$T,"B") -> #N/A | H10: =SUMIFS('Minuta MTA 2025 GR3'!$AF:$AF,'Minuta MTA 2025 GR3'!$AH:$AH,H$1,'Minuta MTA 2025 GR3'!$I:$I,$A10,'Minuta MTA 2025 GR3'!$T:$T,"A")+SUMIFS('Minuta MTA 2025 GR3'!$AF:$AF,'Minuta MTA 2025 GR3'!$AH:$AH,H$1,'Minuta MTA 2025 GR3'!$I:$I,$A10,'Minuta MTA 2025 GR3'!$T:$T,"B") -> #N/A | I10: =SUMIFS('Minuta MTA 2025 GR3'!$AF:$AF,'Minuta MTA 2025 GR3'!$AH:$AH,I$1,'Minuta MTA 2025 GR3'!$I:$I,$A10,'Minuta MTA 2025 GR3'!$T:$T,"A")+SUMIFS('Minuta MTA 2025 GR3'!$AF:$AF,'Minuta MTA 2025 GR3'!$AH:$AH,I$1,'Minuta MTA 2025 GR3'!$I:$I,$A10,'Minuta MTA 2025 GR3'!$T:$T,"B") -> #N/A | ... O10: =SUMIFS('Minuta MTA 2025 GR3'!$AF:$AF,'Minuta MTA 2025 GR3'!$AH:$AH,O$1,'Minuta MTA 2025 GR3'!$I:$I,$A10,'Minuta MTA 2025 GR3'!$T:$T,"A")+SUMIFS('Minuta MTA 2025 GR3'!$AF:$AF,'Minuta MTA 2025 GR3'!$AH:$AH,O$1,'Minuta MTA 2025 GR3'!$I:$I,$A10,'Minuta MTA 2025 GR3'!$T:$T,"B") -> #N/A | P10: =SUM(B10:O10) -> #N/A
A11: SSS | B11: =SUMIFS('Minuta MTA 2025 GR3'!$AF:$AF,'Minuta MTA 2025 GR3'!$AH:$AH,B$1,'Minuta MTA 2025 GR3'!$I:$I,$A11,'Minuta MTA 2025 GR3'!$T:$T,"A")+SUMIFS('Minuta MTA 2025 GR3'!$AF:$AF,'Minuta MTA 2025 GR3'!$AH:$AH,B$1,'Minuta MTA 2025 GR3'!$I:$I,$A11,'Minuta MTA 2025 GR3'!$T:$T,"B") -> #N/A | C11: =SUMIFS('Minuta MTA 2025 GR3'!$AF:$AF,'Minuta MTA 2025 GR3'!$AH:$AH,C$1,'Minuta MTA 2025 GR3'!$I:$I,$A11,'Minuta MTA 2025 GR3'!$T:$T,"A")+SUMIFS('Minuta MTA 2025 GR3'!$AF:$AF,'Minuta MTA 2025 GR3'!$AH:$AH,C$1,'Minuta MTA 2025 GR3'!$I:$I,$A11,'Minuta MTA 2025 GR3'!$T:$T,"B") -> #N/A | D11: =SUMIFS('Minuta MTA 2025 GR3'!$AF:$AF,'Minuta MTA 2025 GR3'!$AH:$AH,D$1,'Minuta MTA 2025 GR3'!$I:$I,$A11,'Minuta MTA 2025 GR3'!$T:$T,"A")+SUMIFS('Minuta MTA 2025 GR3'!$AF:$AF,'Minuta MTA 2025 GR3'!$AH:$AH,D$1,'Minuta MTA 2025 GR3'!$I:$I,$A11,'Minuta MTA 2025 GR3'!$T:$T,"B") -> #N/A | E11: =SUMIFS('Minuta MTA 2025 GR3'!$AF:$AF,'Minuta MTA 2025 GR3'!$AH:$AH,E$1,'Minuta MTA 2025 GR3'!$I:$I,$A11,'Minuta MTA 2025 GR3'!$T:$T,"A")+SUMIFS('Minuta MTA 2025 GR3'!$AF:$AF,'Minuta MTA 2025 GR3'!$AH:$AH,E$1,'Minuta MTA 2025 GR3'!$I:$I,$A11,'Minuta MTA 2025 GR3'!$T:$T,"B") -> #N/A | F11: =SUMIFS('Minuta MTA 2025 GR3'!$AF:$AF,'Minuta MTA 2025 GR3'!$AH:$AH,F$1,'Minuta MTA 2025 GR3'!$I:$I,$A11,'Minuta MTA 2025 GR3'!$T:$T,"A")+SUMIFS('Minuta MTA 2025 GR3'!$AF:$AF,'Minuta MTA 2025 GR3'!$AH:$AH,F$1,'Minuta MTA 2025 GR3'!$I:$I,$A11,'Minuta MTA 2025 GR3'!$T:$T,"B") -> #N/A | G11: =SUMIFS('Minuta MTA 2025 GR3'!$AF:$AF,'Minuta MTA 2025 GR3'!$AH:$AH,G$1,'Minuta MTA 2025 GR3'!$I:$I,$A11,'Minuta MTA 2025 GR3'!$T:$T,"A")+SUMIFS('Minuta MTA 2025 GR3'!$AF:$AF,'Minuta MTA 2025 GR3'!$AH:$AH,G$1,'Minuta MTA 2025 GR3'!$I:$I,$A11,'Minuta MTA 2025 GR3'!$T:$T,"B") -> #N/A | H11: =SUMIFS('Minuta MTA 2025 GR3'!$AF:$AF,'Minuta MTA 2025 GR3'!$AH:$AH,H$1,'Minuta MTA 2025 GR3'!$I:$I,$A11,'Minuta MTA 2025 GR3'!$T:$T,"A")+SUMIFS('Minuta MTA 2025 GR3'!$AF:$AF,'Minuta MTA 2025 GR3'!$AH:$AH,H$1,'Minuta MTA 2025 GR3'!$I:$I,$A11,'Minuta MTA 2025 GR3'!$T:$T,"B") -> #N/A | I11: =SUMIFS('Minuta MTA 2025 GR3'!$AF:$AF,'Minuta MTA 2025 GR3'!$AH:$AH,I$1,'Minuta MTA 2025 GR3'!$I:$I,$A11,'Minuta MTA 2025 GR3'!$T:$T,"A")+SUMIFS('Minuta MTA 2025 GR3'!$AF:$AF,'Minuta MTA 2025 GR3'!$AH:$AH,I$1,'Minuta MTA 2025 GR3'!$I:$I,$A11,'Minuta MTA 2025 GR3'!$T:$T,"B") -> #N/A | ... O11: =SUMIFS('Minuta MTA 2025 GR3'!$AF:$AF,'Minuta MTA 2025 GR3'!$AH:$AH,O$1,'Minuta MTA 2025 GR3'!$I:$I,$A11,'Minuta MTA 2025 GR3'!$T:$T,"A")+SUMIFS('Minuta MTA 2025 GR3'!$AF:$AF,'Minuta MTA 2025 GR3'!$AH:$AH,O$1,'Minuta MTA 2025 GR3'!$I:$I,$A11,'Minuta MTA 2025 GR3'!$T:$T,"B") -> #N/A | P11: =SUM(B11:O11) -> #N/A
A12: PNEUS | B12: =SUMIFS('Minuta MTA 2025 GR3'!$AF:$AF,'Minuta MTA 2025 GR3'!$AH:$AH,B$1,'Minuta MTA 2025 GR3'!$I:$I,$A12,'Minuta MTA 2025 GR3'!$T:$T,"A")+SUMIFS('Minuta MTA 2025 GR3'!$AF:$AF,'Minuta MTA 2025 GR3'!$AH:$AH,B$1,'Minuta MTA 2025 GR3'!$I:$I,$A12,'Minuta MTA 2025 GR3'!$T:$T,"B") -> #N/A | C12: =SUMIFS('Minuta MTA 2025 GR3'!$AF:$AF,'Minuta MTA 2025 GR3'!$AH:$AH,C$1,'Minuta MTA 2025 GR3'!$I:$I,$A12,'Minuta MTA 2025 GR3'!$T:$T,"A")+SUMIFS('Minuta MTA 2025 GR3'!$AF:$AF,'Minuta MTA 2025 GR3'!$AH:$AH,C$1,'Minuta MTA 2025 GR3'!$I:$I,$A12,'Minuta MTA 2025 GR3'!$T:$T,"B") -> #N/A | D12: =SUMIFS('Minuta MTA 2025 GR3'!$AF:$AF,'Minuta MTA 2025 GR3'!$AH:$AH,D$1,'Minuta MTA 2025 GR3'!$I:$I,$A12,'Minuta MTA 2025 GR3'!$T:$T,"A")+SUMIFS('Minuta MTA 2025 GR3'!$AF:$AF,'Minuta MTA 2025 GR3'!$AH:$AH,D$1,'Minuta MTA 2025 GR3'!$I:$I,$A12,'Minuta MTA 2025 GR3'!$T:$T,"B") -> #N/A | E12: =SUMIFS('Minuta MTA 2025 GR3'!$AF:$AF,'Minuta MTA 2025 GR3'!$AH:$AH,E$1,'Minuta MTA 2025 GR3'!$I:$I,$A12,'Minuta MTA 2025 GR3'!$T:$T,"A")+SUMIFS('Minuta MTA 2025 GR3'!$AF:$AF,'Minuta MTA 2025 GR3'!$AH:$AH,E$1,'Minuta MTA 2025 GR3'!$I:$I,$A12,'Minuta MTA 2025 GR3'!$T:$T,"B") -> #N/A | F12: =SUMIFS('Minuta MTA 2025 GR3'!$AF:$AF,'Minuta MTA 2025 GR3'!$AH:$AH,F$1,'Minuta MTA 2025 GR3'!$I:$I,$A12,'Minuta MTA 2025 GR3'!$T:$T,"A")+SUMIFS('Minuta MTA 2025 GR3'!$AF:$AF,'Minuta MTA 2025 GR3'!$AH:$AH,F$1,'Minuta MTA 2025 GR3'!$I:$I,$A12,'Minuta MTA 2025 GR3'!$T:$T,"B") -> #N/A | G12: =SUMIFS('Minuta MTA 2025 GR3'!$AF:$AF,'Minuta MTA 2025 GR3'!$AH:$AH,G$1,'Minuta MTA 2025 GR3'!$I:$I,$A12,'Minuta MTA 2025 GR3'!$T:$T,"A")+SUMIFS('Minuta MTA 2025 GR3'!$AF:$AF,'Minuta MTA 2025 GR3'!$AH:$AH,G$1,'Minuta MTA 2025 GR3'!$I:$I,$A12,'Minuta MTA 2025 GR3'!$T:$T,"B") -> #N/A | H12: =SUMIFS('Minuta MTA 2025 GR3'!$AF:$AF,'Minuta MTA 2025 GR3'!$AH:$AH,H$1,'Minuta MTA 2025 GR3'!$I:$I,$A12,'Minuta MTA 2025 GR3'!$T:$T,"A")+SUMIFS('Minuta MTA 2025 GR3'!$AF:$AF,'Minuta MTA 2025 GR3'!$AH:$AH,H$1,'Minuta MTA 2025 GR3'!$I:$I,$A12,'Minuta MTA 2025 GR3'!$T:$T,"B") -> #N/A | I12: =SUMIFS('Minuta MTA 2025 GR3'!$AF:$AF,'Minuta MTA 2025 GR3'!$AH:$AH,I$1,'Minuta MTA 2025 GR3'!$I:$I,$A12,'Minuta MTA 2025 GR3'!$T:$T,"A")+SUMIFS('Minuta MTA 2025 GR3'!$AF:$AF,'Minuta MTA 2025 GR3'!$AH:$AH,I$1,'Minuta MTA 2025 GR3'!$I:$I,$A12,'Minuta MTA 2025 GR3'!$T:$T,"B") -> #N/A | ... O12: =SUMIFS('Minuta MTA 2025 GR3'!$AF:$AF,'Minuta MTA 2025 GR3'!$AH:$AH,O$1,'Minuta MTA 2025 GR3'!$I:$I,$A12,'Minuta MTA 2025 GR3'!$T:$T,"A")+SUMIFS('Minuta MTA 2025 GR3'!$AF:$AF,'Minuta MTA 2025 GR3'!$AH:$AH,O$1,'Minuta MTA 2025 GR3'!$I:$I,$A12,'Minuta MTA 2025 GR3'!$T:$T,"B") -> #N/A | P12: =SUM(B12:O12) -> #N/A
A13: GL | B13: =SUMIFS('Minuta MTA 2025 GR3'!$AF:$AF,'Minuta MTA 2025 GR3'!$AH:$AH,B$1,'Minuta MTA 2025 GR3'!$I:$I,$A13,'Minuta MTA 2025 GR3'!$T:$T,"A")+SUMIFS('Minuta MTA 2025 GR3'!$AF:$AF,'Minuta MTA 2025 GR3'!$AH:$AH,B$1,'Minuta MTA 2025 GR3'!$I:$I,$A13,'Minuta MTA 2025 GR3'!$T:$T,"B") -> #N/A | C13: =SUMIFS('Minuta MTA 2025 GR3'!$AF:$AF,'Minuta MTA 2025 GR3'!$AH:$AH,C$1,'Minuta MTA 2025 GR3'!$I:$I,$A13,'Minuta MTA 2025 GR3'!$T:$T,"A")+SUMIFS('Minuta MTA 2025 GR3'!$AF:$AF,'Minuta MTA 2025 GR3'!$AH:$AH,C$1,'Minuta MTA 2025 GR3'!$I:$I,$A13,'Minuta MTA 2025 GR3'!$T:$T,"B") -> #N/A | D13: =SUMIFS('Minuta MTA 2025 GR3'!$AF:$AF,'Minuta MTA 2025 GR3'!$AH:$AH,D$1,'Minuta MTA 2025 GR3'!$I:$I,$A13,'Minuta MTA 2025 GR3'!$T:$T,"A")+SUMIFS('Minuta MTA 2025 GR3'!$AF:$AF,'Minuta MTA 2025 GR3'!$AH:$AH,D$1,'Minuta MTA 2025 GR3'!$I:$I,$A13,'Minuta MTA 2025 GR3'!$T:$T,"B") -> #N/A | E13: =SUMIFS('Minuta MTA 2025 GR3'!$AF:$AF,'Minuta MTA 2025 GR3'!$AH:$AH,E$1,'Minuta MTA 2025 GR3'!$I:$I,$A13,'Minuta MTA 2025 GR3'!$T:$T,"A")+SUMIFS('Minuta MTA 2025 GR3'!$AF:$AF,'Minuta MTA 2025 GR3'!$AH:$AH,E$1,'Minuta MTA 2025 GR3'!$I:$I,$A13,'Minuta MTA 2025 GR3'!$T:$T,"B") -> #N/A | F13: =SUMIFS('Minuta MTA 2025 GR3'!$AF:$AF,'Minuta MTA 2025 GR3'!$AH:$AH,F$1,'Minuta MTA 2025 GR3'!$I:$I,$A13,'Minuta MTA 2025 GR3'!$T:$T,"A")+SUMIFS('Minuta MTA 2025 GR3'!$AF:$AF,'Minuta MTA 2025 GR3'!$AH:$AH,F$1,'Minuta MTA 2025 GR3'!$I:$I,$A13,'Minuta MTA 2025 GR3'!$T:$T,"B") -> #N/A | G13: =SUMIFS('Minuta MTA 2025 GR3'!$AF:$AF,'Minuta MTA 2025 GR3'!$AH:$AH,G$1,'Minuta MTA 2025 GR3'!$I:$I,$A13,'Minuta MTA 2025 GR3'!$T:$T,"A")+SUMIFS('Minuta MTA 2025 GR3'!$AF:$AF,'Minuta MTA 2025 GR3'!$AH:$AH,G$1,'Minuta MTA 2025 GR3'!$I:$I,$A13,'Minuta MTA 2025 GR3'!$T:$T,"B") -> #N/A | H13: =SUMIFS('Minuta MTA 2025 GR3'!$AF:$AF,'Minuta MTA 2025 GR3'!$AH:$AH,H$1,'Minuta MTA 2025 GR3'!$I:$I,$A13,'Minuta MTA 2025 GR3'!$T:$T,"A")+SUMIFS('Minuta MTA 2025 GR3'!$AF:$AF,'Minuta MTA 2025 GR3'!$AH:$AH,H$1,'Minuta MTA 2025 GR3'!$I:$I,$A13,'Minuta MTA 2025 GR3'!$T:$T,"B") -> #N/A | I13: =SUMIFS('Minuta MTA 2025 GR3'!$AF:$AF,'Minuta MTA 2025 GR3'!$AH:$AH,I$1,'Minuta MTA 2025 GR3'!$I:$I,$A13,'Minuta MTA 2025 GR3'!$T:$T,"A")+SUMIFS('Minuta MTA 2025 GR3'!$AF:$AF,'Minuta MTA 2025 GR3'!$AH:$AH,I$1,'Minuta MTA 2025 GR3'!$I:$I,$A13,'Minuta MTA 2025 GR3'!$T:$T,"B") -> #N/A | ... O13: =SUMIFS('Minuta MTA 2025 GR3'!$AF:$AF,'Minuta MTA 2025 GR3'!$AH:$AH,O$1,'Minuta MTA 2025 GR3'!$I:$I,$A13,'Minuta MTA 2025 GR3'!$T:$T,"A")+SUMIFS('Minuta MTA 2025 GR3'!$AF:$AF,'Minuta MTA 2025 GR3'!$AH:$AH,O$1,'Minuta MTA 2025 GR3'!$I:$I,$A13,'Minuta MTA 2025 GR3'!$T:$T,"B") -> #N/A | P13: =SUM(B13:O13) -> #N/A
A14: APOIO | B14: 0 | C14: 0 | D14: 0 | E14: 0 | F14: 4980250 | G14: 1282500 | H14: 1675000 | I14: 2052750 | J14: 2586500 | K14: 500000 | L14: 0 | M14: 0 | N14: 0 | O14: 0 | P14: =SUM(B14:O14) -> 13077000
A15: TOTAL | B15: =SUM(B2:B14) -> #N/A | C15: =SUM(C2:C14) -> #N/A | D15: =SUM(D2:D14) -> #N/A | E15: =SUM(E2:E14) -> #N/A | F15: =SUM(F2:F14) -> #N/A | G15: =SUM(G2:G14) -> #N/A | H15: =SUM(H2:H14) -> #N/A | I15: =SUM(I2:I14) -> #N/A | ... O15: =SUM(O2:O14) -> #N/A
A16: CÉLULA E RESTANTE (FORA MOTOR)
B17: 1 | C17: 2 | D17: 3 | E17: 4 | F17: 5 | G17: 6 | H17: 7 | I17: 8 | J17: 9 | K17: 10 | L17: 11 | M17: 12 | N17: 13 | O17: 14 | P17: TOTAL
A18: A-29 | B18: =SUMIFS('Minuta MTA 2025 GR3'!$AF:$AF,'Minuta MTA 2025 GR3'!$AH:$AH,B$1,'Minuta MTA 2025 GR3'!$I:$I,$A18,'Minuta MTA 2025 GR3'!$T:$T,"A",'Minuta MTA 2025 GR3'!$AC:$AC,"")+SUMIFS('Minuta MTA 2025 GR3'!$AF:$AF,'Minuta MTA 2025 GR3'!$AH:$AH,B$1,'Minuta MTA 2025 GR3'!$I:$I,$A18,'Minuta MTA 2025 GR3'!$T:$T,"B",'Minuta MTA 2025 GR3'!$AC:$AC,"") -> #N/A | C18: =SUMIFS('Minuta MTA 2025 GR3'!$AF:$AF,'Minuta MTA 2025 GR3'!$AH:$AH,C$1,'Minuta MTA 2025 GR3'!$I:$I,$A18,'Minuta MTA 2025 GR3'!$T:$T,"A",'Minuta MTA 2025 GR3'!$AC:$AC,"")+SUMIFS('Minuta MTA 2025 GR3'!$AF:$AF,'Minuta MTA 2025 GR3'!$AH:$AH,C$1,'Minuta MTA 2025 GR3'!$I:$I,$A18,'Minuta MTA 2025 GR3'!$T:$T,"B",'Minuta MTA 2025 GR3'!$AC:$AC,"") -> #N/A | D18: =SUMIFS('Minuta MTA 2025 GR3'!$AF:$AF,'Minuta MTA 2025 GR3'!$AH:$AH,D$1,'Minuta MTA 2025 GR3'!$I:$I,$A18,'Minuta MTA 2025 GR3'!$T:$T,"A",'Minuta MTA 2025 GR3'!$AC:$AC,"")+SUMIFS('Minuta MTA 2025 GR3'!$AF:$AF,'Minuta MTA 2025 GR3'!$AH:$AH,D$1,'Minuta MTA 2025 GR3'!$I:$I,$A18,'Minuta MTA 2025 GR3'!$T:$T,"B",'Minuta MTA 2025 GR3'!$AC:$AC,"") -> #N/A | E18: =SUMIFS('Minuta MTA 2025 GR3'!$AF:$AF,'Minuta MTA 2025 GR3'!$AH:$AH,E$1,'Minuta MTA 2025 GR3'!$I:$I,$A18,'Minuta MTA 2025 GR3'!$T:$T,"A",'Minuta MTA 2025 GR3'!$AC:$AC,"")+SUMIFS('Minuta MTA 2025 GR3'!$AF:$AF,'Minuta MTA 2025 GR3'!$AH:$AH,E$1,'Minuta MTA 2025 GR3'!$I:$I,$A18,'Minuta MTA 2025 GR3'!$T:$T,"B",'Minuta MTA 2025 GR3'!$AC:$AC,"") -> #N/A | F18: =SUMIFS('Minuta MTA 2025 GR3'!$AF:$AF,'Minuta MTA 2025 GR3'!$AH:$AH,F$1,'Minuta MTA 2025 GR3'!$I:$I,$A18,'Minuta MTA 2025 GR3'!$T:$T,"A",'Minuta MTA 2025 GR3'!$AC:$AC,"")+SUMIFS('Minuta MTA 2025 GR3'!$AF:$AF,'Minuta MTA 2025 GR3'!$AH:$AH,F$1,'Minuta MTA 2025 GR3'!$I:$I,$A18,'Minuta MTA 2025 GR3'!$T:$T,"B",'Minuta MTA 2025 GR3'!$AC:$AC,"") -> #N/A | G18: =SUMIFS('Minuta MTA 2025 GR3'!$AF:$AF,'Minuta MTA 2025 GR3'!$AH:$AH,G$1,'Minuta MTA 2025 GR3'!$I:$I,$A18,'Minuta MTA 2025 GR3'!$T:$T,"A",'Minuta MTA 2025 GR3'!$AC:$AC,"")+SUMIFS('Minuta MTA 2025 GR3'!$AF:$AF,'Minuta MTA 2025 GR3'!$AH:$AH,G$1,'Minuta MTA 2025 GR3'!$I:$I,$A18,'Minuta MTA 2025 GR3'!$T:$T,"B",'Minuta MTA 2025 GR3'!$AC:$AC,"") -> #N/A | H18: =SUMIFS('Minuta MTA 2025 GR3'!$AF:$AF,'Minuta MTA 2025 GR3'!$AH:$AH,H$1,'Minuta MTA 2025 GR3'!$I:$I,$A18,'Minuta MTA 2025 GR3'!$T:$T,"A",'Minuta MTA 2025 GR3'!$AC:$AC,"")+SUMIFS('Minuta MTA 2025 GR3'!$AF:$AF,'Minuta MTA 2025 GR3'!$AH:$AH,H$1,'Minuta MTA 2025 GR3'!$I:$I,$A18,'Minuta MTA 2025 GR3'!$T:$T,"B",'Minuta MTA 2025 GR3'!$AC:$AC,"") -> #N/A | I18: =SUMIFS('Minuta MTA 2025 GR3'!$AF:$AF,'Minuta MTA 2025 GR3'!$AH:$AH,I$1,'Minuta MTA 2025 GR3'!$I:$I,$A18,'Minuta MTA 2025 GR3'!$T:$T,"A",'Minuta MTA 2025 GR3'!$AC:$AC,"")+SUMIFS('Minuta MTA 2025 GR3'!$AF:$AF,'Minuta MTA 2025 GR3'!$AH:$AH,I$1,'Minuta MTA 2025 GR3'!$I:$I,$A18,'Minuta MTA 2025 GR3'!$T:$T,"B",'Minuta MTA 2025 GR3'!$AC:$AC,"") -> #N/A | ... O18: =SUMIFS('Minuta MTA 2025 GR3'!$AF:$AF,'Minuta MTA 2025 GR3'!$AH:$AH,O$1,'Minuta MTA 2025 GR3'!$I:$I,$A18,'Minuta MTA 2025 GR3'!$T:$T,"A",'Minuta MTA 2025 GR3'!$AC:$AC,"")+SUMIFS('Minuta MTA 2025 GR3'!$AF:$AF,'Minuta MTA 2025 GR3'!$AH:$AH,O$1,'Minuta MTA 2025 GR3'!$I:$I,$A18,'Minuta MTA 2025 GR3'!$T:$T,"B",'Minuta MTA 2025 GR3'!$AC:$AC,"") -> #N/A | P18: =SUM(B18:O18) -> #N/A
A19: C-95 | B19: =SUMIFS('Minuta MTA 2025 GR3'!$AF:$AF,'Minuta MTA 2025 GR3'!$AH:$AH,B$1,'Minuta MTA 2025 GR3'!$I:$I,$A19,'Minuta MTA 2025 GR3'!$T:$T,"A",'Minuta MTA 2025 GR3'!$AC:$AC,"")+SUMIFS('Minuta MTA 2025 GR3'!$AF:$AF,'Minuta MTA 2025 GR3'!$AH:$AH,B$1,'Minuta MTA 2025 GR3'!$I:$I,$A19,'Minuta MTA 2025 GR3'!$T:$T,"B",'Minuta MTA 2025 GR3'!$AC:$AC,"") -> #N/A | C19: =SUMIFS('Minuta MTA 2025 GR3'!$AF:$AF,'Minuta MTA 2025 GR3'!$AH:$AH,C$1,'Minuta MTA 2025 GR3'!$I:$I,$A19,'Minuta MTA 2025 GR3'!$T:$T,"A",'Minuta MTA 2025 GR3'!$AC:$AC,"")+SUMIFS('Minuta MTA 2025 GR3'!$AF:$AF,'Minuta MTA 2025 GR3'!$AH:$AH,C$1,'Minuta MTA 2025 GR3'!$I:$I,$A19,'Minuta MTA 2025 GR3'!$T:$T,"B",'Minuta MTA 2025 GR3'!$AC:$AC,"") -> #N/A | D19: =SUMIFS('Minuta MTA 2025 GR3'!$AF:$AF,'Minuta MTA 2025 GR3'!$AH:$AH,D$1,'Minuta MTA 2025 GR3'!$I:$I,$A19,'Minuta MTA 2025 GR3'!$T:$T,"A",'Minuta MTA 2025 GR3'!$AC:$AC,"")+SUMIFS('Minuta MTA 2025 GR3'!$AF:$AF,'Minuta MTA 2025 GR3'!$AH:$AH,D$1,'Minuta MTA 2025 GR3'!$I:$I,$A19,'Minuta MTA 2025 GR3'!$T:$T,"B",'Minuta MTA 2025 GR3'!$AC:$AC,"") -> #N/A | E19: =SUMIFS('Minuta MTA 2025 GR3'!$AF:$AF,'Minuta MTA 2025 GR3'!$AH:$AH,E$1,'Minuta MTA 2025 GR3'!$I:$I,$A19,'Minuta MTA 2025 GR3'!$T:$T,"A",'Minuta MTA 2025 GR3'!$AC:$AC,"")+SUMIFS('Minuta MTA 2025 GR3'!$AF:$AF,'Minuta MTA 2025 GR3'!$AH:$AH,E$1,'Minuta MTA 2025 GR3'!$I:$I,$A19,'Minuta MTA 2025 GR3'!$T:$T,"B",'Minuta MTA 2025 GR3'!$AC:$AC,"") -> #N/A | F19: =SUMIFS('Minuta MTA 2025 GR3'!$AF:$AF,'Minuta MTA 2025 GR3'!$AH:$AH,F$1,'Minuta MTA 2025 GR3'!$I:$I,$A19,'Minuta MTA 2025 GR3'!$T:$T,"A",'Minuta MTA 2025 GR3'!$AC:$AC,"")+SUMIFS('Minuta MTA 2025 GR3'!$AF:$AF,'Minuta MTA 2025 GR3'!$AH:$AH,F$1,'Minuta MTA 2025 GR3'!$I:$I,$A19,'Minuta MTA 2025 GR3'!$T:$T,"B",'Minuta MTA 2025 GR3'!$AC:$AC,"") -> #N/A | G19: =SUMIFS('Minuta MTA 2025 GR3'!$AF:$AF,'Minuta MTA 2025 GR3'!$AH:$AH,G$1,'Minuta MTA 2025 GR3'!$I:$I,$A19,'Minuta MTA 2025 GR3'!$T:$T,"A",'Minuta MTA 2025 GR3'!$AC:$AC,"")+SUMIFS('Minuta MTA 2025 GR3'!$AF:$AF,'Minuta MTA 2025 GR3'!$AH:$AH,G$1,'Minuta MTA 2025 GR3'!$I:$I,$A19,'Minuta MTA 2025 GR3'!$T:$T,"B",'Minuta MTA 2025 GR3'!$AC:$AC,"") -> #N/A | H19: =SUMIFS('Minuta MTA 2025 GR3'!$AF:$AF,'Minuta MTA 2025 GR3'!$AH:$AH,H$1,'Minuta MTA 2025 GR3'!$I:$I,$A19,'Minuta MTA 2025 GR3'!$T:$T,"A",'Minuta MTA 2025 GR3'!$AC:$AC,"")+SUMIFS('Minuta MTA 2025 GR3'!$AF:$AF,'Minuta MTA 2025 GR3'!$AH:$AH,H$1,'Minuta MTA 2025 GR3'!$I:$I,$A19,'Minuta MTA 2025 GR3'!$T:$T,"B",'Minuta MTA 2025 GR3'!$AC:$AC,"") -> #N/A | I19: =SUMIFS('Minuta MTA 2025 GR3'!$AF:$AF,'Minuta MTA 2025 GR3'!$AH:$AH,I$1,'Minuta MTA 2025 GR3'!$I:$I,$A19,'Minuta MTA 2025 GR3'!$T:$T,"A",'Minuta MTA 2025 GR3'!$AC:$AC,"")+SUMIFS('Minuta MTA 2025 GR3'!$AF:$AF,'Minuta MTA 2025 GR3'!$AH:$AH,I$1,'Minuta MTA 2025 GR3'!$I:$I,$A19,'Minuta MTA 2025 GR3'!$T:$T,"B",'Minuta MTA 2025 GR3'!$AC:$AC,"") -> #N/A | ... O19: =SUMIFS('Minuta MTA 2025 GR3'!$AF:$AF,'Minuta MTA 2025 GR3'!$AH:$AH,O$1,'Minuta MTA 2025 GR3'!$I:$I,$A19,'Minuta MTA 2025 GR3'!$T:$T,"A",'Minuta MTA 2025 GR3'!$AC:$AC,"")+SUMIFS('Minuta MTA 2025 GR3'!$AF:$AF,'Minuta MTA 2025 GR3'!$AH:$AH,O$1,'Minuta MTA 2025 GR3'!$I:$I,$A19,'Minuta MTA 2025 GR3'!$T:$T,"B",'Minuta MTA 2025 GR3'!$AC:$AC,"") -> #N/A | P19: =SUM(B19:O19) -> #N/A
A20: C-97 | B20: =SUMIFS('Minuta MTA 2025 GR3'!$AF:$AF,'Minuta MTA 2025 GR3'!$AH:$AH,B$1,'Minuta MTA 2025 GR3'!$I:$I,$A20,'Minuta MTA 2025 GR3'!$T:$T,"A",'Minuta MTA 2025 GR3'!$AC:$AC,"")+SUMIFS('Minuta MTA 2025 GR3'!$AF:$AF,'Minuta MTA 2025 GR3'!$AH:$AH,B$1,'Minuta MTA 2025 GR3'!$I:$I,$A20,'Minuta MTA 2025 GR3'!$T:$T,"B",'Minuta MTA 2025 GR3'!$AC:$AC,"") -> #N/A | C20: =SUMIFS('Minuta MTA 2025 GR3'!$AF:$AF,'Minuta MTA 2025 GR3'!$AH:$AH,C$1,'Minuta MTA 2025 GR3'!$I:$I,$A20,'Minuta MTA 2025 GR3'!$T:$T,"A",'Minuta MTA 2025 GR3'!$AC:$AC,"")+SUMIFS('Minuta MTA 2025 GR3'!$AF:$AF,'Minuta MTA 2025 GR3'!$AH:$AH,C$1,'Minuta MTA 2025 GR3'!$I:$I,$A20,'Minuta MTA 2025 GR3'!$T:$T,"B",'Minuta MTA 2025 GR3'!$AC:$AC,"") -> #N/A | D20: =SUMIFS('Minuta MTA 2025 GR3'!$AF:$AF,'Minuta MTA 2025 GR3'!$AH:$AH,D$1,'Minuta MTA 2025 GR3'!$I:$I,$A20,'Minuta MTA 2025 GR3'!$T:$T,"A",'Minuta MTA 2025 GR3'!$AC:$AC,"")+SUMIFS('Minuta MTA 2025 GR3'!$AF:$AF,'Minuta MTA 2025 GR3'!$AH:$AH,D$1,'Minuta MTA 2025 GR3'!$I:$I,$A20,'Minuta MTA 2025 GR3'!$T:$T,"B",'Minuta MTA 2025 GR3'!$AC:$AC,"") -> #N/A | E20: =SUMIFS('Minuta MTA 2025 GR3'!$AF:$AF,'Minuta MTA 2025 GR3'!$AH:$AH,E$1,'Minuta MTA 2025 GR3'!$I:$I,$A20,'Minuta MTA 2025 GR3'!$T:$T,"A",'Minuta MTA 2025 GR3'!$AC:$AC,"")+SUMIFS('Minuta MTA 2025 GR3'!$AF:$AF,'Minuta MTA 2025 GR3'!$AH:$AH,E$1,'Minuta MTA 2025 GR3'!$I:$I,$A20,'Minuta MTA 2025 GR3'!$T:$T,"B",'Minuta MTA 2025 GR3'!$AC:$AC,"") -> #N/A | F20: =SUMIFS('Minuta MTA 2025 GR3'!$AF:$AF,'Minuta MTA 2025 GR3'!$AH:$AH,F$1,'Minuta MTA 2025 GR3'!$I:$I,$A20,'Minuta MTA 2025 GR3'!$T:$T,"A",'Minuta MTA 2025 GR3'!$AC:$AC,"")+SUMIFS('Minuta MTA 2025 GR3'!$AF:$AF,'Minuta MTA 2025 GR3'!$AH:$AH,F$1,'Minuta MTA 2025 GR3'!$I:$I,$A20,'Minuta MTA 2025 GR3'!$T:$T,"B",'Minuta MTA 2025 GR3'!$AC:$AC,"") -> #N/A | G20: =SUMIFS('Minuta MTA 2025 GR3'!$AF:$AF,'Minuta MTA 2025 GR3'!$AH:$AH,G$1,'Minuta MTA 2025 GR3'!$I:$I,$A20,'Minuta MTA 2025 GR3'!$T:$T,"A",'Minuta MTA 2025 GR3'!$AC:$AC,"")+SUMIFS('Minuta MTA 2025 GR3'!$AF:$AF,'Minuta MTA 2025 GR3'!$AH:$AH,G$1,'Minuta MTA 2025 GR3'!$I:$I,$A20,'Minuta MTA 2025 GR3'!$T:$T,"B",'Minuta MTA 2025 GR3'!$AC:$AC,"") -> #N/A | H20: =SUMIFS('Minuta MTA 2025 GR3'!$AF:$AF,'Minuta MTA 2025 GR3'!$AH:$AH,H$1,'Minuta MTA 2025 GR3'!$I:$I,$A20,'Minuta MTA 2025 GR3'!$T:$T,"A",'Minuta MTA 2025 GR3'!$AC:$AC,"")+SUMIFS('Minuta MTA 2025 GR3'!$AF:$AF,'Minuta MTA 2025 GR3'!$AH:$AH,H$1,'Minuta MTA 2025 GR3'!$I:$I,$A20,'Minuta MTA 2025 GR3'!$T:$T,"B",'Minuta MTA 2025 GR3'!$AC:$AC,"") -> #N/A | I20: =SUMIFS('Minuta MTA 2025 GR3'!$AF:$AF,'Minuta MTA 2025 GR3'!$AH:$AH,I$1,'Minuta MTA 2025 GR3'!$I:$I,$A20,'Minuta MTA 2025 GR3'!$T:$T,"A",'Minuta MTA 2025 GR3'!$AC:$AC,"")+SUMIFS('Minuta MTA 2025 GR3'!$AF:$AF,'Minuta MTA 2025 GR3'!$AH:$AH,I$1,'Minuta MTA 2025 GR3'!$I:$I,$A20,'Minuta MTA 2025 GR3'!$T:$T,"B",'Minuta MTA 2025 GR3'!$AC:$AC,"") -> #N/A | ... O20: =SUMIFS('Minuta MTA 2025 GR3'!$AF:$AF,'Minuta MTA 2025 GR3'!$AH:$AH,O$1,'Minuta MTA 2025 GR3'!$I:$I,$A20,'Minuta MTA 2025 GR3'!$T:$T,"A",'Minuta MTA 2025 GR3'!$AC:$AC,"")+SUMIFS('Minuta MTA 2025 GR3'!$AF:$AF,'Minuta MTA 2025 GR3'!$AH:$AH,O$1,'Minuta MTA 2025 GR3'!$I:$I,$A20,'Minuta MTA 2025 GR3'!$T:$T,"B",'Minuta MTA 2025 GR3'!$AC:$AC,"") -> #N/A | P20: =SUM(B20:O20) -> #N/A
